Workbook

Sheet ReadMe
A1: CNQ investigation workbook
A2: FTO2 / Airbus Electric Center, quality. Built 19 October 2026.
A4: Two calculations
A5: 1. NC cost of non-quality: one cost per NC (level 3 of the CNQ model). The operator's aléa that leads to an NC is part of it (the 30-min alert step).
A6: 2. Disruption block, shown beside it and never added inside it: quality aléas that did not lead to an NC (option B), plus other-kind aléas you decide count as quality (M1).
A8: How to use
A9: Start with the Checklist tab: one line per check, priority, question, where to look, and a link to its tab. Each tab lists the orders, NCs or aléas to look at.
A10: Yellow cells (blue text) are yours to fill: Y / N answers, findings, figures you find. Totals and the Figures tab recalculate from them.
A11: Example: in D_Block, an aléa whose NC was written by ERMA gets N in 'Keep in block?'; the block total in Figures drops by its hours.
A12: Example: in H3, typing 3 in 'Repair hours at the customer' replaces the model's rework for that return by 3 h x the rate in Figures!C4.
A14: Sources
A15: Work orders: SAP operations confirmed 1 Sep - 1 Oct 2026 (order type S03 = rework orders). Planned time = standard value in IM (1/100 h); confirmed times equal planned for 98% of operations.
... A18: CNQ model: cnq_handoever, version cnq-2026.10.19. Scripts that rebuild every list: 07_scripts/wo_disruption (build_checklist.py builds this file).

Sheet Checklist
A1: CNQ investigation checklist
A2: Built 19 October 2026 from the work orders (Sept 2026), the MES disruptions (Jan-Sep 2026) and the NC files (2025, 2026). One line per check; each has its own tab.
A4: Yellow cells are yours to fill (Status, Finding, Decision here; the yellow columns in each tab). Example of a filled line: Status 'Done' · Finding 'Orders are created by support without times when the rework is done by the test team' · Decision 'Use the model for orders with no time'.
A6: ID | B6: Priority | C6: Check | D6: What we know | E6: Question to answer | F6: Where to look / who to ask | G6: Tab | H6: Status | I6: Finding | J6: Decision
A7: H1 | B7: High | C7: Rework done without an NC (shop floor) | D7: 105 rework orders, about 181 planned h in September, no NC behind them: quality-team time, cable cutting, rework after test with no NC, cable / label remakes with no NC reference, formboard checks. | E7: Which are non-quality? Which should have had an NC? | F7: Rework order texts in SAP; line leaders; quality | G7: H1_ReworkNoNC | H7: To do
A8: H2 | B8: High | C8: Quality team time booked on rework orders | D8: 2 orders, 70.5 h in September (A350 and A330 lines), incl. 15 h 'Gestion NC retours clients + analyse' and 4 h 'Alerte qualité'. | E8: Monthly? Which hours are NC handling? Overlap with the model's writing / support steps? | F8: Quality line managers (4QEH5I07, 4QEH1I07); SAP orders | G8: H2_QualityTime | H8: To do
A9: H3 | B9: High | C9: Customer returns: actual cost incl. work at the customer | D9: 69 returns in 2026, model cost about 10,250 EUR. Repair happens at the customer (FNZ1 kits, FFF1 via REC orders); analysis, transport, penalties not counted. | E9: Repair hours at the customer, analysis hours, transport / kits, penalties. Put the customer's alert back? | F9: Quality (customer returns), TOF / FNZ1 / FFF1 contacts, REC | G9: H3_CustomerReturns | H9: To do
A10: H4 | B10: High | C10: BF24 / BF20 cable cutting for stock | D10: 37 orders, 78 h, 2,600 cables cut in September for the PTVU line, after disruptions on Elec ABC quantities and missing BF24. | E10: Non-quality, or a definition / kitting problem? | F10: Methods (Elec ABC), A330 print room, PTVU line leader | G10: H4_CableCutting | H10: To do
A11: H5 | B11: High | C11: Reworked NCs with no rework order | D11: 47 NCs (2026 and 2025) decided 'rework' with nothing in linked_document. | E11: Fixed on the spot, or an order that was never linked? | F11: SAP: NC and orders on the same work order / MSN | G11: H5_NCsNoOrder | H11: To do
A12: H6 | B12: High | C12: Rework orders with no planned time | D12: 79 of 614 rework orders in September have no standard value (63 of 249 on the shop floor). | E12: Why no time? How should those NCs be costed? | F12: Methods / technical support who create the orders | G12: H6_OrdersNoTime | H12: To do
A13: H7 | B13: High | C13: Disruption export complete? | D13: Exactly 2,500 rows, newest first, 5 Jan 08:57 to 30 Sep 23:31. Starts on the plant's restart day, so probably complete. | E13: Re-export Jan-Mar and compare 5 January; look for a row limit. | F13: Skywise / Contour export; MES | G13: H7_DisruptExport | H13: To do
A14: M1 | B14: Medium | C14: Other aléas that look like quality | D14: 107 logistics / work-order / line aléas whose text reads like a quality problem, in 5 groups. | E14: Yes / no per group (no need to read them all). | F14: This workbook | G14: M1_QualityLike | H14: To do
A15: M4 | B15: Medium | C15: ERMA aléas inside the disruption block | D15: 19 of the 108 'no NC' quality aléas are on the MIP / 1101VB, where ERMA writes NCs. Their NC may exist but be excluded with ERMA. | E15: Put N in D_Block for those that have an ERMA NC. | F15: Skywise NCs on the same work order | G15: D_Block | H15: To do
A16: M2 | B16: Medium | C16: Rework orders naming NCs we do not have | D16: 40 orders, about 27 h, name 2026 NCs that are not in our exports. | E16: Plant / liability / writer of those NCs: out of scope, or missing from the export? | F16: Skywise NC lookup | G16: M2_NCsNotHeld | H16: To do
A17: M3 | B17: Medium | C17: Exceptional NCs (not for the presentation) | D17: 4 NCs where the order plans far more than the model, e.g. 34 h of cable reprinting on one NC line. | E17: Is the planned time right? Should such NCs be costed from their order? | F17: You | G17: M3_Exceptional | H17: To do
A18: L1 | B18: Low | C18: MSN 700/701 work (IEVB) | D18: 74 orders, 217 h in September, flight-test installation work. | E18: Confirm out of scope. | F18: Flight-test / IEV team | G18: Later | H18: To do
A19: L2 | B19: Low | C19: Change 5 kept for later | D19: Two defect classes missing from the time table (about 0 EUR). | E19: Apply when convenient. | F19: - | G19: Later | H19: To do
A21: Progress | C21: =COUNTIF(H7:H19,"Done")&" done, "&COUNTIF(H7:H19,"In progress")&" in progress, "&COUNTIF(H7:H19,"To do")&" to do" -> 0 done, 0 in progress, 13 to do

Sheet Figures
A1: CNQ figures as of 19 October 2026
A2: Model cnq-2026.10.19 (alert only when an operator raises one; connection errors 35 then 15 min; internal NCs x 2). Blue = values from the analysis, black = formulas.
A4: Hourly rate used for hours (EUR/h) | C4: 50 | D4: Official France rate used by the CNQ model (RATE_STANDARD). Change it here and every EUR figure in this workbook follows.
A6: 1. NC cost of non-quality (level 3)
A7: Pack reference data, 5 Jan - 6 Jul 2026 (595 NCs) | C7: 121503 | D7: cnq_handoever/tests/expected_totals.json (parser v4.7 data)
A8: 2026 Feb-Sep, raised at FTO2 (695 NCs) | C8: 142151 | D8: Parser v4.8 on the dashboard export + missing IDs; January left out (export cut)
A9: 2025 Jan-Dec, raised at FTO2, without ERMA (818 NCs) | C9: 168633 | D9: 2025 NC file; ERMA NCs left out to match the 2026 pipeline
A10: Customer returns 2026, Jan-Sep (69 NCs), model today | C10: 10250 | D10: Raised at other plants, FTO2 liable; see H3 for the actual cost
A11: Customer returns 2026 with the findings entered in H3 | C11: =H3_CustomerReturns!$R$77 -> 10250 | D11: Follows H3 'Cost with findings'
A13: 2. Disruption block (option B): quality aléas with no NC
A14: Declared quality aléas kept (D_Block), Jan-Sep 2026: hours lost | C14: =SUMIFS(D_Block!$G$7:$G$114,D_Block!$K$7:$K$114,"<>N")/60 -> 91.2
A15: of which Feb-Sep (same period as the 2026 NC cost) | C15: =SUMIFS(D_Block!$G$7:$G$114,D_Block!$K$7:$K$114,"<>N",D_Block!$C$7:$C$114,">=202602")/60 -> 64.933333
A16: Other-kind aléas counted as quality (M1 groups marked Y): hours lost | C16: =SUMIFS(M1_QualityLike!$F$16:$F$122,M1_QualityLike!$I$16:$I$122,"Y")/60 -> 0
A17: Disruption block, Jan-Sep 2026 (EUR) | C17: =(C14+C16)*Figures!$C$4 -> 4560 | D17: Hours lost x rate. Shown beside the NC cost, never added inside it.
A19: 3. Known, not counted (scope or under investigation)
A20: REC rework orders at the FAL, September 2026: planned hours | C20: 746 | D20: Out of scope as decided (REC)
A21: in EUR | C21: =C20*Figures!$C$4 -> 37300
A22: ERMA NCs 2025, FTO2 liable (184 NCs): level 3 EUR | C22: 44472 | D22: Out of scope as decided (ERMA); new model
A23: Shop-floor rework with no NC, September 2026: planned hours (H1) | C23: =H1_ReworkNoNC!$E$112 -> 180.76 | D23: Under investigation (H1)
A24: of which marked non-quality in H1: hours | C24: =SUMIFS(H1_ReworkNoNC!$E$7:$E$111,H1_ReworkNoNC!$I$7:$I$111,"Y") -> 0
A25: of which marked non-quality in H1: EUR | C25: =C24*Figures!$C$4 -> 0

Sheet H1_ReworkNoNC
A1: H1. Rework orders on the FTO2 shop floor with no NC behind them (September 2026)
A2: S03 rework orders on FTO2 work centres (REC, flight test, regularisation and A400M excluded) that no NC links to and that name no NC number.
A4: For each order (or each group, using the filter): is it non-quality, and should an NC exist? Rework after test and cable remakes with no NC are the most likely 'missing NCs'. Planned hours are SAP standard values in IM (1/100 h), converted to hours.
A6: Rework order | B6: Programme | C6: MSN | D6: Work centre(s) | E6: Planned h | F6: Group (my reading) | G6: Named in disruption | H6: What the order says | I6: Non-quality? (Y/N) | J6: Should an NC have been written? (Y/N) | K6: Comment
A7: 1031148483 | B7: A330 | C7: 2166 | D7: Attestation de conformitÃ© / Contrôle impression / Impression | E7: 13.26 | F7: Cable cutting for stock (see H4) | H7: Attestation de conformité || Inspection Qualité || Débiter câbles BF24 Débiter câbles BF24 Veuillez débiter du BF24 => 3 fagots de 50 câbles de 100cm
A8: 1030956049 | B8: A330 | C8: 2169 | D8: Contrôle impression / Impression | E8: 3.42 | F8: Cable cutting for stock (see H4) | H8: Inspection Qualité || Débiter câbles BF24 et BF20 Débiter câbles BF24 et BF20 Veuillez débiter du BF24 50 câbles de 100cm Veuillez débiter du BF24 50 câbles de 80cm Veuillez débiter du BF20 50 câbles de 80cm
A9: 1030956972 | B9: A330 | C9: 2169 | D9: Impression | E9: 3.42 | F9: Cable cutting for stock (see H4) | H9: Débiter câbles BF24 et BF20 Débiter câbles BF24 et BF20 Veuillez débiter du BF24 50 câbles de 100cm Veuillez débiter du BF24 50 câbles de 80cm Veuillez débiter du BF20 50 câbles de 80cm
A10: 1030957008 | B10: A330 | C10: 2169 | D10: Contrôle impression / Impression | E10: 3.42 | F10: Cable cutting for stock (see H4) | H10: Inspection Qualité || Débiter câbles BF24 et BF20 Débiter câbles BF24 et BF20 Veuillez débiter du BF24 50 câbles de 100cm Veuillez débiter du BF24 50 câbles de 80cm Veuillez débiter du BF20 50 câbles de 80cm
A11: 1030957018 | B11: A330 | C11: 2169 | D11: Impression | E11: 3.42 | F11: Cable cutting for stock (see H4) | H11: Débiter câbles BF24 et BF20 Débiter câbles BF24 et BF20 Veuillez débiter du BF24 50 câbles de 100cm Veuillez débiter du BF24 50 câbles de 80cm Veuillez débiter du BF20 50 câbles de 80cm
A12: 1030957042 | B12: A330 | C12: 2169 | D12: Impression | E12: 3.42 | F12: Cable cutting for stock (see H4) | H12: Débiter câbles BF24 et BF20 Débiter câbles BF24 et BF20 Veuillez débiter du BF24 50 câbles de 100cm Veuillez débiter du BF24 50 câbles de 80cm Veuillez débiter du BF20 50 câbles de 80cm
A13: 1030957054 | B13: A330 | C13: 2169 | D13: Impression | E13: 3.42 | F13: Cable cutting for stock (see H4) | H13: Débiter câbles BF24 et BF20 Débiter câbles BF24 et BF20 Veuillez débiter du BF24 50 câbles de 100cm Veuillez débiter du BF24 50 câbles de 80cm Veuillez débiter du BF20 50 câbles de 80cm
A14: 1030957059 | B14: A330 | C14: 2169 | D14: Impression | E14: 3.42 | F14: Cable cutting for stock (see H4) | H14: Débiter câbles BF24 et BF20 Débiter câbles BF24 et BF20 Veuillez débiter du BF24 50 câbles de 100cm Veuillez débiter du BF24 50 câbles de 80cm Veuillez débiter du BF20 50 câbles de 80cm
A15: 1030957073 | B15: A330 | C15: 2169 | D15: Attestation de conformitÃ© / Contrôle impression / Impression | E15: 3.42 | F15: Cable cutting for stock (see H4) | H15: Attestation de conformité || Inspection Qualité || Débiter câbles BF24 et BF20 Débiter câbles BF24 et BF20 Veuillez débiter du BF24 50 câbles de 100cm Veuillez débiter du BF24 50 câbles de 80cm Veuillez débiter du BF20 50 câbles de 80cm
A16: 1030957083 | B16: A330 | C16: 2169 | D16: Contrôle impression / Impression | E16: 3.42 | F16: Cable cutting for stock (see H4) | H16: Inspection Qualité || Débiter câbles BF24 et BF20 Débiter câbles BF24 et BF20 Veuillez débiter du BF24 50 câbles de 100cm Veuillez débiter du BF24 50 câbles de 80cm Veuillez débiter du BF20 50 câbles de 80cm
A17: 1031218410 | B17: A330 | C17: 2171 | D17: Attestation de conformitÃ© / Contrôle impression / Impression | E17: 2.26 | F17: Cable cutting for stock (see H4) | H17: Inspection Qualité || Attestation de conformité || Débiter câbles BF24 Débiter câbles BF24 Veuillez débiter du BF24 => 2 fagots de 50 câbles de 100cm
A18: 1031218471 | B18: A330 | C18: 2171 | D18: Attestation de conformitÃ© / Contrôle impression / Impression | E18: 2.26 | F18: Cable cutting for stock (see H4) | H18: Inspection Qualité || Attestation de conformité || Débiter câbles BF24 Débiter câbles BF24 Veuillez débiter du BF24 => 2 fagots de 50 câbles de 100cm
... A111: 1031263387 | B111: A320 | C111: 7877 | D111: Attestation Conformité / Fabrication Harnais Electrique / Inspection qualité | E111: 0 | F111: Rework after test, no NC written | H111: Attestation de conformité || Contrôle || Dépose NSA940692-1 non conforme Dépose NSA940692-1 non conforme Merci de déposer le harnais UW520 NSA940692-1, 202ZU2 || Repose NSA940692-1 conforme Repose NSA940692-1 conforme Merci de procéder à la repose du harnais UW520 NSA940692-1 W1-Enc || PREPARATION / ANALYSE DOSSIER
A112: Total planned h | E112: =SUM(E7:E111) -> 180.76 | F112: ="Marked non-quality: "&TEXT(SUMIFS(E7:E111,I7:I111,"Y"),"0.0")&" h" -> Marked non-quality: 0.0 h

Sheet H2_QualityTime
A1: H2. Quality team time booked on rework orders (September 2026)
A2: Two S03 orders on quality work centres look like the quality team's time sheet for the month: one for the A350 line, one for the A330 line.
A4: Questions: Is there one such order per line every month? Who books on it? Which operations are NC handling (and so CNQ), and which are normal quality work (QA qualification, production support)? Does any of it overlap the model's 'writing the NC' (30/60 min) or 'technical support' (60 min) steps?
A6: Order | B6: Programme / MSN | C6: Work centre | D6: Op | E6: Operation | F6: Long text | G6: Planned h | H6: NC-related? (Y/N) | I6: Already in the model's steps? (writing / support / none) | J6: Comment
A7: 1031225552 | B7: A330 / 2172 | C7: 4QEH1I07 | D7: 10 | E7: SO et AD-HOC | G7: 4
A8: 1031225552 | B8: A330 / 2172 | C8: 4QEH1I07 | D8: 20 | E8: Passage de QA 1ere attribution et renouv | F8: Passage de QA 1ere attribution et renouvellement | G8: 5
A9: 1031225552 | B9: A330 / 2172 | C9: 4QEH1I07 | D9: 30 | E9: REVUE QA | G9: 1
A10: 1031225552 | B10: A330 / 2172 | C10: 4QEH1I07 | D10: 40 | E10: ALERTE QUALITE SUITE A RETOUR CLIENT OU | F10: ALERTE QUALITE SUITE A RETOUR CLIENT OU ALERTE NOE | G10: 1
A11: 1031225552 | B11: A330 / 2172 | C11: 4QEH1I07 | D11: 50 | E11: ACCOMPAGNEMENT PRODUCTION | G11: 1.5
A12: 1031225552 | B12: A330 / 2172 | C12: 4QEH1I07 | D12: 60 | E12: RECHERCHE IBM | G12: 2
A13: 1031225552 | B13: A330 / 2172 | C13: 4QEH1I07 | D13: 70 | E13: POINTS PTVU / MFT | G13: 5
A14: 1031225552 | B14: A330 / 2172 | C14: 4QEM0I01 | D14: 9995 | E14: Attestation de conformité | G14: 0
A15: 1031243823 | B15: A350 / 872 | C15: 4QEH5I07 | D15: 10 | E15: SO | G15: 3
A16: 1031243823 | B16: A350 / 872 | C16: 4QEH5I07 | D16: 20 | E16: ACCOMPAGNEMENT PROD / QA / L2 / TL | G16: 20
A17: 1031243823 | B17: A350 / 872 | C17: 4QEH5I07 | D17: 30 | E17: ACCOMPAGNEMENT ME | G17: 1
A18: 1031243823 | B18: A350 / 872 | C18: 4QEH5I07 | D18: 40 | E18: Gestion des parachèvements | G18: 2
A19: 1031243823 | B19: A350 / 872 | C19: 4QEH5I07 | D19: 50 | E19: NC cable / Interne | G19: 3
A20: 1031243823 | B20: A350 / 872 | C20: 4QEH5I07 | D20: 60 | E20: Gestion NC Fournisseur et/ou client + a | G20: 2
A21: 1031243823 | B21: A350 / 872 | C21: 4QEH5I07 | D21: 70 | E21: Gestion NC retours clients + analyse | F21: Gestion NC retours clients + analyse lité + admin | G21: 15
A22: 1031243823 | B22: A350 / 872 | C22: 4QEH5I07 | D22: 80 | E22: Controle finale MDCD + accompagnement MD | G22: 1
A23: 1031243823 | B23: A350 / 872 | C23: 4QEH5I07 | D23: 90 | E23: Alerte qualité | G23: 4
A24: 1031243823 | B24: A350 / 872 | C24: 4QEH0I01 | D24: 9995 | E24: Attestation de conformité | G24: 0
A25: Total planned h | G25: =SUM(G7:G24) -> 70.5 | H25: =SUMIFS(G7:G24,H7:H24,"Y") -> 0
H26: h marked NC-related

Sheet H3_CustomerReturns
A1: H3. Customer returns: the actual cost, including the work done at the customer
A2: Customer-return NCs where FTO2 is liable, created in 2026. We are the direct cause, so every cost we can find counts, even outside the plant.
A4: What the model counts today: writing the NC, technical support, re-check, and the rework estimated at FTO2's times (no operator alert since 19 Oct). What it does not count: the repair time actually spent at the customer, the analysis (8D), transport, kits, penalties. Fill what you find in the yellow columns; 'Cost with findings' replaces the model's rework by the real repair hours when you enter them, and adds the rest.
A5: What we already know: FNZ1 returns (cockpit 'mauvais backshell') get an FTO2 rework order that only checks the kit sent to Montoir-de-Bretagne (0 h planned). Two FFF1 returns ('312VU endommagé') are linked to REC rework orders at the FAL (0.5 and 0.8 h planned). In September the quality team's A350 order booked 15 h of 'Gestion NC retours clients + analyse' for 8 A350 returns.
A7: NC | B7: Created | C7: Raised at plant | D7: Programme | E7: MSN | F7: What was found | G7: Decision | H7: Defect lines | I7: Model cost now (EUR) | J7: of which rework at FTO2 times (EUR) | K7: Rework order(s) linked | L7: Planned h on that order (Sept file) | M7: Repair hours at the customer | N7: Analysis / 8D hours | O7: Transport, kit, logistics (EUR) | P7: Penalties, other (EUR) | Q7: Source of the figures | R7: Cost with findings (EUR)
A8: 216060610 | B8: 2026-01-07 | C8: FNZ1 | D8: MT | E8: 159 | F8: Cab*G*C17*L1/2*Prise 624VC non conforme | G8: RWK | H8: 0 | I8: 150 | J8: 50 | K8: 1028164740, 1028176622 | R8: =I8-IF(ISNUMBER(M8),J8-M8*Figures!$C$4,0)+N(N8)*Figures!$C$4+N(O8)+N(P8) -> 150
A9: 216172114 | B9: 2026-01-19 | C9: FNZ1 | D9: MT | E9: 160 | F9: OHP-G Dérivation mal positionnée 2400VB | G9: RWK | H9: 0 | I9: 150 | J9: 50 | K9: 1028305824, 1028306604 | R9: =I9-IF(ISNUMBER(M9),J9-M9*Figures!$C$4,0)+N(N9)*Figures!$C$4+N(O9)+N(P9) -> 150
A10: 216217484 | B10: 2026-01-22 | C10: FFF1 | D10: A330 | E10: 2142 | F10: Vis cassé dans alésage | G10: RWK | H10: 1 | I10: 159.18 | J10: 58.33 | K10: 1028140433 | R10: =I10-IF(ISNUMBER(M10),J10-M10*Figures!$C$4,0)+N(N10)*Figures!$C$4+N(O10)+N(P10) -> 159.18
A11: 216225110 | B11: 2026-01-23 | C11: FFF1 | D11: A330 | E11: 2142 | F11: Disjoncteur 2RE1 cassée | G11: RWK | H11: 1 | I11: 166.67 | J11: 66.67 | K11: 1028174479 | R11: =I11-IF(ISNUMBER(M11),J11-M11*Figures!$C$4,0)+N(N11)*Figures!$C$4+N(O11)+N(P11) -> 166.67
A12: 216308985 | B12: 2026-02-02 | C12: FFF1 | D12: A330 | E12: 2121 | F12: Circuit breaker ATC broken | G12: RWK | H12: 1 | I12: 166.67 | J12: 66.67 | K12: 1028253666 | R12: =I12-IF(ISNUMBER(M12),J12-M12*Figures!$C$4,0)+N(N12)*Figures!$C$4+N(O12)+N(P12) -> 166.67
A13: 216313341 | B13: 2026-02-02 | C13: FFF1 | D13: A320 | E13: 13212 | F13: Damaged 2797VC socket | G13: RWK | H13: 1 | I13: 166.67 | J13: 66.67 | R13: =I13-IF(ISNUMBER(M13),J13-M13*Figures!$C$4,0)+N(N13)*Figures!$C$4+N(O13)+N(P13) -> 166.67
A14: 216340381 | B14: 2026-02-04 | C14: FNZ1 | D14: A350 | E14: 813 | F14: CKPT*C1/3*R0/1*D*Collier HS MIP*SD@* | G14: RWK | H14: 1 | I14: 166.67 | J14: 66.67 | K14: 1028304301, 1028304491 | R14: =I14-IF(ISNUMBER(M14),J14-M14*Figures!$C$4,0)+N(N14)*Figures!$C$4+N(O14)+N(P14) -> 166.67
A15: 216394948 | B15: 2026-02-10 | C15: FNZ1 | D15: A350 | E15: 809 | F15: CKPT*C4/5*G*Montage x2 non conf MIP*RL* | G15: RWK | H15: 1 | I15: 166.67 | J15: 66.67 | K15: 1028411423, 1028411928 | R15: =I15-IF(ISNUMBER(M15),J15-M15*Figures!$C$4,0)+N(N15)*Figures!$C$4+N(O15)+N(P15) -> 166.67
A16: 216457592 | B16: 2026-02-16 | C16: FFF1 | D16: A330 | E16: 2150 | F16: vis manquante 312VU | G16: RWK | H16: 1 | I16: 150 | J16: 50 | K16: 1028454717 | R16: =I16-IF(ISNUMBER(M16),J16-M16*Figures!$C$4,0)+N(N16)*Figures!$C$4+N(O16)+N(P16) -> 150
A17: 216501197 | B17: 2026-02-20 | C17: FNZ1 | D17: A350 | E17: 815 | F17: CKPT*C4/5*D*Orientation Backshel NC*SD@* | G17: RWK | H17: 1 | I17: 166.85 | J17: 66.67 | K17: 1028522896 | R17: =I17-IF(ISNUMBER(M17),J17-M17*Figures!$C$4,0)+N(N17)*Figures!$C$4+N(O17)+N(P17) -> 166.85
A18: 216573781 | B18: 2026-02-27 | C18: DST1 | D18: A320 | E18: 13259 | F18: NoE from Supplier | G18: RWK | H18: 1 | I18: 150 | J18: 50 | K18: 1028699551, 1028699569 | R18: =I18-IF(ISNUMBER(M18),J18-M18*Figures!$C$4,0)+N(N18)*Figures!$C$4+N(O18)+N(P18) -> 150
A19: 216640513 | B19: 2026-03-06 | C19: FFF1 | D19: A350 | E19: 814 | F19: CRG1-FR39/40-LH-BACKSHELL-BE | G19: RWK | H19: 1 | I19: 153.58 | J19: 50 | K19: 1028741420 | R19: =I19-IF(ISNUMBER(M19),J19-M19*Figures!$C$4,0)+N(N19)*Figures!$C$4+N(O19)+N(P19) -> 153.58
A20: 216642382 | B20: 2026-03-06 | C20: FFF1 | D20: A350 | E20: 797 | F20: FOD-WINGBOX-LHS-RIB2-521DB-IN-FOD-HA | G20: PNC | H20: 1 | I20: 100 | J20: 0 | R20: =I20-IF(ISNUMBER(M20),J20-M20*Figures!$C$4,0)+N(N20)*Figures!$C$4+N(O20)+N(P20) -> 100
A21: 216650708 | B21: 2026-03-07 | C21: AFM1 | D21: A320 | E21: 13117 | F21: ESAO/ENG 2/SERVICE INTERPHONE INOP | G21: RWK | H21: 2 | I21: 191.67 | J21: 91.67 | K21: 1028735698 | R21: =I21-IF(ISNUMBER(M21),J21-M21*Figures!$C$4,0)+N(N21)*Figures!$C$4+N(O21)+N(P21) -> 191.67
A22: 216651361 | B22: 2026-03-08 | C22: AFM1 | D22: A320 | E22: 13143 | F22: ESAO/GTI/1GA Circuit breaker tripping | G22: RWK | H22: 1 | I22: 166.67 | J22: 66.67 | R22: =I22-IF(ISNUMBER(M22),J22-M22*Figures!$C$4,0)+N(N22)*Figures!$C$4+N(O22)+N(P22) -> 166.67
A23: 216666114 | B23: 2026-03-09 | C23: FFF1 | D23: A350 | E23: 700 | F23: ELEC/CARGO1/FTI/BONDINGBRAID/DISCONNECT | G23: RWK | H23: 1 | I23: 150 | J23: 50 | R23: =I23-IF(ISNUMBER(M23),J23-M23*Figures!$C$4,0)+N(N23)*Figures!$C$4+N(O23)+N(P23) -> 150
A24: 216668677 | B24: 2026-03-10 | C24: FNZ1 | D24: A350 | E24: 817 | F24: CKPT*C9*L22*D*Détrompeur cassé*MV* | G24: RWK | H24: 1 | I24: 166.67 | J24: 66.67 | K24: 1028762697, 1028762835 | R24: =I24-IF(ISNUMBER(M24),J24-M24*Figures!$C$4,0)+N(N24)*Figures!$C$4+N(O24)+N(P24) -> 166.67
A25: 216672801 | B25: 2026-03-10 | C25: A-DU | D25: A320 | E25: 13143 | F25: ESAO/GTI/1GA Circuit Breaker Tripping | G25: RWK | H25: 2 | I25: 191.67 | J25: 91.67 | K25: 1028762098 | R25: =I25-IF(ISNUMBER(M25),J25-M25*Figures!$C$4,0)+N(N25)*Figures!$C$4+N(O25)+N(P25) -> 191.67
A26: 216678821 | B26: 2026-03-10 | C26: FNZ1 | D26: A350 | E26: 823 | F26: CKPT*C6*L24/25*D*Prise harnais NC*BA@* | G26: RWK | H26: 1 | I26: 166.67 | J26: 66.67 | R26: =I26-IF(ISNUMBER(M26),J26-M26*Figures!$C$4,0)+N(N26)*Figures!$C$4+N(O26)+N(P26) -> 166.67
A27: 216696565 | B27: 2026-03-11 | C27: FFF1 | D27: A350 | E27: 700 | F27: ELEC/CARGO1/HARNESS/CLASH/ESN/FTI | G27: RWK | H27: 1 | I27: 150 | J27: 50 | R27: =I27-IF(ISNUMBER(M27),J27-M27*Figures!$C$4,0)+N(N27)*Figures!$C$4+N(O27)+N(P27) -> 150
A28: 17063910 | B28: 2026-03-12 | C28: 51 | D28: A330 | E28: 2151 | F28: ERGOT WARNING HORN H.S. | G28: REJ | H28: 1 | I28: 100 | J28: 0 | R28: =I28-IF(ISNUMBER(M28),J28-M28*Figures!$C$4,0)+N(N28)*Figures!$C$4+N(O28)+N(P28) -> 100
A29: 216707983 | B29: 2026-03-12 | C29: FFF1 | D29: A350 | E29: 700 | F29: NC.ITEM/CARGO1/ATTENUATOR/CAP | G29: RWK | H29: 1 | I29: 150 | J29: 50 | K29: 1028923893 | R29: =I29-IF(ISNUMBER(M29),J29-M29*Figures!$C$4,0)+N(N29)*Figures!$C$4+N(O29)+N(P29) -> 150
A30: 216748577 | B30: 2026-03-17 | C30: FFF1 | D30: A350 | E30: 804 | F30: Bite Test RAIMS Fault Code 2350F092 | G30: RWK | H30: 1 | I30: 150 | J30: 50 | K30: 1029047483 | R30: =I30-IF(ISNUMBER(M30),J30-M30*Figures!$C$4,0)+N(N30)*Figures!$C$4+N(O30)+N(P30) -> 150
A31: 216750973 | B31: 2026-03-17 | C31: FFF1 | D31: A330 | E31: 2145 | F31: Inversion de câble sur le 9PH | G31: RWK | H31: 1 | I31: 170.83 | J31: 70.83 | K31: 1028908230 | R31: =I31-IF(ISNUMBER(M31),J31-M31*Figures!$C$4,0)+N(N31)*Figures!$C$4+N(O31)+N(P31) -> 170.83
A32: 216854475 | B32: 2026-03-26 | C32: FFF1 | D32: A350 | E32: 802 | F32: BF4-FR63/64-197AT-LH-ABS2210B301F-DC | G32: RWK | H32: 1 | I32: 159.18 | J32: 58.33 | R32: =I32-IF(ISNUMBER(M32),J32-M32*Figures!$C$4,0)+N(N32)*Figures!$C$4+N(O32)+N(P32) -> 159.18
A33: 216926613 | B33: 2026-04-03 | C33: FFF1 | D33: A330 | E33: 2145 | F33: Rampe cassée | G33: RWK | H33: 1 | I33: 159.18 | J33: 58.33 | K33: 1029183367 | R33: =I33-IF(ISNUMBER(M33),J33-M33*Figures!$C$4,0)+N(N33)*Figures!$C$4+N(O33)+N(P33) -> 159.18
A34: 216937725 | B34: 2026-04-05 | C34: FFF1 | D34: A330 | E34: 2148 | F34: FIN breakers érronés | G34: RWK | H34: 1 | I34: 166.67 | J34: 66.67 | R34: =I34-IF(ISNUMBER(M34),J34-M34*Figures!$C$4,0)+N(N34)*Figures!$C$4+N(O34)+N(P34) -> 166.67
A35: 216947614 | B35: 2026-04-07 | C35: FFF1 | D35: A330 | E35: 2149 | F35: Interference 313VU/265VT structure | G35: RWK | H35: 1 | I35: 150 | J35: 50 | K35: 1029181729 | R35: =I35-IF(ISNUMBER(M35),J35-M35*Figures!$C$4,0)+N(N35)*Figures!$C$4+N(O35)+N(P35) -> 150
A36: 216981246 | B36: 2026-04-09 | C36: FFF1 | D36: A330 | E36: 2152 | F36: 17CE manquant | G36: RWK | H36: 1 | I36: 154.17 | J36: 54.17 | R36: =I36-IF(ISNUMBER(M36),J36-M36*Figures!$C$4,0)+N(N36)*Figures!$C$4+N(O36)+N(P36) -> 154.17
A37: 217037645 | B37: 2026-04-15 | C37: AFM1 | D37: A320 | E37: 13115 | F37: ESAO: GTI: 15XE-A INOP | G37: EXC | H37: 1 | I37: 166.67 | J37: 66.67 | K37: 1029256022 | R37: =I37-IF(ISNUMBER(M37),J37-M37*Figures!$C$4,0)+N(N37)*Figures!$C$4+N(O37)+N(P37) -> 166.67
A38: 217070011 | B38: 2026-04-20 | C38: FFF1 | D38: A330 | E38: 2141 | F38: Contact tordu Borne 20 3667VC | G38: RWK | H38: 1 | I38: 166.67 | J38: 66.67 | K38: 1029291474 | R38: =I38-IF(ISNUMBER(M38),J38-M38*Figures!$C$4,0)+N(N38)*Figures!$C$4+N(O38)+N(P38) -> 166.67
A39: 217143872 | B39: 2026-04-27 | C39: FNZ1 | D39: A350 | E39: 816 | F39: CKPT*C8/9*L21/22*D&G*Etiquette mqte*FB* | G39: ACC | H39: 1 | I39: 100 | J39: 0 | R39: =I39-IF(ISNUMBER(M39),J39-M39*Figures!$C$4,0)+N(N39)*Figures!$C$4+N(O39)+N(P39) -> 100
A40: 217171047 | B40: 2026-04-29 | C40: FFF1 | D40: A330 | E40: 2158 | F40: Equipement 314VU VT mal positionnée | G40: RWK | H40: 1 | I40: 150 | J40: 50 | R40: =I40-IF(ISNUMBER(M40),J40-M40*Figures!$C$4,0)+N(N40)*Figures!$C$4+N(O40)+N(P40) -> 150
A41: 217171214 | B41: 2026-04-29 | C41: FFF1 | D41: A330 | E41: 2158 | F41: Equipement 313VU VT mal positionnée | G41: RWK | H41: 2 | I41: 150 | J41: 50 | K41: 1029489899 | R41: =I41-IF(ISNUMBER(M41),J41-M41*Figures!$C$4,0)+N(N41)*Figures!$C$4+N(O41)+N(P41) -> 150
A42: 217253630 | B42: 2026-05-11 | C42: FNZ1 | D42: A350 | E42: 820 | F42: Backshell manquant | G42: RWK | H42: 1 | I42: 154.17 | J42: 54.17 | K42: 1029573005 | R42: =I42-IF(ISNUMBER(M42),J42-M42*Figures!$C$4,0)+N(N42)*Figures!$C$4+N(O42)+N(P42) -> 154.17
A43: 217363914 | B43: 2026-05-25 | C43: FFF1 | D43: A330 | E43: 2141 | F43: etiquette identification absenteSur536VU | G43: RWK | H43: 1 | I43: 150 | J43: 50 | K43: 1029783101 | R43: =I43-IF(ISNUMBER(M43),J43-M43*Figures!$C$4,0)+N(N43)*Figures!$C$4+N(O43)+N(P43) -> 150
A44: 217406539 | B44: 2026-05-29 | C44: FNZ1 | D44: A350 | E44: 839 | F44: ATT*FB*C8/9*D*étiquettes VCs mqtes*BA@* | G44: RWK | H44: 1 | I44: 154.17 | J44: 54.17 | K44: 1029838552, 1029838655 | R44: =I44-IF(ISNUMBER(M44),J44-M44*Figures!$C$4,0)+N(N44)*Figures!$C$4+N(O44)+N(P44) -> 154.17
A45: 217494684 | B45: 2026-06-08 | C45: FNZ1 | D45: MT | E45: 162 | F45: Cock D&G Manque 3 prises F/O (2220VB) | G45: RWK | H45: 0 | I45: 150 | J45: 50 | K45: 1029990837, 1030008895 | R45: =I45-IF(ISNUMBER(M45),J45-M45*Figures!$C$4,0)+N(N45)*Figures!$C$4+N(O45)+N(P45) -> 150
A46: 217506669 | B46: 2026-06-09 | C46: FFF1 | D46: A330 | E46: 2153 | F46: Disjoncteur 15PH défectueux | G46: RWK | H46: 2 | I46: 191.67 | J46: 91.67 | R46: =I46-IF(ISNUMBER(M46),J46-M46*Figures!$C$4,0)+N(N46)*Figures!$C$4+N(O46)+N(P46) -> 191.67
A47: 217507424 | B47: 2026-06-09 | C47: FNZ1 | D47: A350 | E47: 840 | F47: CKPT*C2/3*G*Orientation Backshell*FB* | G47: RWK | H47: 1 | I47: 157.2 | J47: 50 | K47: 1029958376 | R47: =I47-IF(ISNUMBER(M47),J47-M47*Figures!$C$4,0)+N(N47)*Figures!$C$4+N(O47)+N(P47) -> 157.2
A48: 217509313 | B48: 2026-06-09 | C48: FNZ1 | D48: A350 | E48: 837 | F48: CKPT*C7/8*L23/25*G*Insert prise mqt*SD@* | G48: RWK | H48: 1 | I48: 166.67 | J48: 66.67 | R48: =I48-IF(ISNUMBER(M48),J48-M48*Figures!$C$4,0)+N(N48)*Figures!$C$4+N(O48)+N(P48) -> 166.67
A49: 217513743 | B49: 2026-06-09 | C49: FFF1 | D49: A330 | E49: 2153 | F49: Switch 8HL HS | G49: RWK | H49: 1 | I49: 166.67 | J49: 66.67 | K49: 1029994501 | R49: =I49-IF(ISNUMBER(M49),J49-M49*Figures!$C$4,0)+N(N49)*Figures!$C$4+N(O49)+N(P49) -> 166.67
A50: 217542391 | B50: 2026-06-12 | C50: FFF1 | D50: A330 | E50: 2153 | F50: EQPMT/_/MECA | G50: RWK | H50: 1 | I50: 150 | J50: 50 | K50: 1029995826 | R50: =I50-IF(ISNUMBER(M50),J50-M50*Figures!$C$4,0)+N(N50)*Figures!$C$4+N(O50)+N(P50) -> 150
A51: 217582044 | B51: 2026-06-16 | C51: FFF1 | D51: A330 | E51: 2136 | F51: 1RE1 HF1 Inop | G51: RWK | H51: 1 | I51: 166.67 | J51: 66.67 | K51: 1030112449 | R51: =I51-IF(ISNUMBER(M51),J51-M51*Figures!$C$4,0)+N(N51)*Figures!$C$4+N(O51)+N(P51) -> 166.67
A52: 17232524 | B52: 2026-06-18 | C52: 51 | D52: A330 | E52: 2163 | F52: WARNING HORN DETROMPAGE HS | G52: REJ | H52: 1 | I52: 100 | J52: 0 | R52: =I52-IF(ISNUMBER(M52),J52-M52*Figures!$C$4,0)+N(N52)*Figures!$C$4+N(O52)+N(P52) -> 100
A53: 217666206 | B53: 2026-06-24 | C53: FFF1 | D53: A330 | E53: 2159 | F53: 313VU VT mal positionnée | G53: RWK | H53: 1 | I53: 150 | J53: 50 | R53: =I53-IF(ISNUMBER(M53),J53-M53*Figures!$C$4,0)+N(N53)*Figures!$C$4+N(O53)+N(P53) -> 150
A54: 217733722 | B54: 2026-07-01 | C54: FFF1 | D54: A330 | E54: 2160 | F54: 312 VU endommagé | G54: RWK | H54: 1 | I54: 151.32 | J54: 50 | K54: 1030303190 | R54: =I54-IF(ISNUMBER(M54),J54-M54*Figures!$C$4,0)+N(N54)*Figures!$C$4+N(O54)+N(P54) -> 151.32
A55: 217803687 | B55: 2026-07-08 | C55: FFF1 | D55: A330 | E55: 2161 | F55: 313VU VT mal positionnée | G55: RWK | H55: 1 | I55: 150 | J55: 50 | K55: 1030337485 | R55: =I55-IF(ISNUMBER(M55),J55-M55*Figures!$C$4,0)+N(N55)*Figures!$C$4+N(O55)+N(P55) -> 150
A56: 217804240 | B56: 2026-07-08 | C56: FFF1 | D56: A330 | E56: 2161 | F56: 314VU VT mal positionnée | G56: RWK | H56: 1 | I56: 150 | J56: 50 | K56: 1030338005 | R56: =I56-IF(ISNUMBER(M56),J56-M56*Figures!$C$4,0)+N(N56)*Figures!$C$4+N(O56)+N(P56) -> 150
A57: 217874230 | B57: 2026-07-16 | C57: FNZ1 | D57: A350 | E57: 853 | F57: CKPT*C3/5*L22*D&G*Colliers mal pos*SD@* | G57: PNC | H57: 1 | I57: 100 | J57: 0 | R57: =I57-IF(ISNUMBER(M57),J57-M57*Figures!$C$4,0)+N(N57)*Figures!$C$4+N(O57)+N(P57) -> 100
A58: 217876176 | B58: 2026-07-16 | C58: FFF1 | D58: A330 | E58: 2162 | F58: 313VU VT mal positionnée | G58: RWK | H58: 1 | I58: 150 | J58: 50 | R58: =I58-IF(ISNUMBER(M58),J58-M58*Figures!$C$4,0)+N(N58)*Figures!$C$4+N(O58)+N(P58) -> 150
A59: 217876510 | B59: 2026-07-16 | C59: FFF1 | D59: A330 | E59: 2162 | F59: 314VU VT mal positionnée | G59: RWK | H59: 1 | I59: 150 | J59: 50 | R59: =I59-IF(ISNUMBER(M59),J59-M59*Figures!$C$4,0)+N(N59)*Figures!$C$4+N(O59)+N(P59) -> 150
A60: 217913046 | B60: 2026-07-21 | C60: FNZ1 | D60: A350 | E60: 854 | F60: CKPT*C3/5*L22*D&G*Colliers mal pos*SD@* | G60: PNC | H60: 1 | I60: 100 | J60: 0 | R60: =I60-IF(ISNUMBER(M60),J60-M60*Figures!$C$4,0)+N(N60)*Figures!$C$4+N(O60)+N(P60) -> 100
A61: 218048183 | B61: 2026-08-20 | C61: FFF1 | D61: A330 | E61: 2136 | F61: VU/BUTTON/MECA | G61: REJ | H61: 1 | I61: 100 | J61: 0 | K61: 1030684585 | R61: =I61-IF(ISNUMBER(M61),J61-M61*Figures!$C$4,0)+N(N61)*Figures!$C$4+N(O61)+N(P61) -> 100
A62: 218069153 | B62: 2026-08-24 | C62: FFF1 | D62: A350 | E62: 833 | F62: WING-FAIR-RHS-REFF-LOCK WIRE-BH-621AB | G62: NDC | H62: 1 | I62: 25 | J62: 0 | R62: =I62-IF(ISNUMBER(M62),J62-M62*Figures!$C$4,0)+N(N62)*Figures!$C$4+N(O62)+N(P62) -> 25
A63: 218072156 | B63: 2026-08-24 | C63: FFF1 | D63: A350 | E63: 833 | F63: WINGBOX-RHS-621DB-IN-2446VT590-BCA | G63: NDC | H63: 1 | I63: 25 | J63: 0 | R63: =I63-IF(ISNUMBER(M63),J63-M63*Figures!$C$4,0)+N(N63)*Figures!$C$4+N(O63)+N(P63) -> 25
A64: 218121463 | B64: 2026-08-28 | C64: FNZ1 | D64: A350 | E64: 856 | F64: CKPT*C1*L22/21*D*Gaine écrasée*BA@* | G64: RWK | H64: 1 | I64: 166.67 | J64: 66.67 | K64: 1030818179, 1030818370 | L64: 0 | R64: =I64-IF(ISNUMBER(M64),J64-M64*Figures!$C$4,0)+N(N64)*Figures!$C$4+N(O64)+N(P64) -> 166.67
A65: 218121468 | B65: 2026-08-28 | C65: FNZ1 | D65: A350 | E65: 856 | F65: CKPT*C1*L22/23*G*Gaine écrasée*BA@* | G65: RWK | H65: 1 | I65: 166.67 | J65: 66.67 | K65: 1030817749, 1030818117, 1030818361 | L65: 0 | R65: =I65-IF(ISNUMBER(M65),J65-M65*Figures!$C$4,0)+N(N65)*Figures!$C$4+N(O65)+N(P65) -> 166.67
A66: 218149694 | B66: 2026-09-01 | C66: FFF1 | D66: A350 | E66: 701 | F66: Filetage abîmé capteur 219ZCA965 | G66: EXC | H66: 1 | I66: 159.18 | J66: 58.33 | R66: =I66-IF(ISNUMBER(M66),J66-M66*Figures!$C$4,0)+N(N66)*Figures!$C$4+N(O66)+N(P66) -> 159.18
A67: 218177900 | B67: 2026-09-03 | C67: FFF1 | D67: A330 | E67: 2165 | F67: 312 VU endommagé planche de bord | G67: RWK | H67: 1 | I67: 166.67 | J67: 66.67 | K67: 1030917181 | L67: 0.5 | R67: =I67-IF(ISNUMBER(M67),J67-M67*Figures!$C$4,0)+N(N67)*Figures!$C$4+N(O67)+N(P67) -> 166.67
A68: 218211772 | B68: 2026-09-08 | C68: FFF1 | D68: A330 | E68: 2164 | F68: 312VU endommagé | G68: RWK | H68: 1 | I68: 150 | J68: 50 | K68: 1030953684 | L68: 0.75 | R68: =I68-IF(ISNUMBER(M68),J68-M68*Figures!$C$4,0)+N(N68)*Figures!$C$4+N(O68)+N(P68) -> 150
A69: 218221555 | B69: 2026-09-09 | C69: FNZ1 | D69: A350 | E69: 858 | F69: ATT*FB*C6*L25*D*Mauvais backshell *LA@* | G69: RWK | H69: 1 | I69: 166.67 | J69: 66.67 | K69: 1030989646, 1030991132 | L69: 0 | R69: =I69-IF(ISNUMBER(M69),J69-M69*Figures!$C$4,0)+N(N69)*Figures!$C$4+N(O69)+N(P69) -> 166.67
A70: 218293184 | B70: 2026-09-16 | C70: FNZ1 | D70: MT | E70: 165 | F70: OVHP-MB234 Mqt sachet sur prises OLME TO | G70: UNKNOWN | H70: 0 | I70: 25 | J70: 0 | R70: =I70-IF(ISNUMBER(M70),J70-M70*Figures!$C$4,0)+N(N70)*Figures!$C$4+N(O70)+N(P70) -> 25
A71: 218348034 | B71: 2026-09-22 | C71: FNZ1 | D71: A350 | E71: 728 | F71: CKPT*C7/8*L24/25*D*Mauvais Backshell*FB* | G71: RWK | H71: 1 | I71: 166.85 | J71: 66.67 | K71: 1031170705, 1031170727 | L71: 0 | R71: =I71-IF(ISNUMBER(M71),J71-M71*Figures!$C$4,0)+N(N71)*Figures!$C$4+N(O71)+N(P71) -> 166.85
A72: 218348243 | B72: 2026-09-22 | C72: FNZ1 | D72: A350 | E72: 856 | F72: CKPT*C7/8*L24/25*D*Mauvais Backshell*FB* | G72: RWK | H72: 1 | I72: 166.85 | J72: 66.67 | K72: 1031171305, 1031171401 | L72: 0 | R72: =I72-IF(ISNUMBER(M72),J72-M72*Figures!$C$4,0)+N(N72)*Figures!$C$4+N(O72)+N(P72) -> 166.85
A73: 218390072 | B73: 2026-09-25 | C73: FNZ1 | D73: A350 | E73: 858 | F73: CKPT*C7/8*D&G*Mauvais Backshell*FB* | G73: RWK | H73: 1 | I73: 166.85 | J73: 66.67 | K73: 1031227280, 1031227284 | L73: 0 | R73: =I73-IF(ISNUMBER(M73),J73-M73*Figures!$C$4,0)+N(N73)*Figures!$C$4+N(O73)+N(P73) -> 166.85
A74: 218390076 | B74: 2026-09-25 | C74: FNZ1 | D74: A350 | E74: 857 | F74: CKPT*C7/8*L24/25*D*Mauvais Backshell*FB* | G74: RWK | H74: 1 | I74: 166.85 | J74: 66.67 | K74: 1031220048, 1031220696 | L74: 0 | R74: =I74-IF(ISNUMBER(M74),J74-M74*Figures!$C$4,0)+N(N74)*Figures!$C$4+N(O74)+N(P74) -> 166.85
A75: 218390345 | B75: 2026-09-25 | C75: FNZ1 | D75: A350 | E75: 861 | F75: CKPT*C7/8*D&G*Mauvais Backshell*FB* | G75: RWK | H75: 1 | I75: 166.85 | J75: 66.67 | K75: 1031227573, 1031227576 | L75: 0 | R75: =I75-IF(ISNUMBER(M75),J75-M75*Figures!$C$4,0)+N(N75)*Figures!$C$4+N(O75)+N(P75) -> 166.85
A76: 218392061 | B76: 2026-09-25 | C76: FNZ1 | D76: A350 | E76: 859 | F76: CKPT*C7/8*D*Backshell 7HT2A NC*BA@* | G76: RWK | H76: 1 | I76: 166.67 | J76: 66.67 | K76: 1031227496, 1031227500 | L76: 0 | R76: =I76-IF(ISNUMBER(M76),J76-M76*Figures!$C$4,0)+N(N76)*Figures!$C$4+N(O76)+N(P76) -> 166.67
A77: Total | I77: =SUM(I8:I76) -> 10250 | J77: =SUM(J8:J76) -> 3558.42 | R77: =SUM(R8:R76) -> 10250

Sheet H4_CableCutting
A1: H4. BF24 / BF20 cables cut for stock on rework orders (A330 print room, September 2026)
A2: 37 S03 orders on work centre 4FEM0E14 asking for bundles of 50 cables. The PTVU line had raised disruptions about BF24 quantities in Elec ABC and missing BF24 cables.
A4: Question: is this a consequence of non-quality (cables remade or replaced because of defects) or a definition / kitting problem (cut lists not giving the line the right cables)? Who to ask: methods (Elec ABC quantities), the A330 print room, the PTVU line leader. The related disruptions and NCs are listed further down.
A6: Order | B6: Confirmed | C6: MSN | D6: Planned h | E6: Request | F6: Comment
A7: 1030956049 | B7: 2026-09-09 | C7: 2169 | D7: 3.42 | E7: Débiter câbles BF24 et BF20 Débiter câbles BF24 et BF20 Veuillez débiter du BF24 50 câbles de 100cm Veuillez débiter du BF24 50 câbles de 80cm Veuillez débiter du BF20 50 câbles de 80cm
A8: 1030956972 | B8: 2026-09-09 | C8: 2169 | D8: 3.42 | E8: Débiter câbles BF24 et BF20 Débiter câbles BF24 et BF20 Veuillez débiter du BF24 50 câbles de 100cm Veuillez débiter du BF24 50 câbles de 80cm Veuillez débiter du BF20 50 câbles de 80cm
A9: 1030957008 | B9: 2026-09-09 | C9: 2169 | D9: 3.42 | E9: Débiter câbles BF24 et BF20 Débiter câbles BF24 et BF20 Veuillez débiter du BF24 50 câbles de 100cm Veuillez débiter du BF24 50 câbles de 80cm Veuillez débiter du BF20 50 câbles de 80cm
A10: 1030957018 | B10: 2026-09-09 | C10: 2169 | D10: 3.42 | E10: Débiter câbles BF24 et BF20 Débiter câbles BF24 et BF20 Veuillez débiter du BF24 50 câbles de 100cm Veuillez débiter du BF24 50 câbles de 80cm Veuillez débiter du BF20 50 câbles de 80cm
A11: 1030957042 | B11: 2026-09-09 | C11: 2169 | D11: 3.42 | E11: Débiter câbles BF24 et BF20 Débiter câbles BF24 et BF20 Veuillez débiter du BF24 50 câbles de 100cm Veuillez débiter du BF24 50 câbles de 80cm Veuillez débiter du BF20 50 câbles de 80cm
A12: 1030957054 | B12: 2026-09-09 | C12: 2169 | D12: 3.42 | E12: Débiter câbles BF24 et BF20 Débiter câbles BF24 et BF20 Veuillez débiter du BF24 50 câbles de 100cm Veuillez débiter du BF24 50 câbles de 80cm Veuillez débiter du BF20 50 câbles de 80cm
A13: 1030957059 | B13: 2026-09-09 | C13: 2169 | D13: 3.42 | E13: Débiter câbles BF24 et BF20 Débiter câbles BF24 et BF20 Veuillez débiter du BF24 50 câbles de 100cm Veuillez débiter du BF24 50 câbles de 80cm Veuillez débiter du BF20 50 câbles de 80cm
A14: 1030957073 | B14: 2026-09-09 | C14: 2169 | D14: 3.42 | E14: Débiter câbles BF24 et BF20 Débiter câbles BF24 et BF20 Veuillez débiter du BF24 50 câbles de 100cm Veuillez débiter du BF24 50 câbles de 80cm Veuillez débiter du BF20 50 câbles de 80cm
A15: 1030957083 | B15: 2026-09-09 | C15: 2169 | D15: 3.42 | E15: Débiter câbles BF24 et BF20 Débiter câbles BF24 et BF20 Veuillez débiter du BF24 50 câbles de 100cm Veuillez débiter du BF24 50 câbles de 80cm Veuillez débiter du BF20 50 câbles de 80cm
A16: 1031059358 | B16: 2026-09-17 | C16: 2170 | D16: 1.16 | E16: Débiter câbles BF24 Débiter câbles BF24 Veuillez débiter du BF24 50 câbles de 80cm
A17: 1031059254 | B17: 2026-09-17 | C17: 2170 | D17: 1.16 | E17: Débiter câbles BF24 Débiter câbles BF24 Veuillez débiter du BF24 50 câbles de 80cm
A18: 1031059144 | B18: 2026-09-17 | C18: 2170 | D18: 1.16 | E18: Débiter câbles BF24 Débiter câbles BF24 Veuillez débiter du BF24 50 câbles de 80cm
... A43: 1031244826 | B43: 2026-09-30 | C43: 2173 | D43: 1.16 | E43: Débiter câbles BF24 Débiter câbles BF24 Veuillez débiter du BF24 50 câbles de 100cm
A44: Total planned h | D44: =SUM(D7:D43) -> 77.56
A46: Related disruptions (mention BF24 / BF20)
A47: Disruption | B47: Opened | C47: Line | D47: Time lost (min) | E47: What the operator wrote | F47: Kind
A48: OZ2037505 | B48: 2026-05-29 | C48: IMPRESSION_A380 | D48: 90 | E48: OF 57564460 RECHANGE : il est demandé des manchons sur SOI mais pas de câble à débiter...des câbles BF24 et BF18 apparaissent sur Fiche suiveuse.Doit on livrer que les manchons ? | F48: SUPTECH - Probleme OF-OT et Definition
A49: OZ2099671 | B49: 2026-06-30 | C49: PTVU | D49: 14 | E49: dans elec abc l'onglet qté de type/jauge, pour la VT il est demandé de sertir 64 câbles de bf24 avec en3155-016m2018 alors qu'en comptant à partir de chaque modules il en faut seulement 13 | F49: SUPTECH - Probleme OF-OT et Definition
A50: OZ2146779 | B50: 2026-08-13 | C50: PTVU | D50: 14 | E50: Sur Elec ABC, dans le menu "Quantité de type/jauge (élément d'extrémité)", il y a marqué 22 câbles en BF24 contact 16M2018 mais il n'y a en réalité que 12 câbles à sertir avec ces contacts et les autres doivent être sertis avec les contacts 16M2222 | F50: SUPTECH - Probleme OF-OT et Definition
A51: OZ2170456 | B51: 2026-08-27 | C51: PTVU | D51: 14 | E51: Pièce manquante Bonjour, afin de répondre aux besoins de la production, nous sollicitons la fourniture de câbles BF24 d'une longueur de 80 cm. Merci de vous référer au courriel envoyé par Rachid A. | F51: LOG - Probleme servitude
A52: OZ2188489 | B52: 2026-09-04 | C52: PTVU | D52: 14 | E52: Pièce manquante MQT : Câbles BF24 en 100cm et 80cm. | F52: LOG - Probleme servitude
A53: OZ2243953 | B53: 2026-09-29 | C53: IMPRESSION_A330 | D53: 60 | E53: F955.00412.001.95 OF 57702138 57702341 57702244 57702544 57702549 57701440 Incohérence entre débit cables BF sur Fiche suiveuse et SOI Fiche suiveuse BF 24 L=80cm 29 PCES SUR SOI : 31 câbles de 75cm, 4 de 65cm et 1 de 45 cm BF18 L= 80cm 2 PCES SUR SOI : 2 cables de 75cm | F53: SUPTECH - Probleme OF-OT et Definition
A55: Related NCs (2026 NCs mentioning BF24 / BF20)
A56: NC | B56: Created | C56: Programme | D56: Type | E56: What was found | F56: Long text (extract)
A57: 216074163 | B57: 2026-01-08 | C57: A330 | D57: TEST | E57: 2148 | F57: 14/AIRBUS OPERATIONS SAS ) Tél. 33607657447 NonConformity 0001 : Type of nonconformity : Connection * Def 1-T01 : Câble BF24 N° : 2351-0459 manquant entre 19RN 1 ET 18RN 2. Def 2-T01 : Câble BF24 N° : 2351-0458 manquant entre 19RN 2 ET 18RN 1. Merci
A58: 216111281 | B58: 2026-01-13 | C58: A330 | D58: TEST | E58: Retouche Test 612VU MSN 02148 | F58: 14/AIRBUS OPERATIONS SAS ) Tél. 33607657447 NonConformity 0001 : Type of nonconformity : Connection * Def 1-T01 : Câble BF 24 N° : 2351-0303 manquant entre 15RN 1 et 16RN 2. Def 2-T01 : Câble BF 24 N° : 2351-0302 manquant entre 15RN 2 et 16RN 1. Merc
A59: 216195310 | B59: 2026-01-21 | C59: A330 | D59: TEST | E59: Retouche Test 313VU MSN 02145. | F59: 607657447 NonConformity 0001 : Type of nonconformity : Connection * Def 1-T01 : 4 Câbles manquants en 261VT 1 : - Câble BF24 N°:3163-0918 manquant entre 261VT 1 A et 54FP1 A B1. - Câble BF24 N°:3163-0919 manquant entre 261VT 1 B et 54FP1 A A1. - Câbl
A60: 216195654 | B60: 2026-01-21 | C60: A330 | D60: TEST | E60: Retouche Test 31'VU MSN 02145. | F60: 607657447 NonConformity 0001 : Type of nonconformity : Connection * Def 1-T01 : 3 Câbles manquants en 260VT 1 : - Câble BF 24 N° : 3163-0924 Manquant entre 260VT 1 A et 54FP2 A B1. - Câble BF 24 N° : 3163-0925 Manquant entre 260VT 1 B et 54FP2 A A1.
A61: 216851910 | B61: 2026-03-26 | C61: A330 | D61: TEST | E61: Retouche Test 417VU MSN 02158. | F61: 14/AIRBUS OPERATIONS SAS ) Tél. 33607657447 NonConformity 0001 : Type of nonconformity : Connection * Def 1-T02 : Câble BF24 N° : 3163-0588 branché en 1WS A 7 au lieu de 8WK1 A 7. Merci de remettre le VU en conformité. -- -- -- -- -- -- -- -- -- -- -
A62: 217019027 | B62: 2026-04-14 | C62: A330 | D62: TEST | E62: Retouche Test 245VU MSN 02157. | F62: OPERATIONS SAS ) Tél. 33607657447 NonConformity 0001 : Type of nonconformity : Fault in continuity * Def 1-T03 : Shunt BF24 N° : 3314-0919 Manquant entre 651VT3 C et 651VT5 R. Merci de remettre le VU en conformité. -- -- -- -- -- -- -- -- -- -- -- --
A63: 217055268 | B63: 2026-04-17 | C63: A330 | D63: TEST | E63: Retouche Test 616VU MSN 02157. | F63: OPERATIONS SAS ) Tél. 33607657447 NonConformity 0001 : Type of nonconformity : Fault in continuity * Def 1-T01 : Câble BF24 N° : 2351-0458 Manquant entre 18RN 1 et 19RN 2. Def 2-T01 : Câble BF24 N° : 2351-0459 Manquant entre 18RN 2 et 19RN 1. Câbles
A64: 217140319 | B64: 2026-04-27 | C64: A330 | D64: QUALITE | E64: Cables manquants suite NC 217055268 | F64: ng Part/Component / Incomplete Kit * Suite à la NC 217055268 , il a été détecté lors du test deux câbles manquant. * 1- BF24 N° 2351-0458 entre 18RN 1 et 19RN 2 2- BF24 N° 2351-0459 entre 18RN 2 et 19RN 1 * Merci de commander ces câbles pour effectue
A65: 217451299 | B65: 2026-06-03 | C65: A330 | D65: TEST | E65: Retouches Test 245VU MSN 02160. | F65: nconformity : Connection * Def 1-Q06 : Le Câblage en 653VT 7 a été effectué avec le MSN 02159 au lieu de 02160. - Câble BF24 N° : 3314-1130 branché entre 653VT 7L et 650VC BB à déposer. Def 2-Q06 : Le Câblage en 653VT 7 a été effectué avec le MSN 021

Sheet H5_NCsNoOrder
A1: H5. Reworked NCs with no rework order
A2: Decision 'rework', FTO2 liable, raised at FTO2, but no rework order in the NC's linked_document (an AW_/WO_/RS_ number different from its own work order).
A4: 96-97% of reworked NCs get their own rework order. For these few, check in SAP whether the rework was done on the spot (no order needed) or whether an order exists but was never linked to the NC. If orders exist unlinked, the 'rework order' rule misses them.
A6: NC | B6: Year | C6: Created | D6: NC type | E6: Workflow | F6: Station | G6: Written by | H6: What was found | I6: linked_document | J6: Own work order | K6: Fixed on the spot? (Y/N) | L6: Order exists but link missing? (Y/N) | M6: Comment
A7: 218413734 | B7: 2026 | C7: 2026-09-28 | D7: NC Interne | E7: REW-LIGNE-V | F7: V4QMI2 | G7: QRT/DERICHEBOURG AERONAUTICS | H7: Retouches finales | J7: 001030718127
A8: 218409412 | B8: 2026 | C8: 2026-09-28 | D8: TEST | E8: TEST-RET | F8: V42RA1 | G8: OLMEP14/AIRBUS OPERATIONS SAS | H8: RETOUCHES TEST MSN0870. | J8: 001030163689
A9: 218320671 | B9: 2026 | C9: 2026-09-18 | D9: NC Interne | E9: REW-LIGNE-D | F9: D42D01 | G9: QR/DERICHEBOURG AERONAUTICS | H9: Prises 10LB-A et 7588VC-A non torquées | J9: 001030822062
A10: 218315000 | B10: 2026 | C10: 2026-09-17 | D10: CABLES | E10: REW-CA-IMP-V | F10: V4V120 | G10: QRT/DERICHEBOURG AERONAUTICS | H10: Câble trop court | J10: 001030811458
A11: 218208196 | B11: 2026 | C11: 2026-09-08 | D11: CONTROLE FINAL | E11: REW-LIGNE-V | F11: V4V214 | G11: QLOT1/AIRBUS OPERATIONS SAS | H11: Aléa OZ2193509 Prise abimée EN3645-M6CN9 | J11: 001030355794
A12: 218105386 | B12: 2026 | C12: 2026-08-27 | D12: CONTROLE FINAL | E12: REW-LIGNE-F | F12: F4F012 | G12: QLOT1/AIRBUS OPERATIONS SAS | H12: FOURREAU MONTE A L'ENVERS | J12: 001030172079
A13: 218069982 | B13: 2026 | C13: 2026-08-24 | D13: TEST | E13: REW-TEST-F | F13: F4F015 | G13: OLMEP14/AIRBUS OPERATIONS SAS | H13: SHUNTS MANQUANTS | J13: 001030067999
A14: 218005905 | B14: 2026 | C14: 2026-08-14 | D14: NC Interne | F14: V4V142 | G14: QR/DERICHEBOURG AERONAUTICS | H14: FOd contact femelle : MIP 858 | J14: 001029493692
A15: 217530835 | B15: 2026 | C15: 2026-06-11 | D15: TEST | E15: REW-TEST-V | F15: V42RA1 | G15: OLMEP14/AIRBUS OPERATIONS SAS | H15: RETOUCHE TEST MSN 853 CONTACT A REFAIRE | J15: 001029148565
A16: 217407744 | B16: 2026 | C16: 2026-05-29 | D16: DEMANDE DE DQN | E16: LIGNE-F-DQN | F16: M4MMIC | G16: QLOT1/AIRBUS OPERATIONS SAS | H16: Excessive shunt length on 8RZA connector | J16: 001029267550
A17: 217328612 | B17: 2026 | C17: 2026-05-20 | D17: NC Interne | E17: REW-LIGNE-D | F17: D42D01 | G17: QR/DERICHEBOURG AERONAUTICS | H17: Harnais 452VB court | J17: 001029405757
A18: 217230702 | B18: 2026 | C18: 2026-05-07 | D18: CABLES | E18: REW-CA-IMP-F | F18: F4F74C | G18: QLOT1/AIRBUS OPERATIONS SAS | H18: CABLE MANQUANT | J18: 001029148720
A19: 216820892 | B19: 2026 | C19: 2026-03-24 | D19: CONTROLE FINAL | E19: REW-LIGNE-M | F19: M4M30C | G19: QLOT1/AIRBUS OPERATIONS SAS | H19: 3 détrompeurs montés fabriqués par ATM | J19: 001027381521
A20: 216801004 | B20: 2026 | C20: 2026-03-23 | D20: NC Interne | E20: REW-LIGNE-D | F20: D42D01 | G20: QR/DERICHEBOURG AERONAUTICS | H20: Harnais 452VB court | J20: 001028634452
A21: 216764494 | B21: 2026 | C21: 2026-03-18 | D21: CONTROLE FINAL | E21: REW-LIGNE-D | F21: D42F14 | G21: QLOT1/AIRBUS OPERATIONS SAS | H21: Pince à sertir non conforme | J21: 001027973023
A22: 216699966 | B22: 2026 | C22: 2026-03-12 | D22: NC Interne | E22: REW-LIGNE-V | F22: V4V141 | G22: QRT/DERICHEBOURG AERONAUTICS | H22: Contrôle final qualité après test | J22: 001027848168
A23: 216381151 | B23: 2026 | C23: 2026-02-09 | D23: CONTROLE FINAL | E23: REW-LIGNE-M | F23: M4M30C | G23: QLOK310/AIRBUS OPERATIONS SAS | H23: Trous ovalisés hors tolérence | J23: 001026799692
A24: 213554463 | B24: 2025 | C24: 2025-02-18 | D24: NC Interne | E24: REW-LIG-ST-V | F24: V4V120 | G24: OLMEP1/ERMA ELECTRONIQUE | H24: Câble AD24 2797-1126 court
A25: 213618542 | B25: 2025 | C25: 2025-02-26 | D25: CONTROLE FINAL | E25: REW-LIGNE-F | F25: F4F74G | G25: QLOK310/AIRBUS OPERATIONS SAS | H25: impossibilité d'appliquer torquage | J25: 1023914810
A26: 213510668 | B26: 2025 | C26: 2025-02-12 | D26: NC Interne | E26: LIGNE-DQN | F26: V4V115 | G26: QRT/DERICHEBOURG AERONAUTICS | H26: Support lacote petit routes 1S et 2S | J26: 1023996325
A27: 215109338 | B27: 2025 | C27: 2025-09-18 | D27: CONTROLE FINAL | E27: REW-LIGNE-F | F27: F4F015 | G27: QLOK310/AIRBUS OPERATIONS SAS | H27: S/N TEMP SELECTOR non conforme | I27: [TS_000000001019419485] | J27: 1025848561
A28: 215451241 | B28: 2025 | C28: 2025-10-23 | D28: NC Interne | E28: REC-RWK | F28: F42RC1 | G28: QR/DERICHEBOURG AERONAUTICS | H28: CPB NOK | J28: 1026915093
A29: 215030360 | B29: 2025 | C29: 2025-09-10 | D29: CONTROLE FINAL | E29: REW-LIGNE-M | F29: M4MOHF | G29: QLOT1/AIRBUS OPERATIONS SAS | H29: impossibilité d'appliquer torquage rampe | J29: 1025486392
A30: 215372645 | B30: 2025 | C30: 2025-10-15 | D30: NC Interne | E30: REW-LIGNE-F | F30: F4F74E | G30: QR/DERICHEBOURG AERONAUTICS | H30: ERREUR MONTAGE DECOUPLING UNIT | J30: 1026113365
A31: 214388588 | B31: 2025 | C31: 2025-06-11 | D31: CONTROLE FINAL | E31: REW-LIGNE-F | F31: F4F034 | G31: QLOT1/AIRBUS OPERATIONS SAS | H31: Vis endommagée sur fourreau | J31: 1025196094
A32: 213884687 | B32: 2025 | C32: 2025-04-01 | D32: CABLES | E32: REW-CA-IMP-V | F32: V4V120 | G32: QLOT1/AIRBUS OPERATIONS SAS | H32: cable trop court | J32: 1024388395
A33: 215191868 | B33: 2025 | C33: 2025-09-26 | D33: CONTROLE FINAL | E33: REW-LIGNE-F | F33: F4F012 | G33: QLOK310/AIRBUS OPERATIONS SAS | H33: TEMP.SELECTOR avec deux CT176 | I33: [TS_000000001020577721] | J33: 1026106139
A34: 213973964 | B34: 2025 | C34: 2025-04-11 | D34: CABLES | E34: REW-CA-IMP-F | F34: F4F74A | G34: QLOT1/AIRBUS OPERATIONS SAS | H34: CABLE MANQUANT | J34: 1024517181
A35: 213666329 | B35: 2025 | C35: 2025-03-04 | D35: CABLES | E35: REW-CA-IMP-V | F35: V4V120 | G35: QLOT1/AIRBUS OPERATIONS SAS | H35: câble endommagé | J35: 1023833666
A36: 213559949 | B36: 2025 | C36: 2025-02-19 | D36: CABLES | E36: REW-CA-IMP-V | F36: V42RA1 | G36: QLOT1/AIRBUS OPERATIONS SAS | H36: Cable manquant
A37: 214352478 | B37: 2025 | C37: 2025-06-05 | D37: CONTROLE FINAL | E37: REW-LIGNE-F | F37: F4F038 | G37: QLOT1/AIRBUS OPERATIONS SAS | H37: Vis du fourreau 5WW2 endommagées | J37: 1025084201
A38: 215620253 | B38: 2025 | C38: 2025-11-10 | D38: CONTROLE FINAL | E38: REW-LIGNE-V | F38: V4V141 | G38: QLOT1/AIRBUS OPERATIONS SAS | H38: NC en attente réponse BE (DQN) | J38: 1026370581
A39: 213655218 | B39: 2025 | C39: 2025-03-03 | D39: CABLES | E39: REW-CA-IMP-V | F39: V42110 | G39: QRT/DERICHEBOURG AERONAUTICS | H39: Câble trop court et Abimé
A40: 213628687 | B40: 2025 | C40: 2025-02-27 | D40: NC Interne | E40: REW-LIG-ST-V | F40: V42120 | G40: OLMEP1/ERMA ELECTRONIQUE | H40: Cable 2792-0994 abîmé
A41: 215500224 | B41: 2025 | C41: 2025-10-28 | D41: NC Interne | E41: REGROUP-DQN | F41: M4M30C | G41: QLOT1/AIRBUS OPERATIONS SAS | H41: TORQUAGE BARRETTE 315VT | I41: [TS_000000001020387999] | J41: 1026099937
A42: 214750407 | B42: 2025 | C42: 2025-07-23 | D42: CONTROLE FINAL | E42: REW-LIGNE-V | F42: V42120 | G42: QLOT1/AIRBUS OPERATIONS SAS | H42: Mauvaise servitude de contact | J42: 1025774755
A43: 213666138 | B43: 2025 | C43: 2025-03-04 | D43: CABLES | E43: REW-CA-IMP-V | F43: V4V211 | G43: QLOT1/AIRBUS OPERATIONS SAS | H43: cable trop court | J43: 1023936277
A44: 214068791 | B44: 2025 | C44: 2025-04-25 | D44: NC Interne | E44: REW-LIG-ST-V | F44: V4VMIA | G44: OLMEP1/ERMA ELECTRONIQUE | H44: câble bifilaire 2792-0144 court | J44: 1024733455
A45: 215499712 | B45: 2025 | C45: 2025-10-28 | D45: CONTROLE FINAL | E45: REW-LIGNE-V | F45: V4V141 | G45: QLOT1/AIRBUS OPERATIONS SAS | H45: Datum Marker clamp non conforme à la DS | J45: 1026198626
A46: 215883039 | B46: 2025 | C46: 2025-12-05 | D46: NC Interne | E46: REGROUP-DQN | F46: V42140 | G46: QLOT1/AIRBUS OPERATIONS SAS | H46: Demande DQN Ecart gaine de réserve | J46: 1027427739
A47: 214128334 | B47: 2025 | C47: 2025-05-06 | D47: CONTROLE FINAL | E47: REW-LIGNE-V | F47: V4V115 | G47: QLOT1/AIRBUS OPERATIONS SAS | H47: Mesures des points de masse sur platines | J47: 1024388641
A48: 215631480 | B48: 2025 | C48: 2025-11-11 | D48: NC Interne | E48: REW-LIGNE-V | F48: V4V141 | G48: QRT/DERICHEBOURG AERONAUTICS | H48: NC en attente réponse BE (DQN) | J48: 1026288726
A49: 213510190 | B49: 2025 | C49: 2025-02-12 | D49: NC Interne | E49: LIGNE-DQN | F49: V4V115 | G49: QRT/DERICHEBOURG AERONAUTICS | H49: Support Route 1M et 2M non adaptés | J49: 1023996316
A50: 213564809 | B50: 2025 | C50: 2025-02-19 | D50: NC Interne | E50: REW-LIG-ST-V | F50: V4V120 | G50: OLMEP1/ERMA ELECTRONIQUE | H50: Câble DR24 2797-1114 trop court
A51: 215727969 | B51: 2025 | C51: 2025-11-20 | D51: NC Interne | E51: REGROUP-DQN | F51: V4VMIA | G51: QLOT1/AIRBUS OPERATIONS SAS | H51: Demande de DQN Plaquette identification | I51: [TS_000000001021059323] | J51: 1027175164
A52: 215564181 | B52: 2025 | C52: 2025-11-04 | D52: CONTROLE FINAL | E52: REW-LIGNE-F | F52: F4F034 | G52: QLOK310/AIRBUS OPERATIONS SAS | H52: Fixation endommagée | J52: 1026985103
A53: 215208136 | B53: 2025 | C53: 2025-09-29 | D53: TEST | E53: REW-TEST-F | F53: F4F038 | G53: OLMEP14/AIRBUS OPERATIONS SAS | H53: Retouche Test 412VU MSN 02136. | J53: 1026308100

Sheet H6_OrdersNoTime
A1: H6. Rework orders with no planned time (September 2026)
A2: S03 rework orders whose operations carry no standard value. If planned time is the truth, these orders cost 0, which cannot be right.
A4: Questions: why do these orders have no standard value (operations created without time, closed without confirmation, time booked elsewhere)? Until known, the CNQ uses the model's estimate for NCs whose order has no planned time. 63 of the 249 shop-floor rework orders (25%) are in this case.
A6: Rework order | B6: Family | C6: Programme | D6: MSN | E6: Linked NC | F6: NC type | G6: NC: what was found | H6: Work centre(s) | I6: Operations | J6: Why no time? (your finding) | K6: Comment
A7: 1030448899 | B7: FTO2 shop floor | C7: A330 | D7: 2169 | E7: 217899785 | F7: CABLES | G7: CABLES MANQUANTS | H7: Attestation de conformitÃ© / Inspection fabrication elec | I7: Attestation de conformité || Inspection Qualité
A8: 1030475889 | B8: FTO2 shop floor | C8: A330 | D8: 2166 | E8: 217913295 | F8: NC Interne | G8: INVERSEUR H.S. | H8: Attestation de conformitÃ© / Inspection fabrication elec | I8: Attestation de conformité || Inspection Qualité
A9: 1030621326 | B9: FTO2 shop floor | C9: A330 | D9: 2166 | E9: 218016079 | F9: TEST | G9: CABLES A CHANGER | H9: Attestation de conformitÃ© / Inspection fabrication elec | I9: Attestation de conformité || Inspection Qualité
A10: 1030623390 | B10: FTO2 shop floor | C10: A350 | D10: 870 | E10: 218020323 | F10: CABLES | G10: Câbles trop courts | H10: Attestation de conformitÃ© / Inspection fabrication elec | I10: Attestation de conformité || Inspection Qualité
A11: 1030721063 | B11: FTO2 shop floor | C11: A330 | D11: 2167 | E11: 218067875 | F11: CONTROLE FINAL | G11: RETOUCHE CONTROLE FINAL | H11: Attestation de conformitÃ© / Inspection fabrication elec | I11: Attestation de conformité || Inspection Qualité
A12: 1030721069 | B12: FTO2 shop floor | C12: A330 | D12: 2167 | E12: 218067687 | F12: CONTROLE FINAL | G12: RETOUCHE CONTROLE FINAL | H12: Attestation de conformitÃ© / Inspection fabrication elec | I12: Attestation de conformité || Inspection Qualité
A13: 1030721510 | B13: FTO2 shop floor | C13: A330 | D13: 2167 | E13: 218070160 | F13: TEST | G13: INTERDIT CASSE | H13: Attestation de conformitÃ© / Inspection fabrication elec | I13: Attestation de conformité || Inspection Qualité
A14: 1030736570 | B14: FTO2 shop floor | C14: A350 | D14: 868 | E14: 218078858 | F14: CABLES | G14: Câble KL coupé trop court | H14: Attestation de conformitÃ© / Inspection fabrication elec | I14: Attestation de conformité || Inspection Qualité
A15: 1030740403 | B15: FTO2 shop floor | C15: A330 | D15: 2167 | H15: Attestation de conformitÃ© / Inspection fabrication elec | I15: Attestation de conformité || Inspection Qualité
A16: 1030763128 | B16: FTO2 shop floor | C16: A350 | D16: 868 | E16: 218094742 | F16: CABLES | G16: Mauuvaise MOE serre module NSA937901S | H16: Attestation de conformitÃ© / Inspection fabrication elec | I16: INSPECTION QUALITE || ATTESTATION DE CONFORMITE ATTESTATION DE CONFORMITE Inspection avant la clôture de l'OF
A17: 1030781941 | B17: FTO2 shop floor | C17: A350 | D17: 872 | E17: 218113625 | F17: CABLES | G17: Câble trop court | H17: Attestation de conformitÃ© / Inspection fabrication elec | I17: Attestation de conformité || Inspection Qualité
A18: 1030818117 | B18: FTO2 shop floor | C18: A350 | D18: 856 | E18: 218121468 | F18: NC Retour client | G18: CKPT*C1*L22/23*G*Gaine écrasée*BA@* | H18: Attestation de conformitÃ© / Inspection fabrication elec | I18: Attestation de conformité || Contrôle du KIT(s) avant le départ pour Contrôle du KIT(s) avant le départ pour Montoir-de-Bretagne Suite à la NC 218121468, veuillez contrôler la conformité du kit avant le départ pour Montoir-de-Bretagne suivant la list
A19: 1030818179 | B19: FTO2 shop floor | C19: A350 | D19: 856 | E19: 218121463 | F19: NC Retour client | G19: CKPT*C1*L22/21*D*Gaine écrasée*BA@* | H19: Attestation de conformitÃ© / Inspection fabrication elec | I19: Attestation de conformité || Contrôle du KIT(s) avant le départ pour Contrôle du KIT(s) avant le départ pour Montoir-de-Bretagne Suite à la NC 218121463, veuillez contrôler la conformité du kit avant le départ pour Montoir-de-Bretagne suivant la list
A20: 1030938126 | B20: FTO2 shop floor | C20: A350 | D20: 865 | E20: 218213110 | F20: TEST | G20: RETOUCHE TEST PRISE DETERIORE | H20: A350-REC-S/T-Attestation Conformité / Basic Electrical harness manufacturing / Réaliser Inspection | I20: Attestation de conformité Attestation de conformité Inspection avant la clôture de l'OF || Inspection Qualité || Remise en conformités de la prise 20TC1 Remise en conformités de la prise 20TC1 A Veuillez Appliquer la NSI joint à la S03.
A21: 1030985640 | B21: FTO2 shop floor | C21: A350 | D21: 866 | E21: 218242503 | F21: TEST | G21: RETOUCHE TEST MSN 866 TWINAX A REFAIRE | H21: A350-REC-S/T-Attestation Conformité / Basic Electrical harness manufacturing / Réaliser Inspection | I21: Attestation de conformité || Inspéction Qualité Inspéction Qualité NC CABLE - Inspection Qualité SI NC TA --> 4QEH1I07 NC TEST - Inspection Qualité --> 4QEH5I07 NC QUALITÉ - Inspection Qualité --> 4QEH8I07 NC CABLE - Inspection Qualité SI NC TB --> 4
A22: 1030986429 | B22: FTO2 shop floor | C22: A350 | D22: 876 | E22: 218246376 | F22: CABLES | G22: Câbles non lasérisés | H22: A350-REC-S/T-Attestation Conformité / Basic Electrical harness manufacturing | I22: Attestation de conformité || PRELEVEMENT MSN 878 VERS MSN 876 PRELEVEMENT MSN 878 VERS MSN 876 S03 suite à la NC 218246376 : Prélèvement des câbles du MSN 878 vers le MSN 876 sous ISOCONF identique (Accord BP)
A23: 1030989646 | B23: FTO2 shop floor | C23: A350 | D23: 858 | E23: 218221555 | F23: NC Retour client | G23: ATT*FB*C6*L25*D*Mauvais backshell *LA@* | H23: Attestation de conformitÃ© / Inspection fabrication elec | I23: Contrôle du KIT(s) avant le départ pour Contrôle du KIT(s) avant le départ pour Montoir-de-Bretagne Suite à la NC 218221555, veuillez contrôler la conformité du kit avant le départ pour Montoir-de-Bretagne suivant la liste ci-dessous : Désignation /
A24: 1031170705 | B24: FTO2 shop floor | C24: A350 | D24: 728 | E24: 218348034 | F24: NC Retour client | G24: CKPT*C7/8*L24/25*D*Mauvais Backshell*FB* | H24: Attestation de conformitÃ© / Inspection fabrication elec | I24: Attestation de conformité || Contrôle du KIT(s) avant le départ pour Contrôle du KIT(s) avant le départ pour Montoir-de-Bretagne Suite à la NC 218348034, veuillez contrôler la conformité du kit avant le départ pour Montoir-de-Bretagne suivant la list
A25: 1031171305 | B25: FTO2 shop floor | C25: A350 | D25: 856 | E25: 218348243 | F25: NC Retour client | G25: CKPT*C7/8*L24/25*D*Mauvais Backshell*FB* | H25: Attestation de conformitÃ© / Inspection fabrication elec | I25: Contrôle du KIT(s) avant le départ pour Contrôle du KIT(s) avant le départ pour Montoir-de-Bretagne Suite à la NC 218348243, veuillez contrôler la conformité du kit avant le départ pour Montoir-de-Bretagne suivant la liste ci-dessous : Désignation /
A26: 1031220048 | B26: FTO2 shop floor | C26: A350 | D26: 857 | E26: 218390076 | F26: NC Retour client | G26: CKPT*C7/8*L24/25*D*Mauvais Backshell*FB* | H26: Attestation de conformitÃ© / Inspection fabrication elec | I26: Attestation de conformité || Contrôle du KIT(s) avant le départ pour Contrôle du KIT(s) avant le départ pour Montoir-de-Bretagne Suite à la NC 218390076, veuillez contrôler la conformité du kit avant le départ pour Montoir-de-Bretagne suivant la list
A27: 1031227280 | B27: FTO2 shop floor | C27: A350 | D27: 858 | E27: 218390072 | F27: NC Retour client | G27: CKPT*C7/8*D&G*Mauvais Backshell*FB* | H27: Attestation de conformitÃ© / Inspection fabrication elec | I27: Contrôle du KIT(s) avant le départ pour Contrôle du KIT(s) avant le départ pour Montoir-de-Bretagne Suite à la NC 218390072, veuillez contrôler la conformité du kit avant le départ pour Montoir-de-Bretagne suivant la liste ci-dessous : Désignation /
... A29: 1031227573 | B29: FTO2 shop floor | C29: A350 | D29: 861 | E29: 218390345 | F29: NC Retour client | G29: CKPT*C7/8*D&G*Mauvais Backshell*FB* | H29: Attestation de conformitÃ© / Inspection fabrication elec | I29: Contrôle du KIT(s) avant le départ pour Contrôle du KIT(s) avant le départ pour Montoir-de-Bretagne Suite à la NC 218390345, veuillez contrôler la conformité du kit avant le départ pour Montoir-de-Bretagne suivant la liste ci-dessous : Désignation /
A30: 1029645893 | B30: FTO2 shop floor | C30: A350 | D30: 701 | H30: Attestation Conformité / Basique fabrication Electrique / Inspection qualité | I30: ATTESTATION DE CONFORMITE || CONTROLE CONTROLE Cet OT est en // de l'OF 1028559128 (FB37531) || Veuillez installer les documents A3 plas Veuillez installer les documents A3 plastifié sur les portes avants, près du trailing cone et près dy FTES avec d
A31: 1030618214 | B31: FTO2 shop floor | C31: A350 | D31: 867 | H31: A350-REC-S/T-Attestation Conformité | I31: Attestation de conformité
A32: 1030699591 | B32: FTO2 shop floor | C32: A350 | D32: 870 | H32: A350-REC-S/T-Attestation Conformité / Basic Electrical harness manufacturing / Réaliser Inspection | I32: Attestation de conformité || Inspection Qualité || ONTROLER SERTISSAGE CDVE tête A || Remise en conformités du câble Remise en conformités du câble Cheminer le câble vers la tête B. S'appuyer des informations décrites suivant la définition sur ElecAB
A33: 1030754959 | B33: FTO2 shop floor | C33: A350 | D33: 865 | H33: A350-REC-S/T-Attestation Conformité | I33: Attestation de conformité
A34: 1030755222 | B34: FTO2 shop floor | C34: A350 | D34: 871 | H34: A350-REC-S/T-Attestation Conformité / Basic Electrical harness manufacturing / Réaliser Inspection | I34: Attestation de conformité || Inspection Qualité || NC CABLE - Remise en conformités du câbl NC CABLE - Remise en conformités du câble Effectuer le dénudage / sertissage du câble en tête A suivant les informations de la définition sur ElecABC/NIICE. E
A35: 1030780734 | B35: FTO2 shop floor | C35: A350 | D35: 872 | H35: A350-REC-S/T-Attestation Conformité / Réaliser Inspection | I35: Attestation de conformité || Inspection Qualité || CONTROLER SERTISSAGE CDVE
A36: 1030780933 | B36: FTO2 shop floor | C36: A350 | D36: 700 | H36: ATTESTATION DE CONFORMITE S/T / Attestation Conformité / Fabrication Harnais Electrique | I36: Attestation de conformité || Intallation support supplémentaires : Intallation support supplémentaires : Localisation: Cadre 72 AFT-US - Cadre-77-AFT-US. Latch Top AFT, Button AFT, TOP FWD et Button FWD. Montez le NSA935405-01 sur la poutre de verrou
A37: 1030791966 | B37: FTO2 shop floor | C37: A330 | D37: 2166 | H37: Attestation de conformitÃ© / Contrôle impression | I37: Inspection Qualité || Attestation de conformité
A38: 1030793434 | B38: FTO2 shop floor | C38: A350 | D38: 700 | H38: ATTESTATION DE CONFORMITE S/T / Attestation Conformité / Fabrication Harnais Electrique | I38: Attestation de conformité || CONTROLER || Remise en conformité. || Analyse de dossier : Analyse de dossier : Localisation : cadres 57/58 et 31/32 coté droit. Merci de refaire le routing au scotch alu sur les Linings en MD.
A39: 1030804587 | B39: FTO2 shop floor | C39: A350 | D39: 868 | H39: A350-REC-S/T-Attestation Conformité / Basic Electrical harness manufacturing / Réaliser Inspection | I39: Attestation de conformité || Inspection Qualité || Remise en conformités du câble Remise en conformités du câble Effectuer le sertissage du câble en tête A et tête B suivant les informations de la définition sur ElecABC/NIICE. Effectuer le branchemen
A40: 1030807762 | B40: FTO2 shop floor | C40: A320 | D40: 6101 | H40: Attestation Conformité / Fabrication Harnais Electrique / Inspection qualité | I40: ATTESTATION DE CONFORMITE || CONTROLER || PREPARATION / ANALYSE DOSSIER || Repose DD253 S/N 25109 et 2511 4ZU Repose DD253 S/N 25109 et 2511 4ZU Veuillez installer les équipements DD253 FIN : 253ZSC2 SN : 25109 ainsi que, FIN : 253ZSC1 SN : 25110 Veu
A41: 1030819680 | B41: FTO2 shop floor | C41: A350 | D41: 701 | H41: Attestation Conformité / Fabrication Harnais Electrique / Inspection qualité | I41: Attestation de conformité || Remise en conformité 743ZVC102-A Remise en conformité 743ZVC102-A Sur la prise 743ZVC102-A Inversion de câblage entre les pin 21,22,23 et 24. Veuillez vous mettre en conformité par rapport au WD V89596412-81. || Contrôle
... A85: 1030742346 | B85: REC (FAL) | C85: A350 | D85: 836 | H85: ATTESTATION OF CONFORMITY / ATTESTATION OF CONFORMITY AUTOCLOSURE / Inspecter installation électri | I85: Inspection avant la clôture de l'OF || Stop point : Attendre Inter. nettoyage || Attestation de conformité Attestation de conformité Controle des points suivants : Toutes les opérations ont été terminées et certifiées Aucun écart évident, manquant ou

Sheet H7_DisruptExport
A1: H7. Is the disruption export complete? (2,500 rows)
A2: The file has exactly 2,500 rows, sorted newest first: the pattern of an export cut at a row limit.
A4: Rows in the file | B4: 2500
A5: First disruption | B5: 2026-01-05 08:57:14
A6: Last disruption | B6: 2026-09-30 23:31:51
A7: File order | B7: newest first (30 Sep 23:31 on the first row)
A8: NCs created 29 Dec 2025 - 2 Jan 2026 (plant closed?) | B8: 0
A9: First NC of 2026 | B9: 5 Jan 2026 (same day as the first disruption)
A10: Usual time of the first disruption of a day | B10: about 07:43
A11: Time of the first disruption on 5 Jan | B11: 08:57 (9 disruptions that day; a usual Monday has about 14)
A13: How to check (any one is enough):
A14: 1. Re-export the disruptions with only 1 Jan - 31 Mar 2026 selected. If 5 January gets more than 9 rows, or rows before 08:57, the first export was cut.
A15: 2. Look in the export tool (Skywise / Contour) for a row limit or a 'first N rows' setting.
A16: 3. Count the disruptions in MES for 5 January 2026 and compare with 9.
A18: Check | B18: Result (your finding) | C18: Export complete? (Y/N)
A19: Re-export Jan-Mar: rows on 5 Jan
A20: Row limit in the export tool
A21: MES count for 5 Jan
A23: Disruptions per day, first two weeks of the file
A24: 2026-01-05 | B24: 9
A25: 2026-01-06 | B25: 26
A26: 2026-01-07 | B26: 14
A27: 2026-01-08 | B27: 18
A28: 2026-01-09 | B28: 10
A29: 2026-01-12 | B29: 28
A30: 2026-01-13 | B30: 19
A31: 2026-01-14 | B31: 38
A32: 2026-01-15 | B32: 18
A33: 2026-01-16 | B33: 5
A35: Time columns: time_lost is typed by the operator (minutes). time_to_get_ack / time_to_get_fix do not match the timestamps (1-2 h time-zone shift; time_to_get_fix is 0 for 64%).

Sheet D_Block
A1: Disruption block (option B): quality aléas that did not lead to an NC
A2: MES disruptions of type 'QLS - Probleme qualite', Jan-Sep 2026, with no NC on the same work order within -2 h..+72 h. Aléas that led to an NC are inside the NC cost (alert step), not here.
A4: Pre-filled Y for every row. Put N for an aléa that should not count (for example, its NC exists but is written by ERMA, which is out of scope). The totals below and in Figures follow.
A6: Disruption | B6: Opened | C6: Month (yyyymm) | D6: Line | E6: Station | F6: Work order | G6: Time lost (min) | H6: What the operator wrote | I6: Answer | J6: Possible ERMA NC (MIP / 1101VB) | K6: Keep in block? (Y/N) | L6: Comment
A7: OZ1780938 | B7: 2026-01-05 08:57 | C7: 202601 | D7: A30 | E7: INTEG2 | F7: 1027044105 | G7: 60 | H7: Impossibilité de monter la Pipe V2511259700000 suite a un montage non conforme fournisseur. | K7: Y
A8: OZ1783404 | B8: 2026-01-06 14:30 | C8: 202601 | D8: MDCD | E8: HARNAIS_MDCD | F8: 1027383554 | G8: 360 | H8: 2 formations réalisé , mesure lineique , recherche de gamme | K8: Y
A9: OZ1785059 | B9: 2026-01-07 12:23 | C9: 202601 | D9: 740VU_743VU | E9: INTE 740VU | F9: 1027341953 | G9: 72 | H9: Changement de deux câbles sur la platine relais temps perdu 2h | K9: Y
A10: OZ1785431 | B10: 2026-01-07 14:47 | C10: 202601 | D10: MDCD | E10: HARNAIS_MDCD | F10: 1027383554 | G10: 330 | H10: Recherche de gamme | K10: Y
A11: OZ1788106 | B11: 2026-01-08 14:47 | C11: 202601 | D11: MDCD | E11: HARNAIS_MDCD | F11: 1027383554 | G11: 330 | H11: recherche de gamme et manque de temps | K11: Y
A12: OZ1790476 | B12: 2026-01-09 13:59 | C12: 202601 | D12: A30 | E12: INTEG2 | F12: 1027175460 | G12: 60 | H12: Manque câble : AD22 : 3422-0191 ET AD22 : 3422-0190 (INFO longueur etc : VOIR IMAGES) | K12: Y
A13: OZ1793801 | B13: 2026-01-12 21:18 | C13: 202601 | D13: 740VU_743VU | E13: CHEMINE SHUNT 740VU | F13: 1027542382 | G13: 7 | H13: Manchon imprimé MSN : 2145 OF : 1027542382 Numéro : 2458-0158 Qté : 1 Type : Manchon numéro de câble | K13: Y
A14: OZ1799496 | B14: 2026-01-14 23:18 | C14: 202601 | D14: A30 | E14: INTEG1 | F14: 1027315420 | G14: 120 | H14: Bonjour, j'ai eu un problème sur mon OP, voir deux... 1) Plusieurs mauvais sertissages ( que j'ai repris ) 2) Recherche dans la S.O.I pour trouver la bonne fixation à appliquer sur les VN & (torquage)... non référencé dans la S.O.I | K14: Y
A15: OZ1806056 | B15: 2026-01-19 17:03 | C15: 202601 | D15: A30 | E15: INTEG1 | F15: 1027320098 | G15: 60 | H15: Colonnette endommagé sur la prise 3CB-A MSN817 poste Inté1 | K15: Y
A16: OZ1806552 | B16: 2026-01-19 20:40 | C16: 202601 | D16: A30 | E16: SSENS4 | F16: 1027717179 | G16: 90 | H16: Bonsoir MSN : 846 RT 1 R OF : 1027717179 Cable abimée AD 24 longueur 232 CM MERCI . | K16: Y
A17: OZ1819701 | B17: 2026-01-26 20:55 | C17: 202601 | D17: A30 | E17: INTEG1 | F17: 1027399407 | G17: 13 | H17: Bonsoir, Merci de bien vouloir créer une NC svp suite à une colonnette qui a cédé lors du torquage de la prise 3CB-A du MIP 819, En vous remerciant, | K17: Y
A18: OZ1822351 | B18: 2026-01-27 20:56 | C18: 202601 | D18: PTVU | E18: MECANIQUE | F18: 1027711744 | G18: 7 | H18: Rail VT tordu, suite à l'alerte Qualité faut-il faire une CT129 ? | K18: Y
A19: OZ1826935 | B19: 2026-01-29 15:55 | C19: 202601 | D19: PTVU | E19: MECANIQUE | F19: 1027711844 | G19: 7 | H19: Un équipement à été servis avec les 19 autres et il a la même ref ABS0064-01 et cms 7388650204 mais n'a pas le même disign (pointe sur le dessus) que tous les autres puis il a aussi des différences sur les autres ref inscrites dessus (voir photos). Vu que c'est un aspect différent des autres pour l'uniformisation peut-on quand même le monter ? | K19: Y
A20: OZ1828564 | B20: 2026-01-30 09:24 | C20: 202601 | D20: IMPRESSION_A320 | E20: FAISCEAU RECHANGE_A320 | G20: 60 | H20: Etiquettes autocollantes 40x46 mm utilisées notamment pour les faisceaux F900.00954.888.95 et F900.00954.887.95 ne collent pas assez et se détachent. | K20: Y
A21: OZ1848430 | B21: 2026-02-10 17:44 | C21: 202602 | D21: PTVU | E21: MECANIQUE | F21: 1027849736 | G21: 6 | H21: prise hs, changer (le TL m'en a apporter un nouveau) | K21: Y
A22: OZ1851957 | B22: 2026-02-11 21:28 | C22: 202602 | D22: A30 | E22: MECA | F22: 1027848096 | G22: 0 | H22: ON NE PEUT TOUJOURS PAS FAIRE LA SAISIE D OUTIL DEPUIS MSN823 | K22: Y
A23: OZ1852109 | B23: 2026-02-11 23:27 | C23: 202602 | D23: PTVU | E23: MECANIQUE | F23: 1028218156 | G23: 7 | H23: peinture bleu face avant écaillée au trou VN | K23: Y
A24: OZ1861152 | B24: 2026-02-17 14:24 | C24: 202602 | D24: A30 | E24: INTEG1 | F24: 1028305007 | G24: 120 | H24: Changement de support route 2M MSN 831 Remise au propre des câbles. | K24: Y
A25: OZ1868168 | B25: 2026-02-20 08:36 | C25: 202602 | D25: IMPRESSION_A330 | E25: ETIQUETTES + MANCHONS_A330 | G25: 60 | H25: Faisceaux rechanges F900.00954.888.95I et F900.00954.887.95I Les étiquettes autocollantes positionnées sur les câbles se décollent et tombent. | K25: Y
A26: OZ1875389 | B26: 2026-02-25 08:03 | C26: 202602 | D26: A30 | E26: MECA | F26: 1028041621 | G26: 60 | H26: Platine V9241920800000 A00 endommagé prélevé sur MSN834 NC en cours | K26: Y
A27: OZ1890013 | B27: 2026-03-04 14:02 | C27: 202603 | D27: A30 | E27: SSENS_S1 | F27: 1028259874 | G27: 60 | H27: CABLE ABIME PAR TETE A ERMA PRISE 1608VC019 NC PRISE EN COMPTE PAR ERMA | K27: Y
A28: OZ1897602 | B28: 2026-03-09 13:12 | C28: 202603 | D28: A30 | E28: MECA | F28: 1028259713 | G28: 60 | H28: NON METALISE | I28: Fait par l'opérateur | K28: Y
A29: OZ1909961 | B29: 2026-03-15 11:36 | C29: 202603 | D29: A30 | E29: INTEG2 | F29: 1027963079 | G29: 0 | H29: Suite a Aléa OZ1897649, la qualité a t'elle statué? Constat de désaffleurement sur le rivet à frapper au niveau de la plage de la 300VN359 (voir pièce jointe). Attente statut pour installer la VN. Acceptable ou création de NC, intervention CIB. | K29: Y
A30: OZ1915409 | B30: 2026-03-17 21:28 | C30: 202603 | D30: A30 | E30: INTEG1 | F30: 1028434441 | G30: 0 | H30: bonjour, la nouvelle livraison de plaquettes présente une différence sur les plaquettes d'ensemble notées "V92931101000 WF201/1101VB SER". Le SER est placé à gauche de la dernière ligne alors qu'il était au milieu jusqu'alors, est-ce une non conformité? doit-on déjà conserver les anciennes plaquettes en surnombre sur les msn précédents le 839? et si la nouvelle disposition est correcte, le PB peut | K30: Y
A31: OZ1916115 | B31: 2026-03-18 08:51 | C31: 202603 | D31: A30 | E31: INTEG1 | F31: 1028139158 | G31: 15 | H31: Bonjour, Merci de bien vouloir créer une NC suite à une erreur de vis, un écrou riveté est endommagé sur le MIP 835 intégration 1, Merci, | K31: Y
A32: OZ1923144 | B32: 2026-03-20 21:42 | C32: 202603 | D32: A30 | E32: INTEG1 | F32: 1028259994 | G32: 0 | H32: Tuyauterie endommagé au montage prélevée pour MSN 834. | I32: Tuyauterie conforme | K32: Y
A33: OZ1927807 | B33: 2026-03-24 14:10 | C33: 202603 | D33: A30 | E33: MECA | F33: 1028041859 | G33: 60 | H33: rail de vt défectueux tordu V92931101000 PRELEVE SUR MSN844 POUR MSN835 | K33: Y
A34: OZ1937210 | B34: 2026-03-28 08:40 | C34: 202603 | D34: PTVU | E34: MECANIQUE | F34: 1028739402 | G34: 7 | H34: pas l outillage nécessaire pour torquer les lampes E0430-02 | K34: Y
A35: OZ1948066 | B35: 2026-04-02 18:58 | C35: 202604 | D35: A30 | E35: MECA | F35: 1028522326 | G35: 60 | H35: NON METALLISEES comme l avion precedent vu avec manu la fois d avant | K35: Y
A36: OZ1948068 | B36: 2026-04-02 19:01 | C36: 202604 | D36: A30 | E36: MECA | F36: 1028522338 | G36: 60 | H36: Le support sur la rampe mal serti comme l autre fois a croire que c est la meme rampe qui est revenue sur l avion d apres.... | K36: Y
A37: OZ1950308 | B37: 2026-04-03 15:18 | C37: 202604 | D37: 740VU_743VU | E37: TA 742VU | F37: 1028821309 | G37: 7 | H37: Raison: mauvaise jauge de câble. 2434-0002 DRC12 300cm | K37: Y
A38: OZ1950989 | B38: 2026-04-05 11:35 | C38: 202604 | D38: A30 | E38: INTEG2 | F38: 1028041917 | G38: 3 | H38: Tuyauterie fournisseur au dessus de la 1WK12-A étiquette référence et stamp décollé. Demande avis QLS. Rail 500VT200 déformé, demande avis qualité également. | K38: Y
A39: OZ1955084 | B39: 2026-04-08 12:39 | C39: 202604 | D39: PTVU | E39: MECANIQUE | F39: 1028960434 | G39: 7 | H39: Pas d'outils pour torquer à la valeur nominale 0.225 | K39: Y
A40: OZ1957281 | B40: 2026-04-09 09:50 | C40: 202604 | D40: 740VU_743VU | E40: INTE 740VU | F40: 1028572610 | G40: 0 | H40: TEST | K40: Y
A41: OZ1957798 | B41: 2026-04-09 12:30 | C41: 202604 | D41: E-RUDDER_A320 | E41: TETE A_A320 | F41: 1029074623 | G41: 11 | H41: Pour la mise en œuvre des auto soudeurs sur les câbles blindés, sur la traçabilité des outils on ne nous demande pas l'infrarouge. Voir pour le faire rajouter svp. Merci. | K41: Y
A42: OZ1958836 | B42: 2026-04-09 18:50 | C42: 202604 | D42: A30 | E42: INTEG2 | F42: 1028434456 | G42: 60 | H42: Problème sur toutes les plaquettes 1WK mauvais marquage de plaquette | K42: Y
A43: OZ1961259 | B43: 2026-04-10 16:58 | C43: 202604 | D43: A30 | E43: MECA | F43: 1028348065 | G43: 60 | H43: Bonjour. A quand de montage des éléments dans le platine V9241959500000, je remarque que la même il' Ya 2 petites impacte au niveau da RAMP. Voici la photo annexé pour meilleur voir. Merci et bonne journée | K43: Y
A44: OZ1969972 | B44: 2026-04-15 23:54 | C44: 202604 | D44: A30 | E44: INTEG2 | F44: 1028522354 | G44: 30 | H44: bonjour, nous avons une colonnette HS dans le pylone route 2M, merci d'avance. cordialement | K44: Y
... A47: OZ1992065 | B47: 2026-04-28 23:29 | C47: 202604 | D47: 740VU_743VU | E47: FABRICATION 743VU | F47: 1029062553 | G47: 7 | H47: Platine VG défectueuse réf F9251529400000 la VG ne se monte pas car filetage endommagé | K47: Y
A48: OZ1995533 | B48: 2026-04-30 10:33 | C48: 202604 | D48: 740VU_743VU | E48: MECANIQUE 740VU | F48: 1029148710 | G48: 15 | H48: Disjoncteur EN3661-005A35AB reçu sans écrou ni rondelle Kanban 26F-PW740 Casier 38 CMS 7173240039 | I48: Pris en compte, les autres du kanban sont a prioiri conforme. Je cloture donc l'incident | K48: Y
A49: OZ1995563 | B49: 2026-04-30 10:48 | C49: 202604 | D49: 740VU_743VU | E49: CHEMINEMENT 742VU | F49: 1029148722 | G49: 7 | H49: Cable manquant livraison. 2424-0053 DR24 200cm | K49: Y
A50: OZ1996292 | B50: 2026-04-30 14:42 | C50: 202604 | D50: A30 | E50: INTEG1 | F50: 1028657632 | G50: 8 | H50: Bonjour, Suite câbles abîmés, merci ce bien vouloir créer une NC afin de faire le remplacement des câbles svp, route 2S MIP 844, DR20 2781-0065 longueur 130 cms DR24 2751-0970 longueur 135 cms DR24 2781-0355 longueur 135 cms DR24 7325-0087 longueur 125 cms AD24 7835-0094 longueur 116 cms Merci, | K50: Y
A51: OZ1997045 | B51: 2026-04-30 23:28 | C51: 202604 | D51: 740VU_743VU | E51: CHEMINEMENT 742VU | F51: 1029148722 | G51: 7 | H51: MSN:2140 ( 742 VU ) OF: 109148722 cable manquant dr 20 longueur 240 2829-0030 | K51: Y
A52: OZ2002831 | B52: 2026-05-06 12:19 | C52: 202605 | D52: A30 | E52: SSENS4 | F52: 1028998503 | G52: 0 | H52: Cable trop court Cable DRB 24 numéros: 3313-0124 Longueur: 520 | K52: Y
A53: OZ2003175 | B53: 2026-05-06 14:19 | C53: 202605 | D53: E-RUDDER_A320 | E53: FABRICATION_A320 | F53: 1029305294 | G53: 0 | H53: Par la présente, nous réitérons l’urgence absolue concernant le remplacement des contreprises et des connecteurs sur les équipements RUDDER et MFRL. Malgré nos précédents signalements, la situation a évolué vers un stade de risque critique qui nécessite une action immédiate. 1. Constatations sur le terrain Présence de particules métalliques : Des dépôts de limaille (effritement de l’émail de fer) | I53: Pris en compte par équipe projet | K53: Y
A54: OZ2005623 | B54: 2026-05-07 14:21 | C54: 202605 | D54: A30 | E54: TETEA1 | G54: 36 | H54: Bonjour , j'ai une prise rectangle endommager , il est impossible d'enficher .Ref équipement :2306E12FP1A5 | I54: ok donner en prod | K54: Y
A55: OZ2006595 | B55: 2026-05-09 10:51 | C55: 202605 | D55: PTVU | E55: MECANIQUE | F55: 1029282394 | G55: 0 | H55: Etiquette autocollante 590VC abimée | I55: étiquette reçu et donnée à la prod | K55: Y
A56: OZ2010276 | B56: 2026-05-12 12:34 | C56: 202605 | D56: A30 | E56: INTEG1 | F56: 1028745430 | G56: 60 | H56: Bonjour. Suite casse back Shell 3CB-A ref. E0684E05FBN merci de bien vouloir crée une NC pour replacement prise prélevé du chariot du MSN 857. | I56: ok | K56: Y
A57: OZ2011668 | B57: 2026-05-12 22:58 | C57: 202605 | D57: E-RUDDER_A320 | E57: FABRICATION_A320 | F57: 1029305376 | G57: 24 | H57: NETTOYAGE DES CONTRES PRISES SUR TABLE DE CHEMINEMENT | K57: Y
A58: OZ2020544 | B58: 2026-05-20 09:08 | C58: 202605 | D58: MULTIPROGRAMME_A350 | E58: TRESSE DE MASSE | G58: 30 | H58: 20/05/2026 Poste Pièces élémentaires. Pour la fabrication des câbles de Masses Alu grosses sections. Deux câbles fournis sont endommagés et inutilisables pour l’OF concerné. Câbles Alu, Type AD3, de longueur 1010 mm. Gammes impactées : OF 57547818 (débit câble) OF 57532750 (Fabrication) En attente de deux nouveaux câbles. | K58: Y
A59: OZ2027531 | B59: 2026-05-22 18:10 | C59: 202605 | D59: A30 | E59: INTEG2 | F59: 1028998899 | G59: 30 | H59: Pipe endommagée au montage sur le MSN 848 prélevée sur le MSN 851. Pipe endommagée déposée sur bureau QLS Es-Salehy.R | K59: Y
A60: OZ2027570 | B60: 2026-05-22 19:11 | C60: 202605 | D60: 740VU_743VU | E60: CS 742VU | F60: 1029361317 | G60: 14 | H60: Sur porte 742VU, MSN2162. Port de branchement "B" H.S de a barette 709VT, module 1. Demande : Changement du module. | K60: Y
A61: OZ2027591 | B61: 2026-05-22 21:17 | C61: 202605 | D61: A30 | E61: SSENS2 | F61: 1029207721 | G61: 60 | H61: Bonjour, Câble coupé trop court sur la 20TC2A Câble N°4612-0350 KL24 Longueur : 320CM | K61: Y
A62: OZ2027685 | B62: 2026-05-23 10:52 | C62: 202605 | D62: A30 | E62: SSENS4 | F62: 1028998503 | G62: 60 | H62: Cable coupé trop court par l'operateur sur la 2M CDVE DR 24 Numéros: 2797-0602 Longueur : 540 Merci | K62: Y
A63: OZ2027875 | B63: 2026-05-25 15:56 | C63: 202605 | D63: A30 | E63: SSENS_S1 | F63: 1029207701 | G63: 0 | H63: Pièce manquante bonjour, les plaquettes des prises 7DG1-A et 8DG1-A (ref. E0248A2-6H9 ), imprimées afin de palier à la non-conformité des lots reçus, sont épuisées. Il est nécessaire d'en imprimer de nouveau, svp. merci henri | J63: Y | K63: Y
A64: OZ2030680 | B64: 2026-05-26 23:21 | C64: 202605 | D64: 740VU_743VU | E64: MECANIQUE 740VU | F64: 1029361481 | G64: 14 | H64: Pièce manquante msn 2163 of 1029361481 740vu ref f113.120123.000.00 probleme sur 5 lot etiquette manque 1er page etiquette de 2pc a 5xb . | K64: Y
A65: OZ2030717 | B65: 2026-05-26 23:50 | C65: 202605 | D65: 740VU_743VU | E65: CHEMINEMENT 742VU | F65: 1029361543 | G65: 7 | H65: MSN 2163 OF: 1029361543 742 VU PORTE CABLE MANQUANT DR 24 2911-0447 LONGUEUR: 220 | K65: Y
A66: OZ2034049 | B66: 2026-05-28 08:18 | C66: 202605 | D66: MULTIPROGRAMME_A320 | E66: SIMU_A320 | G66: 15 | H66: Pour les 59 VU, OF: 57499773 et 57513681 Il manque dans les blisters 1 support équipé D925.20133.000 Nous avons regardé L' ENS. Structure D925.20536.000.60, et il y est. Donc il manque 2 supports équipés au total qui n'étaient pas dans les blisters | I66: SERVITUDE OK | K66: Y
A67: OZ2044597 | B67: 2026-06-03 06:57 | C67: 202606 | D67: A30 | E67: SSENS1 | F67: 1029210892 | G67: 60 | H67: Pièce manquante BONJOUR OF:1029210892 MSN:855 ROUTE 1R PLAQUETTE DE LA PRISE 1706VC001 MANQUANTE (PRELEVEE POUR UN AUTRE MSN ET PAS REMPLACEE) | I67: servi | K67: Y
A68: OZ2048057 | B68: 2026-06-04 09:57 | C68: 202606 | D68: PTVU | E68: MECANIQUE | F68: 1029399691 | G68: 0 | H68: Test olivier et Marc | K68: Y
A69: OZ2059347 | B69: 2026-06-10 10:01 | C69: 202606 | D69: 740VU_743VU | E69: CONDITIONNEMENT 740VU | F69: 1029237370 | G69: 14 | H69: Câble à recommander : Numéro : 2434-0003 Type : DG 4 Longueur : 80 Raison : Mise en œuvre incorrect. MSN : 2161 | K69: Y
A70: OZ2061700 | B70: 2026-06-11 00:02 | C70: 202606 | D70: A30 | E70: SSENS4 | F70: 1029324529 | G70: 0 | H70: bonjour, backshell cassé lors du torquage de la prise Réf. raccord : ABS1896A08E Merci | I70: servi | J70: Y | K70: Y
A71: OZ2071840 | B71: 2026-06-16 17:12 | C71: 202606 | D71: A30 | E71: TETEA1 | F71: 1029637798 | G71: 120 | H71: Bonjour. Suite a mauvais identification de certains câbles, il avez de câbles da prise 1608VC070 A identifie comme câbles da prise 1608VC066 A et le contraire aussi Save-dire câbles da 1608VC066 A dans la prise 1608VC070 A. Merci de bien Controller les arbores avant de les envoie en Tête A. Bonne Soirée. | J71: Y | K71: Y
A72: OZ2073378 | B72: 2026-06-17 09:08 | C72: 202606 | D72: A30 | E72: SSENS4 | F72: 1029554910 | G72: 30 | H72: Manque prise 20TC2 A Réf. équipement : ABS2306E08FR1A1 Réf. raccord : EN3545-007SCE Merci | I72: fait | J72: Y | K72: Y
A73: OZ2076534 | B73: 2026-06-18 09:55 | C73: 202606 | D73: A30 | E73: SSENS3 | F73: 1029574118 | G73: 90 | H73: Bonjour câble KL mauvaises sens numero : 4612-0371 ET 4612-370 MSN : 861 2M LIGNE : 3 OF: 1029574118 MERCI | J73: Y | K73: Y
A74: OZ2078766 | B74: 2026-06-18 23:22 | C74: 202606 | D74: A30 | E74: MECA | F74: 1029377348 | G74: 60 | H74: La structure MSN 857, les étiquettes autocollantes ne sont pas installées pour l'identification des prises Arinc et 3CB A/B. | K74: Y
A75: OZ2078821 | B75: 2026-06-19 00:42 | C75: 202606 | D75: A30 | E75: MECA | F75: 1029376652 | G75: 60 | H75: Bonjour. Sur le MSN 856 ils sont pas installe les 6 étiquette autocollante de repère des prises arinc plus le 2 de prise 3CB A/B. Merci de vérifier et de le remettre en conformité Bonne Journée. | K75: Y
A76: OZ2088070 | B76: 2026-06-24 15:15 | C76: 202606 | D76: MULTIPROGRAMME_A320 | E76: FOMAX_A320 | F76: 57590665 | G76: 9 | H76: Fomax 786-95 OF 57590665 apparemment, 1 étiquette rapidshare a dû tomber. L'étiquette pour le KL 24 n°4626-7114 est manquante Besoin d'une réimpression. Merci d'avance | K76: Y
A77: OZ2088755 | B77: 2026-06-24 23:47 | C77: 202606 | D77: A30 | E77: SSENS4 | F77: 1029554905 | G77: 60 | H77: BONSOIR OF 1029554905 MSN 8S0 ROUITE 2M CDVE LE BACKSHELL DE LA PRISE 9KS J14 S'EST CASSE EN TORQUANT REFERENCE ABS1896A09P MERCI | J77: Y | K77: Y
A78: OZ2095101 | B78: 2026-06-29 11:02 | C78: 202606 | D78: A30 | E78: INTEG1 | F78: 1029377424 | G78: 150 | H78: Bonjour, Nous avons une étiquette auto-collant manquant sur une prise NON CDVE 1608VC021 A, route 1S, poste TEST 1. Pourriez vous nous fournir pour qu'elle soit conformité. Merci! Cordialement, Vanessa. | I78: Demande impression étiquette réaliser. | J78: Y | K78: Y
A79: OZ2097291 | B79: 2026-06-29 22:37 | C79: 202606 | D79: A30 | E79: MECA | F79: 1029574611 | G79: 60 | H79: Bonjour. Le MIP MSN 861, les étiquettes autocollantes de repère de prise arinc plus des deux prise 3CB-A/B sont pas installer. SVP de passer sur poste pour vérifier et demande de installer les mêmes étiquettes. Merci et bonne journée. | K79: Y
A80: OZ2107275 | B80: 2026-07-03 09:42 | C80: 202607 | D80: E-RUDDER_A320 | E80: FABRICATION_A320 | F80: 1029958964 | G80: 186 | H80: attente d'un controle sertissage cdve depuis 7H30 | I80: contrôle cdve effectue | K80: Y
A81: OZ2108613 | B81: 2026-07-03 17:52 | C81: 202607 | D81: A30 | E81: TETEA1 | F81: 1030138820 | G81: 59 | H81: Bonjour, MSN 859 ULR Connecteur : 20TC2 A L2 2M Présence de feutre noir sur le connecteur. Prélèvement fait sur le MSN 867 Merci. | J81: Y | K81: Y
A82: OZ2109398 | B82: 2026-07-06 07:56 | C82: 202607 | D82: IMPRESSION_A350 | E82: FO A350 | F82: 1030238752 | G82: 24 | H82: Les postes de travails pour les opérations 20 30 et 40 ne peuvent pas être badgés car il n y a de QA associé ( 4VEF702). Merci de prendre le point. | I82: Postes de travail modifiés pour les phases 20, 30 et 40. | K82: Y
A83: OZ2116698 | B83: 2026-07-08 13:42 | C83: 202607 | D83: MULTIPROGRAMME_A330 | E83: RMAX_A330 | F83: 57580106 | G83: 69 | H83: RMAX A330 PN 872-95 et 873-95 les plaquettes repère n'apparaissent pas sur le plan de câblage. Faut-il les ajouter sachant qu'au moins 1 des 3 est présente sur la planche qui se trouve en page 9 de la SOI ? Merci | I83: c'set résolu. merci | K83: Y
A84: OZ2117932 | B84: 2026-07-08 20:51 | C84: 202607 | D84: A30 | E84: MECA | F84: 1029637876 | G84: 67 | H84: Pièce manquante pas de brossage et pas de vaseline non conforme | I84: Bonjour, pris en compte sous S03 = 1030330408 | J84: Y | K84: Y
A85: OZ2117941 | B85: 2026-07-08 20:53 | C85: 202607 | D85: A30 | E85: MECA | F85: 1029638120 | G85: 120 | H85: Pièce manquante NON CONFORME | I85: Bonjour, pris en compte sous S03 = 1030330186 | J85: Y | K85: Y
A86: OZ2117961 | B86: 2026-07-08 20:55 | C86: 202607 | D86: A30 | E86: MECA | F86: 1029638900 | G86: 66 | H86: NON CONFORME | J86: Y | K86: Y
A87: OZ2130029 | B87: 2026-07-16 18:42 | C87: 202607 | D87: 740VU_743VU | E87: FINITION 740VU | F87: 1029734826 | G87: 7 | H87: Bonjour, Suite à la détérioration (déchirure) du grommet de notre raccord arrière, nous sollicitons la servitude d'un raccord neuf référence NSA938025A12M, dans le but d'y prélever le grommet de rechange. Merci d'avance. | K87: Y
A88: OZ2131583 | B88: 2026-07-17 10:07 | C88: 202607 | D88: MULTIPROGRAMME_A330 | E88: RMAX_A330 | F88: 57600569 | G88: 0 | H88: RMAX A330 PN 888-95 OF 57600569 PB survenu lors de la mise en œuvre de la gaine thermo haute température. La gaine du DR24 en sortie a fait une bulle qui a éclaté. Vérification du réglage de la température du générateur d'air chaude faite en consultant l'AIPI07-07-001 faite. Le DR24 semble ne pas être le même que celui que nous avions avant (changement de fournisseur ?), | K88: Y
A89: OZ2131597 | B89: 2026-07-17 10:11 | C89: 202607 | D89: MULTIPROGRAMME_A330 | E89: RMAX_A330 | F89: 57600569 | G89: 60 | H89: RMAX A330 PN 888-95 OF 57600569 PB survenu lors de la mise en œuvre de la gaine thermo haute température. La gaine du DR24 en sortie a fait une bulle qui a éclaté. Vérification du réglage de la température du générateur d'air chaude faite en consultant l'AIPI07-07-001 faite. Le DR24 semble ne pas être le même que celui que nous avions avant (changement de fournisseur ?), | I89: Vu avec les methodes, nous n'avons pas pu reproduire de bulles sur l'echantillon de câble de 5m. Ils valident donc l'utilisation du câble vu que ça à l'air d'etre un cas isolé. Je joints à cet MES leur analyse. | K89: Y
A90: OZ2137377 | B90: 2026-07-21 15:47 | C90: 202607 | D90: A30 | E90: SSENS_S1 | F90: 1029638829 | G90: 0 | H90: probleme avec la prise ne se torque pas, tourne sur elle meme | J90: Y | K90: Y
A91: OZ2139044 | B91: 2026-07-22 09:56 | C91: 202607 | D91: A30 | E91: SSENS2 | F91: 1029638884 | G91: 30 | H91: Bonjour, Sur la route 2M du MSN 866, le backshell ABS1896A08E de la prise 52CV-A s'est abimé lors du torquage. Merci d'en fournir un autre. Ref: ABS1896A08E | I91: SERVI | J91: Y | K91: Y
A92: OZ2142810 | B92: 2026-07-23 17:36 | C92: 202607 | D92: A30 | E92: MECA | F92: 1029638460 | G92: 120 | H92: MSN 864 et 865 impossible de badger les op10 | I92: voir IMAGE | K92: Y
A93: OZ2150862 | B93: 2026-08-18 15:37 | C93: 202608 | D93: IMPRESSION_A320 | E93: DEBIT SUR STOCKS_A320 | F93: 57461975 | G93: 120 | H93: Problème de serrage tyrap sur les gaines de réserve rigides. L'AIPS indique un serrage à 2.50. Mais selon les pistolets ce serrage est trop lâche. Après vérification il serait plus adapté d'appliquer un serrage à 2.75 pour les pistolets que nous avons actuellement au poste. | I93: Suite à MFT du 16/09/2026 les pistolets tyrap qui ont été rendu au labo sont non conforme. Le 3eme pistolet restant est retiré de la production. L'analyse des impacts potentiels entre juillet et aôut sur les produits livrés est en cours. voir amandine plante, vanessa malet et nicolas gailler. Sur le relâchement des tyrap, le problème n'a pas été identifié ailleurs donc sans suite mais en obsvervat | K93: Y
A94: OZ2151820 | B94: 2026-08-18 22:23 | C94: 202608 | D94: A30 | E94: MECA | F94: 1029638982 | G94: 90 | H94: IMPOSSIBLE DE VALIDER LES NUMEROS DE SERIE | K94: Y
A95: OZ2153845 | B95: 2026-08-19 18:42 | C95: 202608 | D95: A30 | E95: INTEG2 | F95: 1029637895 | G95: 60 | H95: Bonjour, Nous avons bien reçu la platine V924.19534.000. Cependant, les métallisations à brosser n'ont pas été réalisées. Les séries concernées (MSN) sont les 863, 864 et 865. Merci de bien vouloir traiter ce point dès que possible. | J95: Y | K95: Y
A96: OZ2155816 | B96: 2026-08-20 14:17 | C96: 202608 | D96: PTVU | E96: MECANIQUE | F96: 1030067907 | G96: 7 | H96: Plaquette 34CE 2 mal imprimée (écrit 34) plusieurs cas comme ça sur cet avion | K96: Y
A97: OZ2155834 | B97: 2026-08-20 14:23 | C97: 202608 | D97: PTVU | E97: MECANIQUE | F97: 1030068580 | G97: 7 | H97: Plaquette 34CE 1 mal imprimée (écrit "34") plusieurs cas similaires sur cet avion | K97: Y
A98: OZ2156839 | B98: 2026-08-20 21:44 | C98: 202608 | D98: E-RUDDER_A320 | E98: FABRICATION_A320 | F98: 1030259828 | G98: 9 | H98: ABSENCE DE LA QUALITER SUR LE POSTE A320 | K98: Y
A99: OZ2160067 | B99: 2026-08-24 12:43 | C99: 202608 | D99: A30 | E99: CONDITIONNEMENT | F99: 1030699917 | G99: 7 | H99: Câble trop court de l'impression ( TETE A ) 2R MSN 871 VNC24 Numéro 2351-3348 LONG: 260 | I99: Suite à erreur de longueur dans la S03 rajout de 3 phase pour ré impression S03 remis au kiting. | K99: Y
A100: OZ2166780 | B100: 2026-08-26 14:20 | C100: 202608 | D100: A30 | E100: SSENS1 | F100: 1030167753 | G100: 480 | H100: Perte de temps suite a une erreur de gainage/frettage des MV/MG | I100: pris en compte | J100: Y | K100: Y
A101: OZ2181890 | B101: 2026-09-02 14:15 | C101: 202609 | D101: PTVU | E101: MECANIQUE | F101: 1030183058 | G101: 14 | H101: Problème sur les vis NAS1635-04-6, elles casses pendant le torquage. | I101: vu avec la prod, j'ai isolé les deux boites kb afin d'avoir une nouvelle réappro ! la prod n'est pas bloqué, servitude en attendant d'un autre kb | K101: Y
A102: OZ2185072 | B102: 2026-09-03 13:27 | C102: 202609 | D102: A30 | E102: INTEG2 | F102: 1029638929 | G102: 4 | H102: MODULE ABIME REF ABS 1569ME2002 (Module déjà changé) | I102: Module déjà changé | J102: Y | K102: Y
A103: OZ2186752 | B103: 2026-09-03 22:54 | C103: 202609 | D103: 740VU_743VU | E103: CHEMINEMENT 742VU | F103: 1030470824 | G103: 14 | H103: A330 PORTE 742 VU MSN: 2171 OF: 1030470824 CABLES NON IMPRIMES DR 24 4942-0001 LONG 204 3523-0001 LONG 196 3121-0019 LONG 207 3121-0020 LONG 207 3261-0197 LONG 177 3162-0286 LONG 204 3162-0334 LONG 202 3162-0362 LONG 197 3154-0579 LONG 194 7325-1840 LONG 215 | I103: NC prise en compte par OF 1030910333. | K103: Y
A104: OZ2208614 | B104: 2026-09-14 18:46 | C104: 202609 | D104: PTVU | E104: MECANIQUE | F104: 1030599514 | G104: 36 | H104: manque rampe | I104: servi | K104: Y
...

Sheet M1_QualityLike
A1: M1. Aléas of other kinds whose text describes a quality problem (no NC followed)
A2: Logistics, work-order and line disruptions whose comment reads like a quality problem. Grouped so you can answer yes / no per group instead of reading 107 rows.
A4: Answer Y or N in the yellow column for each group. Rows of a group marked Y are added to the disruption block (see Figures). The full list is below the table.
A6: Group | B6: Aléas | C6: Hours lost | D6: Three examples | E6: Count as quality? (Y/N) | F6: Comment
A7: Cable damaged, cut too short or duplicated | B7: =COUNTIF($G$16:$G$122,A7) -> 13 | C7: =SUMIFS($F$16:$F$122,$G$16:$G$122,A7)/60 -> 19.116667 | D7: Reprise du câble bloquant le test 2452-0017 Et reprise de 3 câbles abimé vue lors du cheminement du câble temp | Pièce manquante BONJOUR SERAIT IL POSSIBLE DE RAJOUTER SUR TOUS LES POSTES DE TETE A DES CABLES DE REPRISE DR2 | Bonjour, En regardant la SOI je me suis aperçu que nous n'avons pas d'éléments nous stipulant la longueur de c
A8: Workmanship error on the line (crimping, forgotten, wrong fitting) | B8: =COUNTIF($G$16:$G$122,A8) -> 19 | C8: =SUMIFS($F$16:$F$122,$G$16:$G$122,A8)/60 -> 24.133333 | D8: Pièce manquante Faire attention a la reappro car il y a un ordre de haut en bas entre les tresses car inversio | Reprise TEST connecteurs inversés MSN 813 (9KSJ25, 9KSJ26) Explication a CIB pour intervention suite NC 216038 | Reprise des auto-soudeurs (Mauvaise mise en œuvre) manque reprise de 15CM pour MEO Band-IT
A9: Part or component broken, damaged or faulty | B9: =COUNTIF($G$16:$G$122,A9) -> 52 | C9: =SUMIFS($F$16:$F$122,$G$16:$G$122,A9)/60 -> 30.7 | D9: Pièce manquante | Pièce manquante Bonjour, j'ai le module 6 de la VT 300VT400 défectueux, il me faudrait un de rechange ABS1569M | Pièce manquante BACKSHELL ABÎME EN3545007SCD PRISE 1610VC051 MSN816 ROUTE 1M
A10: Wrong or non-conforming part or document supplied | B10: =COUNTIF($G$16:$G$122,A10) -> 13 | C10: =SUMIFS($F$16:$F$122,$G$16:$G$122,A10)/60 -> 9.9333333 | D10: OF : 1028348137 MSN : 840 Etiquette repère non conforme écriture non centré prise : 11CP1 D . Etiquette repère | Bonjour, sur les 2S, les plaquettes de la 100VN220, qui avaient été réimprimées car non conformes dans la dern | Bonjour, sur les 2S, les 100VN220, les plaquettes E0248A1-4H22, qui avaient été réimprimées car non conformes
A11: Other wording | B11: =COUNTIF($G$16:$G$122,A11) -> 10 | C11: =SUMIFS($F$16:$F$122,$G$16:$G$122,A11)/60 -> 7.3666667 | D11: 255VU MSN 1741 ( 57455142 ), Sur le plan F925-10607.003.b003, on me demande de mettre des vis NAS1100-06-5 pou | Sur le MSN13506 452VB, au moment de la finition, je m'aperçois que le harnais a été coupé trop court (il a été | Toutes les phases 30 ou 36 (contrôle du câble) de toutes les gammes NC de tous les programmes ne sont pas corr
A12: Counted as quality (groups marked Y) | B12: =COUNTIF($I$16:$I$122,"Y") -> 0 | C12: =SUMIFS($F$16:$F$122,$I$16:$I$122,"Y")/60 -> 0
A15: Disruption | B15: Opened | C15: Month (yyyymm) | D15: Kind | E15: Line | F15: Time lost (min) | G15: Group | H15: What the operator wrote | I15: Counted
A16: OZ1832784 | B16: 2026-02-03 | C16: 202602 | D16: TL - Trou de production - pas d activite | E16: 740VU_743VU | F16: 420 | G16: Cable damaged, cut too short or duplicated | H16: Reprise du câble bloquant le test 2452-0017 Et reprise de 3 câbles abimé vue lors du cheminement du câble temps perdue 7h | I16: =IF(IFERROR(INDEX($E$7:$E$11,MATCH(G16,$A$7:$A$11,0)),"")="Y","Y","N") -> N
A17: OZ1945005 | B17: 2026-04-01 | C17: 202604 | D17: LOG - Probleme servitude | E17: A30 | F17: 60 | G17: Cable damaged, cut too short or duplicated | H17: Pièce manquante BONJOUR SERAIT IL POSSIBLE DE RAJOUTER SUR TOUS LES POSTES DE TETE A DES CABLES DE REPRISE DR24 COUPES à 20 CM. ILS SONT NECESSAIRES 0 LA MISE EN OEUVRE DE CERTAINES PRISES SUR L'ENSEMBLES DES ROUTES M, S ET R MERCI | I17: =IF(IFERROR(INDEX($E$7:$E$11,MATCH(G17,$A$7:$A$11,0)),"")="Y","Y","N") -> N
A18: OZ2053260 | B18: 2026-06-08 | C18: 202606 | D18: SUPTECH - Probleme OF-OT et Definition | E18: A30 | F18: 30 | G18: Cable damaged, cut too short or duplicated | H18: Bonjour, En regardant la SOI je me suis aperçu que nous n'avons pas d'éléments nous stipulant la longueur de coupe des câbles sur les modules VT CDVE platines volantes, Serait-il possible de demander une notation sur les SOI à ce sujet? Merci, | I18: =IF(IFERROR(INDEX($E$7:$E$11,MATCH(G18,$A$7:$A$11,0)),"")="Y","Y","N") -> N
A19: OZ2092418 | B19: 2026-06-26 | C19: 202606 | D19: SUPTECH - Probleme OF-OT et Definition | E19: IMPRESSION_A350 | F19: 120 | G19: Cable damaged, cut too short or duplicated | H19: les longueurs donne dans la soi ne sont pas en accord avec la demande ( câble trop court ) | I19: =IF(IFERROR(INDEX($E$7:$E$11,MATCH(G19,$A$7:$A$11,0)),"")="Y","Y","N") -> N
A20: OZ2102144 | B20: 2026-07-01 | C20: 202607 | D20: SUPTECH - Probleme OF-OT et Definition | E20: IMPRESSION_A350 | F20: 60 | G20: Cable damaged, cut too short or duplicated | H20: OF : 57543631 9012VB : Mauvaises longueurs de câbles dans SOI (Trop courts) / Fichiers LAS | I20: =IF(IFERROR(INDEX($E$7:$E$11,MATCH(G20,$A$7:$A$11,0)),"")="Y","Y","N") -> N
A21: OZ2102153 | B21: 2026-07-01 | C21: 202607 | D21: SUPTECH - Probleme OF-OT et Definition | E21: IMPRESSION_A350 | F21: 60 | G21: Cable damaged, cut too short or duplicated | H21: OF 57543638 9017VB : Mauvaises longueurs de câbles dans SOI (Trop courts) / Fichiers LAS | I21: =IF(IFERROR(INDEX($E$7:$E$11,MATCH(G21,$A$7:$A$11,0)),"")="Y","Y","N") -> N
A22: OZ2102162 | B22: 2026-07-01 | C22: 202607 | D22: SUPTECH - Probleme OF-OT et Definition | E22: IMPRESSION_A350 | F22: 37 | G22: Cable damaged, cut too short or duplicated | H22: 57543641 9019VB Mauvaises longueurs de câbles dans SOI (Trop courts) / Fichiers LAS | I22: =IF(IFERROR(INDEX($E$7:$E$11,MATCH(G22,$A$7:$A$11,0)),"")="Y","Y","N") -> N
A23: OZ2102165 | B23: 2026-07-01 | C23: 202607 | D23: SUPTECH - Probleme OF-OT et Definition | E23: IMPRESSION_A350 | F23: 60 | G23: Cable damaged, cut too short or duplicated | H23: 57543644 9031VB Mauvaises longueurs de câbles dans SOI (Trop courts) / Fichiers LAS | I23: =IF(IFERROR(INDEX($E$7:$E$11,MATCH(G23,$A$7:$A$11,0)),"")="Y","Y","N") -> N
A24: OZ2102169 | B24: 2026-07-01 | C24: 202607 | D24: SUPTECH - Probleme OF-OT et Definition | E24: IMPRESSION_A350 | F24: 60 | G24: Cable damaged, cut too short or duplicated | H24: 57543651 9038VB Mauvaises longueurs de câbles dans SOI (Trop courts) / Fichiers LAS | I24: =IF(IFERROR(INDEX($E$7:$E$11,MATCH(G24,$A$7:$A$11,0)),"")="Y","Y","N") -> N
A25: OZ2102171 | B25: 2026-07-01 | C25: 202607 | D25: SUPTECH - Probleme OF-OT et Definition | E25: IMPRESSION_A350 | F25: 60 | G25: Cable damaged, cut too short or duplicated | H25: 57543635 9014VB Mauvaises longueurs de câbles dans SOI (Trop courts) / Fichiers LAS | I25: =IF(IFERROR(INDEX($E$7:$E$11,MATCH(G25,$A$7:$A$11,0)),"")="Y","Y","N") -> N
A26: OZ2102174 | B26: 2026-07-01 | C26: 202607 | D26: SUPTECH - Probleme OF-OT et Definition | E26: IMPRESSION_A350 | F26: 60 | G26: Cable damaged, cut too short or duplicated | H26: 57543696 9056VB Mauvaises longueurs de câbles dans SOI (Trop courts) / Fichiers LAS | I26: =IF(IFERROR(INDEX($E$7:$E$11,MATCH(G26,$A$7:$A$11,0)),"")="Y","Y","N") -> N
A27: OZ2241681 | B27: 2026-09-28 | C27: 202609 | D27: SUPTECH - Probleme OF-OT et Definition | E27: IMPRESSION_A330 | F27: 60 | G27: Cable damaged, cut too short or duplicated | H27: AOG F900.00954.962.95 Il est demandé des manchons MR0600, du câble XM24 sans aucune longueur associée à chaque manchon (Le fichier manchons est enregistré sous fichier LAS, fichier laser). Il est demandé de la gaine E0718-03-20 or, la matière n'apparaît pas sous un emplacement dans la fiche suiveuse (incohérence dans la désignation sans magasin et emplacement : V929.99067.GAI.01 DECOUPE GAINE POUR | I27: =IF(IFERROR(INDEX($E$7:$E$11,MATCH(G27,$A$7:$A$11,0)),"")="Y","Y","N") -> N
... A122: OZ2147695 | B122: 2026-08-17 | C122: 202608 | D122: TL - Trou de production - pas d activite | E122: PTVU | F122: 67 | G122: Wrong or non-conforming part or document supplied | H122: Etiquettes fin CDVE non conforme | I122: =IF(IFERROR(INDEX($E$7:$E$11,MATCH(G122,$A$7:$A$11,0)),"")="Y","Y","N") -> N

Sheet M2_NCsNotHeld
A1: M2. Rework orders that name an NC we do not have (September 2026)
A2: Their text says 'Suite à la NC 2183…' but that NC is in neither the 2026 dashboard export nor the 2025 file: probably outside the dashboard scope.
A4: Look up each NC in Skywise: plant, liability and user_department. If they are ERMA NCs or NCs of other plants where FTO2 is not liable, they are out of scope as decided. If FTO2 is liable, our NC export misses them.
A6: Rework order | B6: Family | C6: Programme | D6: MSN | E6: NC named | F6: Planned h | G6: What the order says | H6: Plant of the NC | I6: Liability | J6: Written by (ERMA?) | K6: Comment
A7: 1030502425 | B7: IEVB (MSN 700/701) | C7: A350 | D7: 701 | E7: 217923362 | F7: 4.5 | G7: Analyse dossier || Localisation : Soute 1, zone mixeur RH - Localisation : Soute 1, zone mixeur RH - C44 Suite à changement tuyauterie V212.15679.004 par la FAL, veuillez remonter les TT373 suivant NSI V8902064000000-133-000-A0 219ZCA975 (P27/31) 219
A8: 1030281134 | B8: IEVB (MSN 700/701) | C8: A350 | D8: 700 | E8: 217751942 | F8: 2 | G8: ATTESTATION DE CONFORMITE || CONTROLE / POSTE NEUTRE || AR 217751942 - DEPLACEMENT PALETTE POS 2 AR 217751942 - DEPLACEMENT PALETTE POS 2 / (06/07/2026) Veuillez déplacer la palette FTI (Soute 1) en position 1. Vérifier l'environnement (harnais/cable
A9: 1030765521 | B9: IEVB (MSN 700/701) | C9: A350 | D9: 700 | E9: 218091347 | F9: 2 | G9: ATTESTATION DE CONFORMITE || CONTROLER || Analyse dossier: Analyse dossier: Localisation : Frame 44/45 Stringer 41 right hand side Voir documents joints. Merci de rectifier. Voir documents joints, NC218091347. || Descendre position du collier Descend
A10: 1031250059 | B10: IEVB (MSN 700/701) | C10: A350 | D10: 701 | E10: 218357020 | F10: 2 | G10: PHASE POUR CLOTURE || CONTROLE QUALITE CONTROLE QUALITE **Inspection Visuelle Générale** -> Vérifier qu'il n'y a aucun écart évident, manquant ou non conformité. -> Vérifier que les équipement de sécurité sont en place (Ex: bouteile d'extinction). ->
A11: 1031020288 | B11: FTO2 shop floor | C11: A350 | D11: 875 | E11: 218266456 | F11: 0.95 | G11: Inspection Qualité || Attestation de conformité || Remise en conformités du câble Remise en conformités du câble Effectuer le sertissage du câble en tête A suivant les informations de la définition sur ElecABC/NIICE. Effectuer le branchement du câble
A12: 1031000235 | B12: FTO2 shop floor | C12: A350 | D12: 858 | E12: 218247239 | F12: 0.8 | G12: Contrôle du KIT(s) avant le départ pour Contrôle du KIT(s) avant le départ pour Montoir-de-Bretagne Suite à la NC 218247239, veuillez cibtrôler le KIT avant le départ pour Montoir de bretagne suivant la demande effectuer au Kitting Factory OLME et le
A13: 1030828626 | B13: FTO2 shop floor | C13: A350 | D13: 872 | E13: 218143463 | F13: 0.68 | G13: Attestation de conformité || Inspection Qualité || Remise en conformités du câble Remise en conformités du câble Effectuer le branchement du câble en tête A suivant les informations de la définition sur ElecABC/NIICE. Cheminer le câble vers la tête B
A14: 1031268173 | B14: FTO2 shop floor | C14: A350 | D14: 864 | E14: 218429025 | F14: 0.6 | G14: Imprimer étiquettes Imprimer étiquettes Suite à la NC 218429025, veuillez imprimer les étiquettes suivant la demande effectuer au Kitting Factory OLME et les informations ci-dessous : Désignation / Quantité /,, FIN E0248A2-6H4T 1 ESS 2M, 2MF 2MG, 2MN
A15: 1031249183 | B15: FTO2 shop floor | C15: A350 | D15: 880 | E15: 218421807 | F15: 0.52 | G15: Contrôle du câble Contrôle du câble Suite à la NC 218421807, veuillez débiter le câble suivant les informations ci-dessous : Type de câble / Quantité /,,Numéro de câble / Long (cm),, VNB24 1 2351-0680 180 || Débiter câble laser Débiter câble laser Su
A16: 1031233848 | B16: FTO2 shop floor | C16: A350 | D16: 873 | E16: 218415444 | F16: 0.5 | G16: NC CABLE - Contrôle du câble NC CABLE - Contrôle du câble Suite à la NC 218415444, veuillez contrôler le câble et le manchons suivant les informations ci-dessous : Type de câble / Quantité /,,Numéro de câble / Long (cm),, WX26 1 3161-0347 240 Type de
A17: 1030903330 | B17: FTO2 shop floor | C17: A350 | D17: 875 | E17: 218186517 | F17: 0.5 | G17: Attestation de conformité || Inspection Qualité || NC CABLE - Remise en conformité des câbl NC CABLE - Remise en conformité des câbles si SSTT Effectuer les sertissages du câble en tête A suivant les informations de la définition sur ElecABC/NIICE. E
A18: 1030884473 | B18: FTO2 shop floor | C18: A350 | D18: 873 | E18: 218177756 | F18: 0.5 | G18: Attestation de conformité || NC CABLE - Préparation travail/Analyse d NC CABLE - Préparation travail/Analyse du dossier || Inspection Qualité || NC CABLE - CONTROLER SERTISSAGE CDVE TA || NC CABLE - Remise en conformité du câble NC CABLE - Remise en
... A46: 1031216847 | B46: FTO2 shop floor | C46: A350 | D46: 877 | E46: 218403302 | F46: 0.38 | G46: Contrôle du câble Contrôle du câble Suite à la NC 218403302, veuillez contrôler le câble laser ou le câble manchonné suivant les informations ci-dessous : Type de câble / Quantité /,,Numéro de câble / Long (cm),, VNA24 1 2799-0008 549 || Imprimer câb
A47: Total planned h | F47: =SUM(F7:F46) -> 26.97

Sheet M3_Exceptional
A1: M3. Exceptional NCs (to check yourself; not for the presentation)
A2: Reworked NCs whose rework order plans at least 3 h and more than 2.5 times the model's rework time (September 2026 orders).
A4: NC 218233692 ('Câbles non lasérisés') is one defect line for the model but its order plans 34 h of reprinting cables for six routes. The three others have no defect line found by the parser, so the model uses a flat 1 hour. Check whether the planned time is right and whether such NCs should be costed from their order.
A6: NC | B6: NC type | C6: Defect lines (parser) | D6: Planned rework (h) | E6: Model rework (h) | F6: What was found | G6: Long text (extract) | H6: Finding
A7: 218233692 | B7: CABLES | C7: 1 | D7: 34.3 | E7: 1 | F7: Câbles non lasérisés | G7: rical Assembly Installation * Sur la ligne A350 , poste tête A , nous avons constaté qu'aucun câble n'était lasérisé sur les WF201 / WF311 / WF312. Nous demandons le remplacement des câbles non lasérisés. Les câbles étaient manquants sur le MSN 876 et ont été prélevés sur le 878 avec l'accord du ME.
A8: 218172558 | B8: CABLES | C8: 0 | D8: 4.6 | E8: 1 | F8: Câbles trop court Route 11M
A9: 218282208 | B9: TEST | C9: 0 | D9: 3 | E9: 1 | F9: RETOUCHES 300 VU MSN 164
A10: 218338931 | B10: TEST | C10: 0 | D10: 3 | E10: 1 | F10: RETOUCHES TEST MIP 400M MSN 166

Sheet Later
A1: Kept for later, and points to keep in mind
A2: Not for tomorrow's checks, but not to forget.
A4: Item | B4: Detail
A5: Change 5 (kept for later) | B5: Two defect classes produced by parser v4.8 are missing from the CNQ time table and get the 10-min default: 'Mesure hors tolérance' (~25 lines a year) and 'Dommage – tresse de masse' (2-3 lines). Proposal: give them the time of 'Point de masse / mesure' (5 min) and 'Dommage – câble' (30 min). Effect: almost 0 EUR.
A6: Point to keep in mind: alert on customer returns | B6: By the 'direct cause' rule, the customer's own operator alert should count too. Change 3 removed the alert from customer returns; putting it back adds 25 EUR per return (69 returns in 2026, about 1,700 EUR). Decide with H3.
A7: Point to keep in mind: flat 30-min alert | B7: Aléas that led to an NC declare on average 41 min lost (median 30). The NC cost uses a flat 30 min. When the disruption link is in the pipeline, the declared time can replace it.
A8: Point to keep in mind: 4 final-inspection NCs with an aléa | B8: 4 final-inspection NCs did start with a quality aléa (4.6 h) but get no alert step since change 3, and are not in the disruption block either. Small; fixed when the disruption link is in the pipeline.
A9: Point to keep in mind: responders' time | B9: Disruption 'time lost' is the operator's time only. The time of the people who answer the aléa (quality, technical support, logistics) is not counted anywhere.
A10: Point to keep in mind: periods | B10: The disruption block covers Jan-Sep 2026 only (no 2025 disruptions in the data). The NC cost for 2026 is quoted for Feb-Sep because January is cut in the NC export.
A11: Low: MSN 700/701 work (IEVB work centres) | B11: 74 rework orders, 217 h in September on MSN 700/701 (e.g. 'Repose FTI sur bouteille oxy'). Confirm it is flight-test installation and out of scope.
A12: After the presentation | B12: Full year of rework orders (re-check 15 min per connection error and x2 on internal NCs; use planned time per NC in the pipeline). Quality-team time sheets for every month. Repair cost of customer returns from TOF / FNZ1 / FFF1. Euros already booked by Finance on rework orders. Disruption link (work order + 72 h) in the pipeline.
