Workbook

Sheet Read me
A1: CNQ – parts to price
A3: What this is
A4: The cost model counts the value of the part on rejections (REJ), rejections with a rework order (REJ_RW), exchanges (EXC) and scraps (SCR) where FTO2 is liable. Today that value is 0 because no price is known.
A5: 132 NCs need a part price. They come down to 91 parts: 60 with a reference written in the NC, 18 with only a FIN, 13 to identify from the NC's wording.
A6: Source: NC exports of 12 Oct 2026 (fto2_dashboard_data_12 and _missing_ids_3), decisions and liability as in the dashboard (NCs created in 2026, every phase).
A8: How the part was found
A9: The reference is read from the NC title and long text (NSA, ABS, ASNA, NAS, EN, E0…, 14-character Airbus articles, 10-digit references). When none is written, the FIN is used; otherwise the part is listed as the NC names it.
A10: The SAP article on the NC is mostly the assembly being built (a VU or a routing), not the rejected part. It is shown in 'NC detail' for reference only.
A11: This is an automatic reading of the texts: check the reference before asking for a price.
A13: What to fill in
A14: Sheet 'Parts to price', yellow cells only: Unit price (€) and Price source. Part value = unit price × quantity.
A15: Sheet 'NC detail' picks the price up by itself. Its 'Part value (€)' column is what the cost model reads as part_value.
... A22: NCs where FTO2 is not liable cost 0 in the model; they are listed in 'Not charged to FTO2' for completeness (112 NCs).

Sheet Parts to price
A1: Part reference / FIN / name | B1: Found as | C1: Part (as named in the NC) | D1: NCs | E1: MSNs | F1: Quantity | G1: Decisions | H1: Products | I1: Lines | J1: First NC | K1: Last NC | L1: NC numbers | M1: Unit price (€) | N1: Price source | O1: Part value (€)
A2: NSA932844CN | B2: Reference in text | C2: SOCLE DE RACCORDEMENT ABIME | D2: 5 | E2: 5 | F2: 5 | G2: REJ_RW 4, REJ 1 | H2: 740VU | I2: A330 | J2: 2026-01-07 | K2: 2026-04-28 | L2: 216060124 216575897 216602069 217107871 217149659 | O2: =IF(M2="","",M2*F2)
A3: MANQUE TROU DE FIXATION ETEC 115VU | B3: To identify | C3: Manque trou de fixation ETEC 115VU | D3: 5 | E3: 5 | F3: 5 | G3: REJ 4, REJ_RW 1 | H3: PTVU | I3: A330 | J3: 2026-07-15 | K3: 2026-09-15 | L3: 217860541 217862026 217895101 217986779 218276828 | O3: =IF(M3="","",M3*F3)
A4: EN3646A02461AN | B4: Reference in text | C4: CONNECTEUR borne ne verrouille pas | D4: 4 | E4: 3 | F4: 4 | G4: REJ 3, REJ_RW 1 | H4: PTVU | I4: A330 | J4: 2026-04-02 | K4: 2026-06-17 | L4: 216915228 216931836 216943435 217584208 | O4: =IF(M4="","",M4*F4)
A5: 6325010000 | B5: Reference in text | C5: DECOUPLING UNIT CASSE | D5: 3 | E5: 3 | F5: 3 | G5: REJ_RW 3 | H5: 740VU | I5: A330 | J5: 2026-01-09 | K5: 2026-04-28 | L5: 216088280 216605359 217149326 | O5: =IF(M5="","",M5*F5)
A6: ABS0064-01 | B6: Reference in text | C6: BOUTON POUSSOIR INCOMPLET | D6: 3 | E6: 2 | F6: 3 | G6: REJ_RW 2, REJ 1 | H6: PTVU | I6: A330 | J6: 2026-04-23 | K6: 2026-04-27 | L6: 217109331 217112253 217139270 | O6: =IF(M6="","",M6*F6)
A7: ABS1424-3-10 | B7: Reference in text | C7: Colonnette de la structure du MIP cassée | D7: 3 | E7: 3 | F7: 3 | G7: EXC 3 | H7: MIP A350, Other | I7: A350 | J7: 2026-03-03 | K7: 2026-07-02 | L7: 216609710 217040142 217749687 | O7: =IF(M7="","",M7*F7)
A8: ABS1650-02 | B8: Reference in text | C8: CABLES ABIMES SUR OPTICAL ENCODER | D8: 3 | E8: 2 | F8: 3 | G8: REJ_RW 3 | H8: PTVU | I8: A330 | J8: 2026-04-07 | K8: 2026-06-19 | L8: 216943511 217613680 217613893 | O8: =IF(M8="","",M8*F8)
A9: ASNA2328-3-4 | B9: Reference in text | C9: Colonnette de la structure du MIP cassée | D9: 3 | E9: 3 | F9: 3 | G9: EXC 3 | H9: Other | I9: A350 | J9: 2026-01-20 | K9: 2026-02-09 | L9: 216177953 216247653 216376660 | O9: =IF(M9="","",M9*F9)
A10: E0062D1S4BA0A | B10: Reference in text | C10: BORNE HS SUR SWITCH OVER | D10: 3 | E10: 3 | F10: 3 | G10: REJ_RW 3 | H10: PTVU | I10: A330 | J10: 2026-06-16 | K10: 2026-09-24 | L10: 217571217 218307795 218376253 | O10: =IF(M10="","",M10*F10)
A11: E0062E2D4AC0A | B11: Reference in text | C11: BORNE NE VERROUILLE PAS | D11: 3 | E11: 1 | F11: 3 | G11: REJ 3 | H11: PTVU | I11: A330 | J11: 2026-01-28 | K11: 2026-03-10 | L11: 216265972 216336723 216669205 | O11: =IF(M11="","",M11*F11)
A12: E0682-01 | B12: Reference in text | C12: Borne 1 HS sur équipement E0682-01 | D12: 3 | E12: 3 | F12: 3 | G12: REJ_RW 2, REJ 1 | H12: PTVU | I12: A330 | J12: 2026-04-15 | K12: 2026-09-24 | L12: 217026822 218227645 218376309 | O12: =IF(M12="","",M12*F12)
A13: 614VU STRUCTURE ENDOMMAGEE | B13: To identify | C13: 614VU STRUCTURE ENDOMMAGEE | D13: 3 | E13: 2 | F13: 3 | G13: REJ_RW 3 | H13: PTVU | I13: A330 | J13: 2026-06-17 | K13: 2026-08-21 | L13: 217590666 218058588 218056243 | O13: =IF(M13="","",M13*F13)
... A92: TUYAUTERIE ATA21 DESSERRÉE | B92: To identify | C92: Tuyauterie ATA21 desserrée | D92: 1 | E92: 1 | F92: 1 | G92: EXC 1 | H92: MIP A350 | I92: A350 | J92: 2026-04-27 | K92: 2026-04-27 | L92: 217147112 | O92: =IF(M92="","",M92*F92)
A94: Total | D94: =SUM(D2:D92) -> 132 | F94: =SUM(F2:F92) -> 132 | M94: =COUNT(M2:M92)&" of "&COUNTA(A2:A92)&" priced" -> 0 of 91 priced | O94: =SUM(O2:O92) -> 0

Sheet NC detail
A1: NC | B1: Decision | C1: Decision label | D1: Phase | E1: Line | F1: Product | G1: MSN | H1: Created | I1: Quantity | J1: Part reference / FIN / name | K1: Part (as named in the NC) | L1: References in text | M1: FIN in text | N1: SAP article of the NC | O1: SAP article description | P1: Unit price (€) | Q1: Part value (€) | R1: NC text (extract)
A2: 217590666 | B2: REJ_RW | C2: Rejection with a rework order | D2: SERIE | E2: A330 | F2: PTVU | G2: 2163 | H2: 2026-06-17 | I2: 1 | J2: 614VU STRUCTURE ENDOMMAGEE | K2: 614VU STRUCTURE ENDOMMAGEE | N2: F9251072200000 | O2: ELEC ASSY 614VU | P2: =IFERROR(IF(INDEX('Parts to price'!$M$2:$M$92,MATCH(J2,'Parts to price'!$A$2:$A$92,0))="","",INDEX('Parts to price'!$M$2:$M$92,MATCH(J2,'Parts to price'!$A$2:$A$92,0))),"") | Q2: =IF(P2="","",P2*I2) | R2: 614VU STRUCTURE ENDOMMAGEE | NonConformity 0001 : Type of nonconformity : Scratch * Sur la ligne A330 , nous constatons que la structure 614VU /MSN 2163/RE058527 a été endommagée ( rayée ) Nous demandons une nouvelle structure pour la refabrication du produit. Text Description : - TEL~ #TEL~ Task Completed : 0200 `` DO00 `` Task Description : NC prise en compte par OF 1030054521. - Task Completed : 0400 `` ATW0 `` Task Description : remis en conformité - Task Completed : 1000 `` ATQ0 `` Task Description : vu remis en conformité
A3: 218058588 | B3: REJ_RW | C3: Rejection with a rework order | D3: SERIE | E3: A330 | F3: PTVU | G3: 2166 | H3: 2026-08-21 | I3: 1 | J3: 614VU STRUCTURE ENDOMMAGEE | K3: 614VU STRUCTURE ENDOMMAGEE | N3: F9251072200000 | O3: ELEC ASSY 614VU | P3: =IFERROR(IF(INDEX('Parts to price'!$M$2:$M$92,MATCH(J3,'Parts to price'!$A$2:$A$92,0))="","",INDEX('Parts to price'!$M$2:$M$92,MATCH(J3,'Parts to price'!$A$2:$A$92,0))),"") | Q3: =IF(P3="","",P3*I3) | R3: 614VU STRUCTURE ENDOMMAGEE | 0000000000 Sur la ligne A330 , nous constatons que la structure 614VU /MSN 2166/RE 059007 a été endommagée ( rayée ) Nous demandons une nouvelle structure pour la refabrication du produit. VOIR STANDARD DOC NonConformity 0001 : Type of nonconformity : Scratch * Sur la ligne A330 , nous constatons que la structure 614VU /MSN 2166/RE 059007 a été endommagée ( rayée ) Nous demandons une nouvelle structure pour la refabrication du produit. VOIR STANDARD DOC Text Description : RAYURE FACE AVANT 614VU - TEL~ #TEL~ Task Completed : 0200 `` DO00 `` Task Description : NC
A4: 218056243 | B4: REJ_RW | C4: Rejection with a rework order | D4: SERIE | E4: A330 | F4: PTVU | G4: 2166 | H4: 2026-08-21 | I4: 1 | J4: 614VU STRUCTURE ENDOMMAGEE | K4: 614VU STRUCTURE ENDOMMAGEE | N4: F9251072200000 | O4: ELEC ASSY 614VU | P4: =IFERROR(IF(INDEX('Parts to price'!$M$2:$M$92,MATCH(J4,'Parts to price'!$A$2:$A$92,0))="","",INDEX('Parts to price'!$M$2:$M$92,MATCH(J4,'Parts to price'!$A$2:$A$92,0))),"") | Q4: =IF(P4="","",P4*I4) | R4: 614VU STRUCTURE ENDOMMAGEE | 0000000000 Sur la ligne A330 , nous constatons que la structure 614VU /MSN 2166/RE059006 a été endommagée ( rayée ) Nous demandons une nouvelle structure pour la refabrication du produit. VOIR STANDARD DOC NonConformity 0001 : Type of nonconformity : Scratch * Sur la ligne A330 , nous constatons que la structure 614VU /MSN 2166/RE059006 a été endommagée ( rayée ) Nous demandons une nouvelle structure pour la refabrication du produit. VOIR STANDARD DOC Text Description : rayure sur la face avant du 614 VU - TEL~ #TEL~ Task Completed : 0200 `` DO00 `` Task Descript
A5: 216088280 | B5: REJ_RW | C5: Rejection with a rework order | D5: SERIE | E5: A330 | F5: 740VU | G5: 2143 | H5: 2026-01-09 | I5: 1 | J5: 6325010000 | K5: VIS ET FILETAGE SUR DECOUPLING UNIT H.S. | L5: 6325010000 | N5: F92511185000S23 | O5: FINITION 740VU | P5: =IFERROR(IF(INDEX('Parts to price'!$M$2:$M$92,MATCH(J5,'Parts to price'!$A$2:$A$92,0))="","",INDEX('Parts to price'!$M$2:$M$92,MATCH(J5,'Parts to price'!$A$2:$A$92,0))),"") | Q5: =IF(P5="","",P5*I5) | R5: VIS ET FILETAGE SUR DECOUPLING UNIT H.S. | NonConformity 0001 : Type of nonconformity : Electrical Assembly Installation * Lors du contrôle final du 740VU , MSN 2143 , nous constatons que le Decoupling Unit réf. 6325010000 est endommagé. La vis et le filetage sont H.S. * Nous demandons le remplacement de la pièce. Task Completed : 0100 `` DEC0 `` Decision Taken : REJECT Part Fitted Justification : EQUIPEMENT ENDOMMAGE * MRP CONTROLER : #PRS~ #PRS~ #UID~ MATERIAL GROUP : ++++++++++++++++++++++++++++++++++++++++ * Text Description : - Task Completed : 0150 `` DO00 `` Task Description : NC PRIS
A6: 216605359 | B6: REJ_RW | C6: Rejection with a rework order | D6: SERIE | E6: A330 | F6: 740VU | G6: 2152 | H6: 2026-03-03 | I6: 1 | J6: 6325010000 | K6: Vis de fixation endommagée decoupling | L6: 6325010000 | M6: 17CE | P6: =IFERROR(IF(INDEX('Parts to price'!$M$2:$M$92,MATCH(J6,'Parts to price'!$A$2:$A$92,0))="","",INDEX('Parts to price'!$M$2:$M$92,MATCH(J6,'Parts to price'!$A$2:$A$92,0))),"") | Q6: =IF(P6="","",P6*I6) | R6: Vis de fixation endommagée decoupling | TEL~ #TEL~ NonConformity 0001 : Type of nonconformity : Electrical Assembly Installation * Lors de l'installation du decoupling unit pwr FIN 17CE ; P/N:530AL01CN S/N : 66874 CMS:6325010000 sur le socle de la platine relais du 740VU MSN 2152 nous avons constaté que la vis de fixation de celui-ci est endommagée . * Merci de nous fournir un nouvel equipement TEL~ #TEL~ Task Completed : 0100 `` DEC0 `` Decision Taken : REJECT Part Fitted Justification : vis de fixations endommagée ++++++++++++++++++++++++++++++++++++++++ Material characteristics * WBS : MSF
A7: 217149326 | B7: REJ_RW | C7: Rejection with a rework order | D7: SERIE | E7: A330 | F7: 740VU | G7: 2154 | H7: 2026-04-28 | I7: 1 | J7: 6325010000 | K7: DECOUPLING UNIT CASSE | L7: 6325010000 | M7: 17CE | N7: F92511185000S23 | O7: FINITION 740VU | P7: =IFERROR(IF(INDEX('Parts to price'!$M$2:$M$92,MATCH(J7,'Parts to price'!$A$2:$A$92,0))="","",INDEX('Parts to price'!$M$2:$M$92,MATCH(J7,'Parts to price'!$A$2:$A$92,0))),"") | Q7: =IF(P7="","",P7*I7) | R7: DECOUPLING UNIT CASSE | NonConformity 0001 : Type of nonconformity : Electrical Assembly Installation * Sur la ligne A330 , 740VU , MSN 2154 , nous constatons que le decoupling unit 6325010000 sur FIN 17CE est cassé. * Nous demandons le remplacement de l'équipement Text Description : - TEL~ #TEL~ Task Completed : 0200 `` DO00 `` Task Description : NC prise en compte par OF 1029395238 .
A8: 216364146 | B8: REJ | C8: Rejection | D8: SERIE | E8: A330 | F8: 743VU | G8: 2149 | H8: 2026-02-06 | I8: 1 | J8: 6325011700 | K8: MANQUE ECROU SUR BASE CONTACTEUR | L8: 6325011700 | N8: F92513900000S02 | O8: MECA MEUBLE 743VU | P8: =IFERROR(IF(INDEX('Parts to price'!$M$2:$M$92,MATCH(J8,'Parts to price'!$A$2:$A$92,0))="","",INDEX('Parts to price'!$M$2:$M$92,MATCH(J8,'Parts to price'!$A$2:$A$92,0))),"") | Q8: =IF(P8="","",P8*I8) | R8: MANQUE ECROU SUR BASE CONTACTEUR | NonConformity 0001 : Type of nonconformity : Electrical Assembly Installation * Sur la ligne A330 , MSN 2149 , 743 VU , nous constatons lors de l'installation que l'écrou en borne F est manquant sur le base contacteur 6325011700. * Nous demandons le remplacement de l'équipement. Text Description : - TEL~ #TEL~ Task Completed : 0200 `` DO00 `` Task Description : Pas d'action côté ST - TEL~ Task Completed : 0400 `` ATW0 `` Task Description : Travail effectué - Task Completed : 1000 `` ATQ0 `` Task Description : REMIS EN CONFORMITE
A9: 218048183 | B9: REJ_RW | C9: Rejection with a rework order | D9: SERIE | E9: A330 | F9: Other | G9: 2136 | H9: 2026-08-20 | I9: 1 | J9: 6325018500 | K9: VU/BUTTON/MECA | L9: 6325018500 | M9: 2WD1 | N9: FREW25CABINMUL018A | O9: VERIF. INSPEC. ASSIST. FINAL CABINE | P9: =IFERROR(IF(INDEX('Parts to price'!$M$2:$M$92,MATCH(J9,'Parts to price'!$A$2:$A$92,0))="","",INDEX('Parts to price'!$M$2:$M$92,MATCH(J9,'Parts to price'!$A$2:$A$92,0))),"") | Q9: =IF(P9="","",P9*I9) | R9: VU/BUTTON/MECA | Non Conformity 0001 : Type of nonconformity : Part incorrectly fitted * Suite QSR COCKPIT / Cockpit / Aircraft axe / VU BUTTON / - AAD - Pièce mal montée / positionnée Suite au QSR TO/F/EQ/26-00012 nous demandons le remplacement de l'équipement 2WD1 faisant partie du 255VU. * P/N : 334VZ01Y00 CMS : 6325018500 S/N : 334VZ40588 * Demandons intervention. Code cause : Défectueux / endommagé cassé NC_W Due to QSR COCKPIT / Cockpit / Aircraft axe / VU BUTTON / - AAD - Part incorrectly fitted Following QSR TO/F/EQ/26-00012 we require the replacement of equipment 2WD1 which is part
A10: 216701404 | B10: REJ_RW | C10: Rejection with a rework order | D10: SERIE | E10: A330 | F10: PTVU | G10: 2151 | H10: 2026-03-12 | I10: 1 | J10: 6330420000 | K10: ERGOT WARNING HORN H.S. | L10: 6330420000 | N10: F9251685600000 | O10: ELEC ASSY 265VU | P10: =IFERROR(IF(INDEX('Parts to price'!$M$2:$M$92,MATCH(J10,'Parts to price'!$A$2:$A$92,0))="","",INDEX('Parts to price'!$M$2:$M$92,MATCH(J10,'Parts to price'!$A$2:$A$92,0))),"") | Q10: =IF(P10="","",P10*I10) | R10: ERGOT WARNING HORN H.S. | NonConformity 0001 : Type of nonconformity : Electrical Assembly Installation * Sur la ligne A330 , MSN 2151 , 265VU , nous constatons lors de l'installation que l'ergot sur le warning horn 6330420000 est endomagé. * Nous demandons le remplacement de l'équipement. Text Description : - TEL~ #TEL~ Task Completed : 0150 `` DO00 `` Task Description : NC taité sur S03 1028810052 - TEL~ Task Completed : 0400 `` ATW0 `` Task Description : Travail effectué - Task Completed : 1000 `` ATQ0 `` Task Description : Check ok
A11: 17063910 | B11: REJ | C11: Rejection | D11: SERIE | E11: A330 | F11: Other | G11: 2151 | H11: 2026-03-12 | I11: 1 | J11: 6330420000 | K11: ERGOT WARNING HORN H.S. | L11: 6330420000 | P11: =IFERROR(IF(INDEX('Parts to price'!$M$2:$M$92,MATCH(J11,'Parts to price'!$A$2:$A$92,0))="","",INDEX('Parts to price'!$M$2:$M$92,MATCH(J11,'Parts to price'!$A$2:$A$92,0))),"") | Q11: =IF(P11="","",P11*I11) | R11: ERGOT WARNING HORN H.S. | NonConformity 0001 : Type of nonconformity : Electrical Assembly Installation * Sur la ligne A330 , MSN 2151 , 265VU , nous constatons lors de l'installation que l'ergot sur le warning horn 6330420000 est endomagé. * Nous demandons le remplacement de l'équipement.
A12: 217344532 | B12: REJ | C12: Rejection | D12: SERIE | E12: A330 | F12: PTVU | G12: 2159 | H12: 2026-05-21 | I12: 1 | J12: 6374843100 | K12: ETEC 417LF NON CONFORME | L12: 6374843100 | M12: 417LF | N12: F9251671100000 | O12: ELEC ASSY 417VU | P12: =IFERROR(IF(INDEX('Parts to price'!$M$2:$M$92,MATCH(J12,'Parts to price'!$A$2:$A$92,0))="","",INDEX('Parts to price'!$M$2:$M$92,MATCH(J12,'Parts to price'!$A$2:$A$92,0))),"") | Q12: =IF(P12="","",P12*I12) | R12: ETEC 417LF NON CONFORME | NonConformity 0001 : Type of nonconformity : Harness * DEF 1-Q11 : ETEC 417LF CMS 6374843100 SURPLUS DE MATIERE POUR LE MONTAGE CORRECTE D'UNE VIS. Text Description : - Task Completed : 0150 `` DO00 `` Task Description : nc prise en compte par so3 1029282330 - TEL~ #TEL~ Task Completed : 0200 `` DO00 `` Task Description : Pas d'action côté ST / suivre OF série pour la suite des OP. - TEL~ Task Completed : 0400 `` ATW0 `` Task Description : TRAVAIL EFFECTUE - Task Completed : 1000 `` ATQ0 `` Task Description : remis en conformité
A13: 216064934 | B13: REJ_RW | C13: Rejection with a rework order | D13: REC | E13: A330 | F13: 414VU | G13: 2139 | H13: 2026-01-07 | I13: 1 | J13: 6374865800 | K13: INTEGRALLY LIGHTED PLATE HS | L13: 6374865800 | P13: =IFERROR(IF(INDEX('Parts to price'!$M$2:$M$92,MATCH(J13,'Parts to price'!$A$2:$A$92,0))="","",INDEX('Parts to price'!$M$2:$M$92,MATCH(J13,'Parts to price'!$A$2:$A$92,0))),"") | Q13: =IF(P13="","",P13*I13) | R13: INTEGRALLY LIGHTED PLATE HS | NonConformity 0001 : Type of nonconformity : Electrical Assembly Installation * Suite à NC 216057897 , création de la NC pour remplacement de la INTEGRALLY LIGHTED PLATE 6374865800. la remise en conformité sera faite par l'équipe REC. * Task Completed : 0100 `` DEC0 `` Decision Taken : REJECT Part Fitted Justification : INTEGRALLY LIGHTED PLATE HS ++++++++++++++++++++++++++++++++++++++++ Material characteristics * WBS : MSF-002139/FB164 Material : 000000006374865800 * MRP CONTROLER : SMITH Emmanuel STORAGE LOCATION : TS2F MATERIAL GROUP : BLAF LIGHTED_PLATE +++++
A14: 216704810 | B14: REJ | C14: Rejection | D14: SERIE | E14: A330 | F14: PTVU | G14: 2158 | H14: 2026-03-12 | I14: 1 | J14: 6374867600 | K14: INTEGRALLY LIGHTED PLATE H.S. | L14: 6374867600 | N14: F9251649700000 | O14: ELEC ASSY 245VU | P14: =IFERROR(IF(INDEX('Parts to price'!$M$2:$M$92,MATCH(J14,'Parts to price'!$A$2:$A$92,0))="","",INDEX('Parts to price'!$M$2:$M$92,MATCH(J14,'Parts to price'!$A$2:$A$92,0))),"") | Q14: =IF(P14="","",P14*I14) | R14: INTEGRALLY LIGHTED PLATE H.S. | NonConformity 0001 : Type of nonconformity : Electrical Assembly Installation * Sur la ligne A330 , MSN 2158 , 245VU , nous constatons lors de la réception que la lighted plate 6374867600 est endommagée. Voir standard doc. * Nous demandons le remplacement de l'équipement. Task Completed : 0100 `` DEC0 `` Decision Taken : REJECT Part Not Fitted Justification : Etec rayée ++++++++++++++++++++++++++++++++++++++++ Material characteristics * WBS : MSF-002158/FB149 Material : 000000006374867600 * MRP CONTROLER : SMITH Emmanuel STORAGE LOCATION : TS2F MATERIAL GROUP :
A15: 217109331 | B15: REJ_RW | C15: Rejection with a rework order | D15: SERIE | E15: A330 | F15: PTVU | G15: 2155 | H15: 2026-04-23 | I15: 1 | J15: ABS0064-01 | K15: BOUTON POUSSOIR INCOMPLET | L15: ABS0064-01 | N15: F9251694600000 | O15: ELEC ASSY 261VU | P15: =IFERROR(IF(INDEX('Parts to price'!$M$2:$M$92,MATCH(J15,'Parts to price'!$A$2:$A$92,0))="","",INDEX('Parts to price'!$M$2:$M$92,MATCH(J15,'Parts to price'!$A$2:$A$92,0))),"") | Q15: =IF(P15="","",P15*I15) | R15: BOUTON POUSSOIR INCOMPLET | NonConformity 0001 : Type of nonconformity : Electrical Assembly Installation * Sur la ligne A330 , MSN 2155 , 261VU , nous constatons que le bouton poussoir ABS0064-01 est incomplet. Rondelle et écrou manquants. * Nous demandons le remplacement de l'équipement. Text Description : - TEL~ #TEL~ Task Completed : 0200 `` DO00 `` Task Description : 1029379066 TEL~ #TEL~ NC prise en compte par OF 1029379066. - TEL~ Task Completed : 0400 `` ATW0 `` Task Description : Travail effectué - Task Completed : 1000 `` ATQ0 `` Task Description : CHECK OK *
A16: 217112253 | B16: REJ_RW | C16: Rejection with a rework order | D16: SERIE | E16: A330 | F16: PTVU | G16: 2155 | H16: 2026-04-23 | I16: 1 | J16: ABS0064-01 | K16: BOUTON POUSSOIR INCOMPLET | L16: ABS0064-01 | M16: 14WH | N16: F9251695700000 | O16: ELEC ASSY 262VU | P16: =IFERROR(IF(INDEX('Parts to price'!$M$2:$M$92,MATCH(J16,'Parts to price'!$A$2:$A$92,0))="","",INDEX('Parts to price'!$M$2:$M$92,MATCH(J16,'Parts to price'!$A$2:$A$92,0))),"") | Q16: =IF(P16="","",P16*I16) | R16: BOUTON POUSSOIR INCOMPLET | NonConformity 0001 : Type of nonconformity : Electrical Assembly Installation * Sur la ligne A330 , MSN 2155 , 262VU , nous constatons que le bouton poussoir ABS0064-01 est incomplet : Rondelle et écrou manquants. * Nous demandons le remplacement de l'équipement. * Text Description : TEL~ #TEL~ Concerné FIN 14WH - TEL~ #TEL~ Task Completed : 0200 `` DO00 `` Task Description : NC prise en compte par OF 1029378973. - TEL~ Task Completed : 0400 `` ATW0 `` Task Description : travail effectué - Task Completed : 1000 `` ATQ0 `` Task Description : CHECK OK
A17: 217139270 | B17: REJ | C17: Rejection | D17: SERIE | E17: A330 | F17: PTVU | G17: 2140 | H17: 2026-04-27 | I17: 1 | J17: ABS0064-01 | K17: BOUTON POUSSOIR ENDOMMAGE | L17: ABS0064-01 | N17: F9251693200000 | O17: ELEC ASSY 261VU | P17: =IFERROR(IF(INDEX('Parts to price'!$M$2:$M$92,MATCH(J17,'Parts to price'!$A$2:$A$92,0))="","",INDEX('Parts to price'!$M$2:$M$92,MATCH(J17,'Parts to price'!$A$2:$A$92,0))),"") | Q17: =IF(P17="","",P17*I17) | R17: BOUTON POUSSOIR ENDOMMAGE | NonConformity 0001 : Type of nonconformity : Electrical Assembly Installation * Sur la ligne A330 , nous avons constaté que le bouton poussoir ABS0064-01 est endommagé. * Text Description : - TEL~ Task Completed : 0400 `` ATW0 `` Task Description : Travail effectué - Task Completed : 1000 `` ATQ0 `` Task Description : remis en conformité
A18: 216758007 | B18: REJ | C18: Rejection | D18: SERIE | E18: A330 | F18: PTVU | G18: 2158 | H18: 2026-03-18 | I18: 1 | J18: ABS0951B3LM002 | K18: INDICATEUR ABS0951B3LM002 H.S. | L18: ABS0951B3LM002 | N18: F9251649300000 | O18: ELEC ASSY 221VU | P18: =IFERROR(IF(INDEX('Parts to price'!$M$2:$M$92,MATCH(J18,'Parts to price'!$A$2:$A$92,0))="","",INDEX('Parts to price'!$M$2:$M$92,MATCH(J18,'Parts to price'!$A$2:$A$92,0))),"") | Q18: =IF(P18="","",P18*I18) | R18: INDICATEUR ABS0951B3LM002 H.S. | NonConformity 0001 : Type of nonconformity : Electrical Assembly Installation * Sur la ligne A330 , MSN 2158 , 221VU , nous constatons lors de l'installation que l'indicateur ABS0951B3LM002 est endommagé. * Nous demandons le remplacement de l'équipement. Text Description : TEL~ #TEL~ Pas d'action côté ST - Task Completed : 1000 `` ATQ0 `` Task Description : Check ok
A19: 217253448 | B19: REJ_RW | C19: Rejection with a rework order | D19: SERIE | E19: A330 | F19: PTVU | G19: 2159 | H19: 2026-05-11 | I19: 1 | J19: ABS0951B3LP114 | K19: INDICATEUR ENDOMMAGE | L19: ABS0951B3LP114 | M19: 27MQ | N19: F9251684300000 | O19: ELEC ASSY 271VU | P19: =IFERROR(IF(INDEX('Parts to price'!$M$2:$M$92,MATCH(J19,'Parts to price'!$A$2:$A$92,0))="","",INDEX('Parts to price'!$M$2:$M$92,MATCH(J19,'Parts to price'!$A$2:$A$92,0))),"") | Q19: =IF(P19="","",P19*I19) | R19: INDICATEUR ENDOMMAGE | NonConformity 0001 : Type of nonconformity : Electrical Assembly Installation * Sur la ligne A330 , MSN 2159 , 271 VU , nous constatons que l'indicateur ABS0951B3LP114 sur le FIN 27MQ est endommagé. * Nous demandons le remplacement de l'équipement. Text Description : - TEL~ #TEL~ Task Completed : 0200 `` DO00 `` Task Description : NCprise en compte par OF 1029590952. - TEL~ Task Completed : 0400 `` ATW0 `` Task Description : travail effectué - Task Completed : 1000 `` ATQ0 `` Task Description : Vu remis en conformité
A20: 217447449 | B20: REJ | C20: Rejection | D20: SERIE | E20: A330 | F20: PTVU | G20: 2161 | H20: 2026-06-03 | I20: 1 | J20: ABS0971-003A01 | K20: CABLE COURT SUITE ERREUR SERTISSAGE | L20: ABS0971-003A01 | N20: F9251689100000 | O20: ELEC ASSY 538VU | P20: =IFERROR(IF(INDEX('Parts to price'!$M$2:$M$92,MATCH(J20,'Parts to price'!$A$2:$A$92,0))="","",INDEX('Parts to price'!$M$2:$M$92,MATCH(J20,'Parts to price'!$A$2:$A$92,0))),"") | Q20: =IF(P20="","",P20*I20) | R20: CABLE COURT SUITE ERREUR SERTISSAGE | NonConformity 0001 : Type of nonconformity : Electrical Assembly Installation * Sur la ligne A330 , MSN 2161 , 538VU , nous constatons suite à une erreur de sertissage que le câble 4631-1221 est trop court. * Nous demandons la re fabrication du câble ainsi que l'installation du connecteur ABS0971-003A01. Task Completed : 0100 `` DEC0 `` Decision Taken : REJECT Part Not Fitted Justification : Câble 4631-1221 trop court suite à erreur de sertissage * MRP CONTROLER : MATERIAL GROUP : ++++++++++++++++++++++++++++++++++++++++ * Text Description : - Task Compl
A21: 216609710 | B21: EXC | C21: Exchange | D21: SERIE | E21: A350 | F21: MIP A350 | G21: 829 | H21: 2026-03-03 | I21: 1 | J21: ABS1424-3-10 | K21: Colonnette de la structure du MIP cassée | L21: ABS1424-3-10 | N21: V92814615000S01 | O21: Intégration harnais 1101VB sur MIP | P21: =IFERROR(IF(INDEX('Parts to price'!$M$2:$M$92,MATCH(J21,'Parts to price'!$A$2:$A$92,0))="","",INDEX('Parts to price'!$M$2:$M$92,MATCH(J21,'Parts to price'!$A$2:$A$92,0))),"") | Q21: =IF(P21="","",P21*I21) | R21: Colonnette de la structure du MIP cassée | TEL~ #TEL~ NonConformity 0001 : Type of nonconformity : Structural and Mechanical Assembly * Sur le MIP A350 poste integration nous avons endommagé la colonette ABS 1424-3-10 situé dans le pylone central. Veuillez s'il vous plait proceder à sont remplacement. TEL~ #TEL~ Task Completed : 0100 `` DEC0 `` Request for Supplier Assessment Decision Taken : External Exchange Text Description : - Task Completed : 1000 `` ATQ0 `` Task Description : Travail effectué par CIB. - Task Completed : 1000 `` ATQ0 `` Task Description : > X > X* Task Description : >
A22: 217040142 | B22: EXC | C22: Exchange | D22: SERIE | E22: A350 | F22: Other | G22: 843 | H22: 2026-04-16 | I22: 1 | J22: ABS1424-3-10 | K22: Colonnette de la structure du MIP cassée | L22: ABS1424-3-10 | P22: =IFERROR(IF(INDEX('Parts to price'!$M$2:$M$92,MATCH(J22,'Parts to price'!$A$2:$A$92,0))="","",INDEX('Parts to price'!$M$2:$M$92,MATCH(J22,'Parts to price'!$A$2:$A$92,0))),"") | Q22: =IF(P22="","",P22*I22) | R22: Colonnette de la structure du MIP cassée | NonConformity 0001 : Type of nonconformity : Broken * Sur le MIP A350 , MSN843 , un opérateur nous a signalé qu’il a endommagé une colonnette de référence ABS1424-3-10 dans le pylône. Aprés constatation nous demandons le remplacement de celle-ci. Task Completed : 0100 `` DEC0 `` Request for Supplier Assessment Decision Taken : External Exchange Text Description :
A23: 217749687 | B23: EXC | C23: Exchange | D23: SERIE | E23: A350 | F23: MIP A350 | G23: 860 | H23: 2026-07-02 | I23: 1 | J23: ABS1424-3-10 | K23: Colonette Cassée | L23: ABS1424-3-10 | N23: V92814615000S01 | O23: Intégration harnais 1101VB sur MIP | P23: =IFERROR(IF(INDEX('Parts to price'!$M$2:$M$92,MATCH(J23,'Parts to price'!$A$2:$A$92,0))="","",INDEX('Parts to price'!$M$2:$M$92,MATCH(J23,'Parts to price'!$A$2:$A$92,0))),"") | Q23: =IF(P23="","",P23*I23) | R23: Colonette Cassée | 567198748 NonConformity 0001 : Type of nonconformity : Structural and Mechanical Assembly * Sur le MIP A350 poste integration npous avons endommagé la colonette ABS 1424-3-10 situé dans le pylone central. Veuillez s'il vous plait proceder à sont remplacement NonConformity 0001 : Type of nonconformity : Structural and Mechanical Assembly * Sur le MIP A350 poste integration nous avons endommagé la colonette ABS 1424-3-10 situé dans le pylone central. Veuillez s'il vous plait proceder à sont remplacement TEL~ #TEL~ Task Completed : 0100 `` DEC0 `` Request for Supplier Assessm
A24: 216846510 | B24: REJ | C24: Rejection | D24: SERIE | E24: A330 | F24: PTVU | G24: 2153 | H24: 2026-03-26 | I24: 1 | J24: ABS1551L4AD0A | K24: EQUIPEMENT ENDOMMAGE | L24: ABS1551L4AD0A | N24: F9251672000000 | O24: ELEC ASSY 119VU | P24: =IFERROR(IF(INDEX('Parts to price'!$M$2:$M$92,MATCH(J24,'Parts to price'!$A$2:$A$92,0))="","",INDEX('Parts to price'!$M$2:$M$92,MATCH(J24,'Parts to price'!$A$2:$A$92,0))),"") | Q24: =IF(P24="","",P24*I24) | R24: EQUIPEMENT ENDOMMAGE | NonConformity 0001 : Type of nonconformity : Electrical Assembly Installation * Sur la ligne A330 , MSN 2153 , 119VU , nous constatons que l'équipement ABS1551L4AD0A est endommagé. * Nous demandons le remplcement de l'équipement. Text Description : - TEL~ #TEL~ Task Completed : 0150 `` DO00 `` Task Description : > X TEL~ #TEL~ > X* NC traité sur SO1 * - TEL~ #TEL~ Task Completed : 0200 `` DO00 `` Task Description : > X TEL~ #TEL~ > X* Pas d'action côté ST. * - TEL~ Task Completed : 0400 `` ATW0 `` Task Description : Travail effectué
A25: 216943511 | B25: REJ_RW | C25: Rejection with a rework order | D25: SERIE | E25: A330 | F25: PTVU | G25: 2158 | H25: 2026-04-07 | I25: 1 | J25: ABS1650-02 | K25: BOUTON OPTICAL ENCODEUR HS | L25: ABS1650-02 | N25: F9251647200000 | O25: ELEC ASSY 313VU | P25: =IFERROR(IF(INDEX('Parts to price'!$M$2:$M$92,MATCH(J25,'Parts to price'!$A$2:$A$92,0))="","",INDEX('Parts to price'!$M$2:$M$92,MATCH(J25,'Parts to price'!$A$2:$A$92,0))),"") | Q25: =IF(P25="","",P25*I25) | R25: BOUTON OPTICAL ENCODEUR HS | NonConformity 0001 : Type of nonconformity : Electrical Assembly Installation * Sur la ligne A330 , nous constatons que le bouton de l'encodeur optical est endommagé = > ABS1650-02. nous demandons la remise en conformité du produit. Text Description : - TEL~ #TEL~ Task Completed : 0150 `` DO00 `` Task Description : NC traitée sous SO3 1029127030 - TEL~ #TEL~ Task Completed : 0200 `` DO00 `` Task Description : Pas d'action côté ST - TEL~ Task Completed : 0400 `` ATW0 `` Task Description : Travail effectué
A26: 217613680 | B26: REJ_RW | C26: Rejection with a rework order | D26: SERIE | E26: A330 | F26: PTVU | G26: 2163 | H26: 2026-06-19 | I26: 1 | J26: ABS1650-02 | K26: CABLES ABIMES SUR OPTICAL ENCODER | L26: ABS1650-02 | N26: F9251647200000 | O26: ELEC ASSY 313VU | P26: =IFERROR(IF(INDEX('Parts to price'!$M$2:$M$92,MATCH(J26,'Parts to price'!$A$2:$A$92,0))="","",INDEX('Parts to price'!$M$2:$M$92,MATCH(J26,'Parts to price'!$A$2:$A$92,0))),"") | Q26: =IF(P26="","",P26*I26) | R26: CABLES ABIMES SUR OPTICAL ENCODER | NonConformity 0001 : Type of nonconformity : Electrical Assembly Installation * Sur la ligne A330 , MSN 2163 , 313 VU , nous constatons que les câbles sur l'optical encoder ABS1650-02 ont été abîmés par la pince à dénuder. * Nous demandons le remplacement de l'équipement. Text Description : - TEL~ #TEL~ Task Completed : 0200 `` DO00 `` Task Description : NC prise en compte per OF 1030084727. - Task Completed : 0400 `` ATW0 `` Task Description : remis en conformité - Task Completed : 1000 `` ATQ0 `` Task Description : CHECK OK
A27: 217613893 | B27: REJ_RW | C27: Rejection with a rework order | D27: SERIE | E27: A330 | F27: PTVU | G27: 2163 | H27: 2026-06-19 | I27: 1 | J27: ABS1650-02 | K27: CABLES ABIMES SUR OPTICAL ENCODER | L27: ABS1650-02 | N27: F9251647400000 | O27: ELEC ASSY 314VU | P27: =IFERROR(IF(INDEX('Parts to price'!$M$2:$M$92,MATCH(J27,'Parts to price'!$A$2:$A$92,0))="","",INDEX('Parts to price'!$M$2:$M$92,MATCH(J27,'Parts to price'!$A$2:$A$92,0))),"") | Q27: =IF(P27="","",P27*I27) | R27: CABLES ABIMES SUR OPTICAL ENCODER | NonConformity 0001 : Type of nonconformity : Electrical Assembly Installation * Sur la ligne A330 , MSN 2163 , 314 VU , nous constatons que les câbles sur l'optical encoder ABS1650-02 sont abîmés suite à un mauvais dénudage. * Nous demandons le remplacement de l'équipement. Text Description : - TEL~ #TEL~ Task Completed : 0200 `` DO00 `` Task Description : NC prise en compte par OF 1030085567 - Task Completed : 0400 `` ATW0 `` Task Description : remis en conformité - Task Completed : 1000 `` ATQ0 `` Task Description : CHECK OK *
A28: 216958097 | B28: REJ | C28: Rejection | D28: SERIE | E28: A330 | F28: PTVU | G28: 2158 | H28: 2026-04-08 | I28: 1 | J28: ABS1650-03 | K28: BOUTON OPTICAL ENCODEUR HS | L28: ABS1650-03 | N28: F9251647200000 | O28: ELEC ASSY 313VU | P28: =IFERROR(IF(INDEX('Parts to price'!$M$2:$M$92,MATCH(J28,'Parts to price'!$A$2:$A$92,0))="","",INDEX('Parts to price'!$M$2:$M$92,MATCH(J28,'Parts to price'!$A$2:$A$92,0))),"") | Q28: =IF(P28="","",P28*I28) | R28: BOUTON OPTICAL ENCODEUR HS | NonConformity 0001 : Type of nonconformity : Electrical Assembly Installation * Sur la ligne A330 , nous constatons que le bouton de l'encodeur optical a été endommagé. ABS1650-03 Task Completed : 0100 `` DEC0 `` Decision Taken : REJECT Part Not Fitted Justification : BOUTON ENDOMMAGE * MRP CONTROLER : MATERIAL GROUP : ++++++++++++++++++++++++++++++++++++++++ * Text Description : - TEL~ #TEL~ Task Completed : 0150 `` DO00 `` Task Description : traitée sous 1028548452 - Task Completed : 1000 `` ATQ0 `` Task Description : produit remis en conformité
A29: 218388588 | B29: REJ_RW | C29: Rejection with a rework order | D29: SERIE | E29: A330 | F29: PTVU | G29: 2170 | H29: 2026-09-24 | I29: 1 | J29: ABS1650-03 | K29: Optical encoder endommagé | L29: ABS1650-03 | M29: 105SG1 | N29: F9251647200000 | O29: ELEC ASSY 313VU | P29: =IFERROR(IF(INDEX('Parts to price'!$M$2:$M$92,MATCH(J29,'Parts to price'!$A$2:$A$92,0))="","",INDEX('Parts to price'!$M$2:$M$92,MATCH(J29,'Parts to price'!$A$2:$A$92,0))),"") | Q29: =IF(P29="","",P29*I29) | R29: Optical encoder endommagé | NonConformity 0001 : Type of nonconformity : Electrical Assembly Installation * Sur la ligne A330 , 313VU , nous constatons que le optical encoder ABS1650-03 sur le FIN 105SG1 est endommagé Text Description : - TEL~ #TEL~ Task Completed : 0200 `` DO00 `` Task Description : NC prise en compte par OF 1031192907 .
A30: 217921499 | B30: REJ_RW | C30: Rejection with a rework order | D30: SERIE | E30: A350 | F30: MIP A350 | G30: 866 | H30: 2026-07-22 | I30: 1 | J30: ABS1896A08E | K30: Backshell abimé lors du torquage | L30: ABS1896A08E | M30: 52CV-A | N30: VESAW92C31101TA2M | O30: 1101VB MIP SUPER 2M A | P30: =IFERROR(IF(INDEX('Parts to price'!$M$2:$M$92,MATCH(J30,'Parts to price'!$A$2:$A$92,0))="","",INDEX('Parts to price'!$M$2:$M$92,MATCH(J30,'Parts to price'!$A$2:$A$92,0))),"") | Q30: =IF(P30="","",P30*I30) | R30: Backshell abimé lors du torquage | NonConformity 0001 : Type of nonconformity : Mis-alignment * Sur la route 2M du MSN 866 , le backshell ABS1896A08E de la prise 52CV-A s'est abimé lors du torquage. ( détrompeur HS ) Merci de nous en fournir un nouveau Text Description : - Task Completed : 0400 `` ATW0 `` Task Description : NC OK - Task Completed : 1000 `` ATQ0 `` Task Description : E/S backshell effectué
A31: 216758388 | B31: EXC | C31: Exchange | D31: SERIE | E31: A350 | F31: Other | G31: 835 | H31: 2026-03-18 | I31: 1 | J31: ASNA2327-3-3 | K31: Ecrou riveté endommagé sur la structure | L31: ASNA2327-3-3 | P31: =IFERROR(IF(INDEX('Parts to price'!$M$2:$M$92,MATCH(J31,'Parts to price'!$A$2:$A$92,0))="","",INDEX('Parts to price'!$M$2:$M$92,MATCH(J31,'Parts to price'!$A$2:$A$92,0))),"") | Q31: =IF(P31="","",P31*I31) | R31: Ecrou riveté endommagé sur la structure | NonConformity 0001 : Type of nonconformity : Fastener ( incl. Bolt/Screw/Washer/Bush ) * Sur la ligne A350 , poste Integration , nous avons constaté que l'écrou riveté ASNA2327-3-3 est endommagé . Nous demmandons une intervention pour la remise en conformité de la structure. Task Completed : 0100 `` DEC0 `` Request for Supplier Assessment Decision Taken : External Exchange Text Description : - Task Completed : 1000 `` ATQ0 `` Task Description : Travail effectué par CIB .
A32: 218277387 | B32: EXC | C32: Exchange | D32: SERIE | E32: A350 | F32: Other | G32: 869 | H32: 2026-09-15 | I32: 1 | J32: ASNA2327-3-3 | K32: Support ASNA2327-3-3 endommagé | L32: ASNA2327-3-3 | P32: =IFERROR(IF(INDEX('Parts to price'!$M$2:$M$92,MATCH(J32,'Parts to price'!$A$2:$A$92,0))="","",INDEX('Parts to price'!$M$2:$M$92,MATCH(J32,'Parts to price'!$A$2:$A$92,0))),"") | Q32: =IF(P32="","",P32*I32) | R32: Support ASNA2327-3-3 endommagé | Support ASNA2327-3-3 endommagé NonConformity 0001 : Type of nonconformity : Structural and Mechanical Assembly * Sur la ligne A350 , poste MECA , l'opérateur a endommagé un support ASNA2327-3-3 lors de l'assemblage de colonnette et de support lacotte. Nous demandons le remplacement du support ASNA2327-3-3 et d'une éventuelle réparation de la structure si elle est endommagée ( à voir lors d'une remplacement du support ) . Task Completed : 0100 `` DEC0 `` Request for Supplier Assessment Decision Taken : External Exchange Text Description :
A33: 216177953 | B33: EXC | C33: Exchange | D33: SERIE | E33: A350 | F33: Other | G33: 817 | H33: 2026-01-20 | I33: 1 | J33: ASNA2328-3-4 | K33: Colonnette de la structure du MIP cassée | L33: ASNA2328-3-4 | P33: =IFERROR(IF(INDEX('Parts to price'!$M$2:$M$92,MATCH(J33,'Parts to price'!$A$2:$A$92,0))="","",INDEX('Parts to price'!$M$2:$M$92,MATCH(J33,'Parts to price'!$A$2:$A$92,0))),"") | Q33: =IF(P33="","",P33*I33) | R33: Colonnette de la structure du MIP cassée | NonConformity 0001 : Type of nonconformity : Structural and Mechanical Assembly * Sur la ligne A350 poste Integration , nous avons endommagé la colonnette ASNA2328-3-4 en appliquant l'OF 1027315420. * Def : Q10-004 : Colonnette cassée. * Demandons remise en conformité du produit Task Completed : 0100 `` DEC0 `` Request for Supplier Assessment Decision Taken : External Exchange Text Description :
A34: 216247653 | B34: EXC | C34: Exchange | D34: SERIE | E34: A350 | F34: Other | G34: 819 | H34: 2026-01-26 | I34: 1 | J34: ASNA2328-3-4 | K34: Colonnette de la structure du MIP cassée | L34: ASNA2328-3-4 | P34: =IFERROR(IF(INDEX('Parts to price'!$M$2:$M$92,MATCH(J34,'Parts to price'!$A$2:$A$92,0))="","",INDEX('Parts to price'!$M$2:$M$92,MATCH(J34,'Parts to price'!$A$2:$A$92,0))),"") | Q34: =IF(P34="","",P34*I34) | R34: Colonnette de la structure du MIP cassée | 567198748 NonConformity 0001 : Type of nonconformity : Structural and Mechanical Assembly * Sur la ligne A350 poste Integration , nous avons endommagé la colonnette ASNA2328-3-4 Veulliez proceder au remplacement de celle-ci. NonConformity 0001 : Type of nonconformity : Structural and Mechanical Assembly * Sur la ligne A350 poste Integration , nous avons endommagé la colonnette ASNA2328-3-4 Veulliez proceder au remplacement de celle-ci. NonConformity 0001 : Type of nonconformity : Broken * Sur la ligne A350 poste Integration , nous avons endommagé la
A35: 216376660 | B35: EXC | C35: Exchange | D35: SERIE | E35: A350 | F35: Other | G35: 823 | H35: 2026-02-09 | I35: 1 | J35: ASNA2328-3-4 | K35: Colonnette de la structure du MIP cassée | L35: ASNA2328-3-4 | P35: =IFERROR(IF(INDEX('Parts to price'!$M$2:$M$92,MATCH(J35,'Parts to price'!$A$2:$A$92,0))="","",INDEX('Parts to price'!$M$2:$M$92,MATCH(J35,'Parts to price'!$A$2:$A$92,0))),"") | Q35: =IF(P35="","",P35*I35) | R35: Colonnette de la structure du MIP cassée | NonConformity 0001 : Type of nonconformity : Broken * Sur la ligne A350 , poste Integration du MSN 823 , nous avons constaté que la colonnette ASNA2328-3-4 est endommagée. Nous demandons le remplacement de celle-ci. * Task Completed : 0100 `` DEC0 `` Request for Supplier Assessment Decision Taken : External Exchange Text Description :
A36: 216227502 | B36: REJ | C36: Rejection | D36: SERIE | E36: A330 | F36: PTVU | G36: 2152 | H36: 2026-01-23 | I36: 1 | J36: COMPOSANT SCRAPE | K36: COMPOSANT SCRAPE | N36: F9251684200000 | O36: ELEC ASSY 255VU | P36: =IFERROR(IF(INDEX('Parts to price'!$M$2:$M$92,MATCH(J36,'Parts to price'!$A$2:$A$92,0))="","",INDEX('Parts to price'!$M$2:$M$92,MATCH(J36,'Parts to price'!$A$2:$A$92,0))),"") | Q36: =IF(P36="","",P36*I36) | R36: COMPOSANT SCRAPE | NonConformity 0001 : Type of nonconformity : Electrical Assembly Installation * le FIRE PUSH A ETE SCAPE REFUS POUR REAPPRO Task Completed : 0100 `` DEC0 `` Decision Taken : REJECT Part Not Fitted Justification : FIRE PUSH SCRAPE * MRP CONTROLER : TROUIS Nathalie +33561936016 MATERIAL GROUP : ++++++++++++++++++++++++++++++++++++++++ * Text Description : - TEL~ Task Completed : 0400 `` ATW0 `` Task Description : Travail effectué - Task Completed : 1000 `` ATQ0 `` Task Description : VU REMIS EN CONFORMITE
A37: 216227907 | B37: REJ | C37: Rejection | D37: SERIE | E37: A330 | F37: PTVU | G37: 2152 | H37: 2026-01-23 | I37: 1 | J37: COMPOSANT SCRAPE | K37: COMPOSANT SCRAPE | N37: F9251684200000 | O37: ELEC ASSY 255VU | P37: =IFERROR(IF(INDEX('Parts to price'!$M$2:$M$92,MATCH(J37,'Parts to price'!$A$2:$A$92,0))="","",INDEX('Parts to price'!$M$2:$M$92,MATCH(J37,'Parts to price'!$A$2:$A$92,0))),"") | Q37: =IF(P37="","",P37*I37) | R37: COMPOSANT SCRAPE | NonConformity 0001 : Type of nonconformity : Electrical Assembly Installation * FIRE PUSH SCRAPE * Text Description : - TEL~ Task Completed : 0400 `` ATW0 `` Task Description : travail effetué - Task Completed : 1000 `` ATQ0 `` Task Description : VU REMIS EN CONFORMITE
A38: 216228052 | B38: REJ | C38: Rejection | D38: SERIE | E38: A330 | F38: PTVU | G38: 2152 | H38: 2026-01-23 | I38: 1 | J38: COMPOSANT SCRAPE | K38: COMPOSANT SCRAPE | N38: F9251684200000 | O38: ELEC ASSY 255VU | P38: =IFERROR(IF(INDEX('Parts to price'!$M$2:$M$92,MATCH(J38,'Parts to price'!$A$2:$A$92,0))="","",INDEX('Parts to price'!$M$2:$M$92,MATCH(J38,'Parts to price'!$A$2:$A$92,0))),"") | Q38: =IF(P38="","",P38*I38) | R38: COMPOSANT SCRAPE | NonConformity 0001 : Type of nonconformity : Electrical Assembly Installation * FIRE PUSH SCRAPE Text Description : - TEL~ Task Completed : 0400 `` ATW0 `` Task Description : Travail effectué - Task Completed : 1000 `` ATQ0 `` Task Description : VU REMIS EN CONFORMITE
A39: 216914342 | B39: REJ | C39: Rejection | D39: SERIE | E39: A330 | F39: PTVU | G39: 2157 | H39: 2026-04-02 | I39: 1 | J39: E0053R14B19PNF | K39: prise non conforme | L39: E0053R14B19PNF | N39: F9251671500000 | O39: ELEC ASSY 241VU | P39: =IFERROR(IF(INDEX('Parts to price'!$M$2:$M$92,MATCH(J39,'Parts to price'!$A$2:$A$92,0))="","",INDEX('Parts to price'!$M$2:$M$92,MATCH(J39,'Parts to price'!$A$2:$A$92,0))),"") | Q39: =IF(P39="","",P39*I39) | R39: prise non conforme | NonConformity 0001 : Type of nonconformity : Electrical Assembly Installation * Sur la ligne A330 , nous constatons qu'il nous a éte fourni un connecteur 14B19SN alors qu'il est demandé au dossier de fabrication un connecteur 14B19PN. nous demandons un connecteur = > E0053R14B19PNF. Task Completed : 0100 `` DEC0 `` Decision Taken : REJECT Part Not Fitted Justification : mauvais connecteur livré * MRP CONTROLER : MATERIAL GROUP : ++++++++++++++++++++++++++++++++++++++++ * Text Description : - TEL~ #TEL~ Task Completed : 0150 `` DO00 `` Task Description : NC Traité sur SO1
A40: 217687557 | B40: REJ_RW | C40: Rejection with a rework order | D40: SERIE | E40: A330 | F40: PTVU | G40: 2164 | H40: 2026-06-26 | I40: 1 | J40: E0053R14B19PNF | K40: Enfichage prise 681VC impossible | L40: E0053R14B19PNF | M40: 681VC | N40: F9251671300000 | O40: ELEC ASSY 145VU | P40: =IFERROR(IF(INDEX('Parts to price'!$M$2:$M$92,MATCH(J40,'Parts to price'!$A$2:$A$92,0))="","",INDEX('Parts to price'!$M$2:$M$92,MATCH(J40,'Parts to price'!$A$2:$A$92,0))),"") | Q40: =IF(P40="","",P40*I40) | R40: Enfichage prise 681VC impossible | NonConformity 0001 : Type of nonconformity : Incorrect connector * Lors de l'enfichage par la production des câbles sur la prise 681VC du 154VU MSN 2164 , il est constaté que plusiueurs borne ne permettent pas l'enfichage des contacts. * Prise REF : E0053R14B19PNF * Merci de changer la prise. Text Description : - TEL~ #TEL~ Task Completed : 0200 `` DO00 `` Task Description : NC prise en compte par OF 1030158587. - Task Completed : 1000 `` ATQ0 `` Task Description : remis en conformité
A41: 218070027 | B41: REJ_RW | C41: Rejection with a rework order | D41: SERIE | E41: A330 | F41: PTVU | G41: 2167 | H41: 2026-08-24 | I41: 1 | J41: E0053R18B32PNF | K41: CONNECTEUR E0053R18B32PNF H.S | L41: E0053R18B32PNF | N41: F9251670800000 | O41: ELEC ASSY 412VU | P41: =IFERROR(IF(INDEX('Parts to price'!$M$2:$M$92,MATCH(J41,'Parts to price'!$A$2:$A$92,0))="","",INDEX('Parts to price'!$M$2:$M$92,MATCH(J41,'Parts to price'!$A$2:$A$92,0))),"") | Q41: =IF(P41="","",P41*I41) | R41: CONNECTEUR E0053R18B32PNF H.S | NonConformity 0001 : Type of nonconformity : Electrical Assembly Installation * Sur la ligne A330 , MSN 2167 , 412 VU , nous constatons que le grommet sur connecteur E0053R18B32PNF est détèrioré. * Nous demandons le remplacement de l'équipement. Task Completed : 0100 `` DEC0 `` Decision Taken : REJECT Part Not Fitted Justification : Equipement HS * MRP CONTROLER : MATERIAL GROUP : ++++++++++++++++++++++++++++++++++++++++ * Text Description : - TEL~ Task Completed : 0400 `` ATW0 `` Task Description : Travail effectué
A42: 216369423 | B42: REJ | C42: Rejection | D42: SERIE | E42: A330 | F42: PTVU | G42: 2147 | H42: 2026-02-06 | I42: 1 | J42: E0053RI8B32PNF | K42: Grommets endommagés | L42: E0053RI8B32PNF | N42: F9251694200000 | O42: ELEC ASSY 925VU | P42: =IFERROR(IF(INDEX('Parts to price'!$M$2:$M$92,MATCH(J42,'Parts to price'!$A$2:$A$92,0))="","",INDEX('Parts to price'!$M$2:$M$92,MATCH(J42,'Parts to price'!$A$2:$A$92,0))),"") | Q42: =IF(P42="","",P42*I42) | R42: Grommets endommagés | NonConformity 0001 : Type of nonconformity : Electrical Assembly Installation * Sur la ligne A330 , nous constatons que le grommet est endommagé sur le connecteur E0053RI8B32PNF. Nous demandons la réappro du connecteur pour remise en conformité. * Text Description : - TEL~ Task Completed : 0400 `` ATW0 `` Task Description : Travail effectué - Task Completed : 1000 `` ATQ0 `` Task Description : remis en conformité
A43: 216431918 | B43: REJ | C43: Rejection | D43: SERIE | E43: A330 | F43: PTVU | G43: 2149 | H43: 2026-02-13 | I43: 1 | J43: E0062A0S4BJOA | K43: SWITCH-OVER ENDOMMAGE | L43: E0062A0S4BJOA | N43: F9251689600000 | O43: ELEC ASSY 215VU | P43: =IFERROR(IF(INDEX('Parts to price'!$M$2:$M$92,MATCH(J43,'Parts to price'!$A$2:$A$92,0))="","",INDEX('Parts to price'!$M$2:$M$92,MATCH(J43,'Parts to price'!$A$2:$A$92,0))),"") | Q43: =IF(P43="","",P43*I43) | R43: SWITCH-OVER ENDOMMAGE | NonConformity 0001 : Type of nonconformity : Electrical Assembly Installation * Sur la ligne A330 , MSN 2149 , 215VU , nous constatons lors de l'installation que le SWITCH-OVER E0062A0S4BJOA est endommagé. Nous demandons le remplacement de l'équipement. Text Description : - TEL~ #TEL~ Task Completed : 0150 `` DO00 `` Task Description : of 1028218109 - TEL~ Task Completed : 0400 `` ATW0 `` Task Description : Travail effectué
A44: 217913295 | B44: REJ_RW | C44: Rejection with a rework order | D44: SERIE | E44: A330 | F44: PTVU | G44: 2166 | H44: 2026-07-21 | I44: 1 | J44: E0062B1G4AD0A | K44: INVERSEUR H.S. | L44: E0062B1G4AD0A | M44: 21MQ | N44: F9251684300000 | O44: ELEC ASSY 271VU | P44: =IFERROR(IF(INDEX('Parts to price'!$M$2:$M$92,MATCH(J44,'Parts to price'!$A$2:$A$92,0))="","",INDEX('Parts to price'!$M$2:$M$92,MATCH(J44,'Parts to price'!$A$2:$A$92,0))),"") | Q44: =IF(P44="","",P44*I44) | R44: INVERSEUR H.S. | NonConformity 0001 : Type of nonconformity : Electrical Assembly Installation * Sur la ligne A330 , MSN 2166 , 271 VU , nous constatons que la borne 1C sur équipement E0062B1G4AD0A , FIN 21MQ , est endommagée. * Nous demandons le remplacement de l'équipement. Task Completed : 0100 `` DEC0 `` Decision Taken : REJECT Part Not Fitted Justification : Equipement endommagé * MRP CONTROLER : MATERIAL GROUP : ++++++++++++++++++++++++++++++++++++++++ * Text Description : - Task Completed : 0150 `` DO00 `` Task Description : CREaTION so3 1030055735 - TEL~ #TEL~ Task Completed : 0200
A45: 217571217 | B45: REJ_RW | C45: Rejection with a rework order | D45: SERIE | E45: A330 | F45: PTVU | G45: 2163 | H45: 2026-06-16 | I45: 1 | J45: E0062D1S4BA0A | K45: BORNE HS SUR SWITCH OVER | L45: E0062D1S4BA0A | M45: 34LE2 | N45: F9251647500000 | O45: ELEC ASSY 513VU | P45: =IFERROR(IF(INDEX('Parts to price'!$M$2:$M$92,MATCH(J45,'Parts to price'!$A$2:$A$92,0))="","",INDEX('Parts to price'!$M$2:$M$92,MATCH(J45,'Parts to price'!$A$2:$A$92,0))),"") | Q45: =IF(P45="","",P45*I45) | R45: BORNE HS SUR SWITCH OVER | NonConformity 0001 : Type of nonconformity : Electrical Assembly Installation * Sur la ligne A330 , MSN 2163 , 513VU , nous constatons que la borne 1A sur le switch Over E0062D1S4BA0A ( Fin 34LE2 ) ne vérouille pas. Nous demandons le remplacement de l'équipement. Text Description : - TEL~ #TEL~ Task Completed : 0200 `` DO00 `` Task Description : NC prise en compte par OF 1030037500. - Task Completed : 1000 `` ATQ0 `` Task Description : CHEC OK
A46: 218307795 | B46: REJ_RW | C46: Rejection with a rework order | D46: SERIE | E46: A330 | F46: PTVU | G46: 2169 | H46: 2026-09-17 | I46: 1 | J46: E0062D1S4BA0A | K46: Grommet de switch-over endommagé | L46: E0062D1S4BA0A | N46: F9251647600000 | O46: ELEC ASSY 514VU | P46: =IFERROR(IF(INDEX('Parts to price'!$M$2:$M$92,MATCH(J46,'Parts to price'!$A$2:$A$92,0))="","",INDEX('Parts to price'!$M$2:$M$92,MATCH(J46,'Parts to price'!$A$2:$A$92,0))),"") | Q46: =IF(P46="","",P46*I46) | R46: Grommet de switch-over endommagé | NonConformity 0001 : Type of nonconformity : Electrical Assembly Installation * Ligne A330 , MSN2169 , sur le 514VU , nous avons constaté que sur switch-overs subminiature E0062D1S4BA0A le grommet est endommagé. Nous demandons le remplacement du switch-overs subminiature E0062D1S4BA0A * Task Completed : 0100 `` DEC0 `` Decision Taken : REJECT Part Not Fitted Justification : Nous demandons le remplacement du switch-overs subminiature endommagé * MRP CONTROLER : MATERIAL GROUP : ++++++++++++++++++++++++++++++++++++++++ * Text Description : - TEL~ #TEL~ Task C
A47: 218376253 | B47: REJ_RW | C47: Rejection with a rework order | D47: SERIE | E47: A330 | F47: PTVU | G47: 2170 | H47: 2026-09-24 | I47: 1 | J47: E0062D1S4BA0A | K47: EQUIPEMENT E0062D1S4BA0A HS | L47: E0062D1S4BA0A | M47: 20LE2 | N47: F9251647600000 | O47: ELEC ASSY 514VU | P47: =IFERROR(IF(INDEX('Parts to price'!$M$2:$M$92,MATCH(J47,'Parts to price'!$A$2:$A$92,0))="","",INDEX('Parts to price'!$M$2:$M$92,MATCH(J47,'Parts to price'!$A$2:$A$92,0))),"") | Q47: =IF(P47="","",P47*I47) | R47: EQUIPEMENT E0062D1S4BA0A HS | NonConformity 0001 : Type of nonconformity : Electrical Assembly Installation * Sur la ligne A330 , MSN 2170 , 514 VU , nous constatons que l'équipement #PRS~ ( FIN 20LE2 ) est HS. * Nous demandons le remplacement de l'équipement. Task Completed : 0100 `` DEC0 `` Decision Taken : REJECT Part Not Fitted Justification : Equipement HS * MRP CONTROLER : MATERIAL GROUP : ++++++++++++++++++++++++++++++++++++++++ * Text Description : - TEL~ #TEL~ Task Completed : 0200 `` DO00 `` Task Description : NC traîté par le ST via OF 1031182335
A48: 216265972 | B48: REJ | C48: Rejection | D48: SERIE | E48: A330 | F48: PTVU | G48: 2146 | H48: 2026-01-28 | I48: 1 | J48: E0062E2D4AC0A | K48: Grommet endommagé | L48: E0062E2D4AC0A | N48: F9251690100000 | O48: ELEC ASSY 312VU | P48: =IFERROR(IF(INDEX('Parts to price'!$M$2:$M$92,MATCH(J48,'Parts to price'!$A$2:$A$92,0))="","",INDEX('Parts to price'!$M$2:$M$92,MATCH(J48,'Parts to price'!$A$2:$A$92,0))),"") | Q48: =IF(P48="","",P48*I48) | R48: Grommet endommagé | NonConformity 0001 : Type of nonconformity : Electrical Assembly Installation * Sur la ligne A330 , nous constatons que le grommet est endommagé sur le switch over E0062E2D4AC0A. Text Description : - TEL~ Task Completed : 0400 `` ATW0 `` Task Description : Travail effectué - Task Completed : 1000 `` ATQ0 `` Task Description : remis en conformité
A49: 216336723 | B49: REJ | C49: Rejection | D49: SERIE | E49: A330 | F49: PTVU | G49: 2146 | H49: 2026-02-04 | I49: 1 | J49: E0062E2D4AC0A | K49: BORNE NE VERROUILLE PAS | L49: E0062E2D4AC0A | N49: F9251690100000 | O49: ELEC ASSY 312VU | P49: =IFERROR(IF(INDEX('Parts to price'!$M$2:$M$92,MATCH(J49,'Parts to price'!$A$2:$A$92,0))="","",INDEX('Parts to price'!$M$2:$M$92,MATCH(J49,'Parts to price'!$A$2:$A$92,0))),"") | Q49: =IF(P49="","",P49*I49) | R49: BORNE NE VERROUILLE PAS | NonConformity 0001 : Type of nonconformity : Electrical Assembly Installation * Sur la ligne A330 , nous constatons qu'une borne de connexion ne verrouille pas sur le switch over E0062E2D4AC0A. Demandons nouveau switch pour remise en conformité du produit. Text Description : - TEL~ #TEL~ Task Completed : 0150 `` DO00 `` Task Description : so3 1027711983 - TEL~ Task Completed : 0400 `` ATW0 `` Task Description : Travail effectué - Task Completed : 1000 `` ATQ0 `` Task Description : remis en conformité
A50: 216669205 | B50: REJ | C50: Rejection | D50: SERIE | E50: A330 | F50: PTVU | G50: 2146 | H50: 2026-03-10 | I50: 1 | J50: E0062E2D4AC0A | K50: SWITCH OVER CASSE | L50: E0062E2D4AC0A | N50: F9251690100000 | O50: ELEC ASSY 312VU | P50: =IFERROR(IF(INDEX('Parts to price'!$M$2:$M$92,MATCH(J50,'Parts to price'!$A$2:$A$92,0))="","",INDEX('Parts to price'!$M$2:$M$92,MATCH(J50,'Parts to price'!$A$2:$A$92,0))),"") | Q50: =IF(P50="","",P50*I50) | R50: SWITCH OVER CASSE | NonConformity 0001 : Type of nonconformity : Electrical Assembly Installation * Sur la ligne A330 , nous constatons que le switch over est endommagé E0062E2D4AC0A. * Task Completed : 0100 `` DEC0 `` Decision Taken : REJECT Part Not Fitted Justification : SWITCH OVER HS * MRP CONTROLER : MATERIAL GROUP : ++++++++++++++++++++++++++++++++++++++++ * Text Description : - TEL~ #TEL~ Task Completed : 0150 `` DO00 `` Task Description : Traité sur SO1 1027711983 - TEL~ Task Completed : 0400 `` ATW0 `` Task Description : Travail effectué - Task Completed : 1000 `` ATQ0 `` Task De
A51: 216627760 | B51: REJ | C51: Rejection | D51: SERIE | E51: A330 | F51: 740VU | G51: 2156 | H51: 2026-03-05 | I51: 1 | J51: E017B01E00 | K51: MICROSWITCH ENDOMMAGE | L51: E017B01E00 | M51: 9PH | N51: F92511185000S22 | O51: INTEGRATION 740VU | P51: =IFERROR(IF(INDEX('Parts to price'!$M$2:$M$92,MATCH(J51,'Parts to price'!$A$2:$A$92,0))="","",INDEX('Parts to price'!$M$2:$M$92,MATCH(J51,'Parts to price'!$A$2:$A$92,0))),"") | Q51: =IF(P51="","",P51*I51) | R51: MICROSWITCH ENDOMMAGE | NonConformity 0001 : Type of nonconformity : Electrical Assembly Installation * Sur la ligne A330 , nous constatons que le micoswitch E017B01E00 a été endommagé. FIN:9PH Nous demandons un nouveau micoswitch pour la remise en conformité. Text Description : - TEL~ #TEL~ Task Completed : 0150 `` DO00 `` Task Description : traitée sur SO1 - TEL~ Task Completed : 0400 `` ATW0 `` Task Description : Travail effectué - Task Completed : 1000 `` ATQ0 `` Task Description : Check done
A52: 217203646 | B52: REJ_RW | C52: Rejection with a rework order | D52: SERIE | E52: A330 | F52: 740VU | G52: 2155 | H52: 2026-05-05 | I52: 1 | J52: E0217XUU001A | K52: VIS TORDUE SUR RELAIS | L52: E0217XUU001A | N52: F92511185000S23 | O52: FINITION 740VU | P52: =IFERROR(IF(INDEX('Parts to price'!$M$2:$M$92,MATCH(J52,'Parts to price'!$A$2:$A$92,0))="","",INDEX('Parts to price'!$M$2:$M$92,MATCH(J52,'Parts to price'!$A$2:$A$92,0))),"") | Q52: =IF(P52="","",P52*I52) | R52: VIS TORDUE SUR RELAIS | NonConformity 0001 : Type of nonconformity : Electrical Assembly Installation * Sur la ligne A330 , MSN 2155 , 740VU , nous constatons que la vis sur le relais E0217XUU001A est tordue. Nous demandons le remplacement de l'équipement. Text Description : - TEL~ #TEL~ Task Completed : 0200 `` DO00 `` Task Description : NC prise en compte par OF 1029496358. - Task Completed : 1000 `` ATQ0 `` Task Description : CHECK OK
A53: 217205879 | B53: REJ_RW | C53: Rejection with a rework order | D53: SERIE | E53: A330 | F53: 740VU | G53: 2155 | H53: 2026-05-05 | I53: 1 | J53: E0219AS | K53: Socle relais 4XE taraudage endommagé | L53: E0219AS | M53: 4XE | N53: F92511185000S22 | O53: INTEGRATION 740VU | P53: =IFERROR(IF(INDEX('Parts to price'!$M$2:$M$92,MATCH(J53,'Parts to price'!$A$2:$A$92,0))="","",INDEX('Parts to price'!$M$2:$M$92,MATCH(J53,'Parts to price'!$A$2:$A$92,0))),"") | Q53: =IF(P53="","",P53*I53) | R53: Socle relais 4XE taraudage endommagé | NonConformity 0001 : Type of nonconformity : Electrical Assembly Installation * Lors de la finition du meuble 740VU MSN 2155 au moment de monter les relais , il est constaté qu'un taraudage des fixation du socle du relais 4XE est endommagé. * Référence du socle : E0219AS * Merci de changer celui-ci. Text Description : - TEL~ #TEL~ Task Completed : 0200 `` DO00 `` Task Description : NC prise en compte par OF 1029482473. - Task Completed : 1000 `` ATQ0 `` Task Description : CHECK OK
A54: 217446552 | B54: REJ | C54: Rejection | D54: SERIE | E54: A330 | F54: PTVU | G54: 2161 | H54: 2026-06-03 | I54: 1 | J54: E0239D5A | K54: BORNE 1A NE VERROUILLE PAS | L54: E0239D5A | N54: F9251649700000 | O54: ELEC ASSY 245VU | P54: =IFERROR(IF(INDEX('Parts to price'!$M$2:$M$92,MATCH(J54,'Parts to price'!$A$2:$A$92,0))="","",INDEX('Parts to price'!$M$2:$M$92,MATCH(J54,'Parts to price'!$A$2:$A$92,0))),"") | Q54: =IF(P54="","",P54*I54) | R54: BORNE 1A NE VERROUILLE PAS | NonConformity 0001 : Type of nonconformity : Electrical Assembly Installation * Sur la ligne A330 , nous constatons que la borne 1A ne verrouille pas sur le switch-push button E0239D5A. Text Description : - Task Completed : 0150 `` DO00 `` Task Description : nc pris en compte par SO3 1029399693 - Task Completed : 1000 `` ATQ0 `` Task Description : VU REMIS EN CONFORMITE
A55: 218333064 | B55: REJ_RW | C55: Rejection with a rework order | D55: SERIE | E55: A330 | F55: PTVU | G55: 2170 | H55: 2026-09-21 | I55: 1 | J55: E0239D5A | K55: BORNE HS SUR SWITCH-PUSH BUTTON | L55: E0239D5A | M55: 15XE | N55: F9251696100000 | O55: ELEC ASSY 211VU | P55: =IFERROR(IF(INDEX('Parts to price'!$M$2:$M$92,MATCH(J55,'Parts to price'!$A$2:$A$92,0))="","",INDEX('Parts to price'!$M$2:$M$92,MATCH(J55,'Parts to price'!$A$2:$A$92,0))),"") | Q55: =IF(P55="","",P55*I55) | R55: BORNE HS SUR SWITCH-PUSH BUTTON | NonConformity 0001 : Type of nonconformity : Electrical Assembly Installation * Sur la ligne A330 , MSN 2170 , 211 VU , nous constatons que la borne 1A sur le SWITCH-PUSH BUTTON E0239D5A , FIN 15XE , ne vérouille pas. * Nous demandons le remplacement de l'équipement. * Task Completed : 0100 `` DEC0 `` Decision Taken : REJECT Part Not Fitted Justification : Equipement HS * MRP CONTROLER : MATERIAL GROUP : ++++++++++++++++++++++++++++++++++++++++ * Text Description : - TEL~ #TEL~ Task Completed : 0200 `` DO00 `` Task Description : NC traitée suivant OF 1031120
A56: 217368374 | B56: REJ | C56: Rejection | D56: SERIE | E56: A330 | F56: 740VU | G56: 2159 | H56: 2026-05-26 | I56: 1 | J56: E0245 | K56: Filetage vis relais incorrect | L56: E0245 | N56: F92511185000S23 | O56: FINITION 740VU | P56: =IFERROR(IF(INDEX('Parts to price'!$M$2:$M$92,MATCH(J56,'Parts to price'!$A$2:$A$92,0))="","",INDEX('Parts to price'!$M$2:$M$92,MATCH(J56,'Parts to price'!$A$2:$A$92,0))),"") | Q56: =IF(P56="","",P56*I56) | R56: Filetage vis relais incorrect | NonConformity 0001 : Type of nonconformity : Electrical Assembly Installation * Sur la ligne A330 , MSN 2159 , 740VU , nous constatons que le filetage sur le relais E0245-28A0 est incorrect. La vis se met en travers lors du serrage. Nous demandons le remplacement de l'équipement. * Text Description : TEL~ #TEL~ Pas d'action côté ST , OF CERT - Task Completed : 1000 `` ATQ0 `` Task Description : CHECK OK
A57: 216945078 | B57: REJ_RW | C57: Rejection with a rework order | D57: SERIE | E57: A330 | F57: 740VU | G57: 2154 | H57: 2026-04-07 | I57: 1 | J57: E0311A0S | K57: Gromet endommagé sur Socket | L57: E0311A0S | N57: F92511185000S22 | O57: INTEGRATION 740VU | P57: =IFERROR(IF(INDEX('Parts to price'!$M$2:$M$92,MATCH(J57,'Parts to price'!$A$2:$A$92,0))="","",INDEX('Parts to price'!$M$2:$M$92,MATCH(J57,'Parts to price'!$A$2:$A$92,0))),"") | Q57: =IF(P57="","",P57*I57) | R57: Gromet endommagé sur Socket | NonConformity 0001 : Type of nonconformity : Electrical Assembly Installation * Sur la ligne A330 , nous constatons que le gromet est endommagé sur le Socket E0311A0S. Nous demandons la remise en conformité du produit. Text Description : - TEL~ #TEL~ Task Completed : 0150 `` DO00 `` Task Description : > X TEL~ #TEL~ > X* nc traitée sur S03 1029127214 * - TEL~ #TEL~ Task Completed : 0200 `` DO00 `` Task Description : NC prise en compte par OF 1029127214. - Task Completed : 1000 `` ATQ0 `` Task Description : remis en conformité
A58: 218166898 | B58: REJ_RW | C58: Rejection with a rework order | D58: SERIE | E58: A330 | F58: PTVU | G58: 2168 | H58: 2026-09-03 | I58: 1 | J58: E0330-01 | K58: EQUIPEMENT E0330-01 ENDOMMAGE | L58: E0330-01 | N58: F9251036300000 | O58: ELEC ASSY | P58: =IFERROR(IF(INDEX('Parts to price'!$M$2:$M$92,MATCH(J58,'Parts to price'!$A$2:$A$92,0))="","",INDEX('Parts to price'!$M$2:$M$92,MATCH(J58,'Parts to price'!$A$2:$A$92,0))),"") | Q58: =IF(P58="","",P58*I58) | R58: EQUIPEMENT E0330-01 ENDOMMAGE | NonConformity 0001 : Type of nonconformity : Electrical Assembly Installation * Sur la ligne A330 , 912 VU , MSN 2168 , nous constatons que l'équipement E0330-01 JACK TELEPHONE présente un impact sur le haut de la prise. * Nous demandons le remplacement de l'équipement. * Text Description : - TEL~ #TEL~ Task Completed : 0200 `` DO00 `` Task Description : NC prise en compte par OF 1030877637. - TEL~ Task Completed : 0400 `` ATW0 `` Task Description : Travail effectué - Task Completed : 1000 `` ATQ0 `` Task Description : REMIS EN CONFORMITE
A59: 217890692 | B59: REJ_RW | C59: Rejection with a rework order | D59: SERIE | E59: A330 | F59: PTVU | G59: 2164 | H59: 2026-07-17 | I59: 1 | J59: E0419A6 | K59: RETOUCHE CONTROLE FINAL | L59: E0419A6 | M59: 9QV-A | N59: F9251678500000 | O59: ELEC ASSY 211VU | P59: =IFERROR(IF(INDEX('Parts to price'!$M$2:$M$92,MATCH(J59,'Parts to price'!$A$2:$A$92,0))="","",INDEX('Parts to price'!$M$2:$M$92,MATCH(J59,'Parts to price'!$A$2:$A$92,0))),"") | Q59: =IF(P59="","",P59*I59) | R59: RETOUCHE CONTROLE FINAL | NonConformity 0001 : Type of nonconformity : Electrical Assembly Installation * Sur la ligne A330 , 211 VU , MSN 2164 , nous constatons lors du contrôle final que le #PRS~ #PRS~ réf : E0419A6 FIN : 9QV-A , est endommagé. * Nous demandons le remplacement de l'équipement. Text Description : - TEL~ #TEL~ Task Completed : 0200 `` DO00 `` Task Description : NC prise en compte par OF 1030437961 - Task Completed : 1000 `` ATQ0 `` Task Description : VU REMIS EN CONFORMITE
A60: 217026822 | B60: REJ | C60: Rejection | D60: SERIE | E60: A330 | F60: PTVU | G60: 2155 | H60: 2026-04-15 | I60: 1 | J60: E0682-01 | K60: Connecteur E0682-01 HS | L60: E0682-01 | N60: F9251686600000 | O60: ELEC ASSY 272VU | P60: =IFERROR(IF(INDEX('Parts to price'!$M$2:$M$92,MATCH(J60,'Parts to price'!$A$2:$A$92,0))="","",INDEX('Parts to price'!$M$2:$M$92,MATCH(J60,'Parts to price'!$A$2:$A$92,0))),"") | Q60: =IF(P60="","",P60*I60) | R60: Connecteur E0682-01 HS | NonConformity 0001 : Type of nonconformity : Structural and Mechanical Assembly * Sur le MSN 2155 , 272VU , le connecteur E0682-01 est défectueux. La bague de montage est HS. * Demandons nouveau connecteur E0682-01 en remplacement. Task Completed : 0100 `` DEC0 `` Decision Taken : REJECT Part Not Fitted Justification : remplacement de l'élément * MRP CONTROLER : MATERIAL GROUP : ++++++++++++++++++++++++++++++++++++++++ * Text Description : - TEL~ #TEL~ Task Completed : 0150 `` DO00 `` Task Description : NC traitée sur SO11029070166 - Task Completed : 1000 `` ATQ0 ``
A61: 218227645 | B61: REJ_RW | C61: Rejection with a rework order | D61: SERIE | E61: A330 | F61: PTVU | G61: 2172 | H61: 2026-09-09 | I61: 1 | J61: E0682-01 | K61: Borne HS sur connecteur E0682-01 | L61: E0682-01 | M61: 112LF | N61: F9251648700000 | O61: ELEC ASSY 112VU | P61: =IFERROR(IF(INDEX('Parts to price'!$M$2:$M$92,MATCH(J61,'Parts to price'!$A$2:$A$92,0))="","",INDEX('Parts to price'!$M$2:$M$92,MATCH(J61,'Parts to price'!$A$2:$A$92,0))),"") | Q61: =IF(P61="","",P61*I61) | R61: Borne HS sur connecteur E0682-01 | NonConformity 0001 : Type of nonconformity : Electrical Assembly Installation * Sur la ligne A330 , MSN 2172 , 112 VU , nous constatons que la borne 1 sur connecteur E0682-01 ( FIN 112LF ) ne vérouille pas. * Nous demandons le remplacement de l'équipement. Task Completed : 0100 `` DEC0 `` Decision Taken : REJECT Part Not Fitted Justification : Connecteur HS * MRP CONTROLER : MATERIAL GROUP : ++++++++++++++++++++++++++++++++++++++++ * Text Description : - Task Completed : 0150 `` DO00 `` Task Description : NC PRIS EN COMPTE PAR SO3 1030184952 - TEL~ #TEL~ T
A62: 218376309 | B62: REJ_RW | C62: Rejection with a rework order | D62: SERIE | E62: A330 | F62: PTVU | G62: 2170 | H62: 2026-09-24 | I62: 1 | J62: E0682-01 | K62: Borne 1 HS sur équipement E0682-01 | L62: E0682-01 | M62: 417LF | N62: F9251671100000 | O62: ELEC ASSY 417VU | P62: =IFERROR(IF(INDEX('Parts to price'!$M$2:$M$92,MATCH(J62,'Parts to price'!$A$2:$A$92,0))="","",INDEX('Parts to price'!$M$2:$M$92,MATCH(J62,'Parts to price'!$A$2:$A$92,0))),"") | Q62: =IF(P62="","",P62*I62) | R62: Borne 1 HS sur équipement E0682-01 | NonConformity 0001 : Type of nonconformity : Electrical Assembly Installation * Sur la ligne A330 , MSN 2170 , 417 VU , nous constatons que la borne 1 sur équipement E0682-01 ( FIN 417LF ) ne vérouille pas. * Nous demandons le remplacement de l'équipement. Task Completed : 0100 `` DEC0 `` Decision Taken : REJECT Part Not Fitted Justification : Equipement HS * MRP CONTROLER : MATERIAL GROUP : ++++++++++++++++++++++++++++++++++++++++ * Text Description : - TEL~ #TEL~ Task Completed : 0200 `` DO00 `` Task Description : NC traîté par le ST via OF 1031182387
A63: 216459539 | B63: REJ | C63: Rejection | D63: SERIE | E63: A330 | F63: PTVU | G63: 2149 | H63: 2026-02-17 | I63: 1 | J63: EN3646A01419AW | K63: Borne H ne verrouille pas | L63: EN3646A01419AW | N63: F9251630100000 | O63: ELEC ASSY 930VU | P63: =IFERROR(IF(INDEX('Parts to price'!$M$2:$M$92,MATCH(J63,'Parts to price'!$A$2:$A$92,0))="","",INDEX('Parts to price'!$M$2:$M$92,MATCH(J63,'Parts to price'!$A$2:$A$92,0))),"") | Q63: =IF(P63="","",P63*I63) | R63: Borne H ne verrouille pas | NonConformity 0001 : Type of nonconformity : Electrical Assembly Installation * Sur la ligne A330 , nous constatons que la borne H ne verrouille pas lors de l'enfichage du contact. .Connecteur= > EN3646A01419AW. * Text Description : - TEL~ #TEL~ Task Completed : 0150 `` DO00 `` Task Description : traité sur so1 1028218100 - TEL~ Task Completed : 0400 `` ATW0 `` Task Description : Travail effectué - Task Completed : 1000 `` ATQ0 `` Task Description : VU remis en conformité .
A64: 217685208 | B64: REJ | C64: Rejection | D64: SERIE | E64: A330 | F64: PTVU | G64: 2164 | H64: 2026-06-26 | I64: 1 | J64: EN3646A02255AN | K64: Borne K HS SUR CONNECTEUR VC | L64: EN3646A02255AN | N64: F9251670300000 | O64: ELEC ASSY 312VU | P64: =IFERROR(IF(INDEX('Parts to price'!$M$2:$M$92,MATCH(J64,'Parts to price'!$A$2:$A$92,0))="","",INDEX('Parts to price'!$M$2:$M$92,MATCH(J64,'Parts to price'!$A$2:$A$92,0))),"") | Q64: =IF(P64="","",P64*I64) | R64: Borne K HS SUR CONNECTEUR VC | NonConformity 0001 : Type of nonconformity : Electrical Assembly Installation * Sur la ligne A330 , nous constatons que la boene K ne verrouille pas sur le connecteur EN3646A02255AN. Nous demandons un nouveau connecteur. NonConformity 0001 : Type of nonconformity : Electrical Assembly Installation * Sur la ligne A330 , nous constatons que la boene K ne verrouille pas sur le connecteur EN3646A02255AN. Nous demandons un nouveau connecteur. Text Description : - Task Completed : 0400 `` ATW0 `` Task Description : remis en conformité - Task Completed : 1000 `` ATQ
A65: 216915228 | B65: REJ_RW | C65: Rejection with a rework order | D65: SERIE | E65: A330 | F65: PTVU | G65: 2156 | H65: 2026-04-02 | I65: 1 | J65: EN3646A02461AN | K65: BORNE NE VERROUILLE PAS | L65: EN3646A02461AN | N65: F9251693900000 | O65: ELEC ASSY 272VU | P65: =IFERROR(IF(INDEX('Parts to price'!$M$2:$M$92,MATCH(J65,'Parts to price'!$A$2:$A$92,0))="","",INDEX('Parts to price'!$M$2:$M$92,MATCH(J65,'Parts to price'!$A$2:$A$92,0))),"") | Q65: =IF(P65="","",P65*I65) | R65: BORNE NE VERROUILLE PAS | NonConformity 0001 : Type of nonconformity : Electrical Assembly Installation * Sur la ligne A330 , nous constatons que la borne NN ne verrouille pas sur le connecteur EN3646A02461AN. Nous demandons un nouveau connecteur. * Text Description : - TEL~ #TEL~ Task Completed : 0150 `` DO00 `` Task Description : nc traitée sur SO3 1029092321 - TEL~ #TEL~ Task Completed : 0200 `` DO00 `` Task Description : La NC est traité côté S/T sous la référence : 1029092321
A66: 216931836 | B66: REJ | C66: Rejection | D66: SERIE | E66: A330 | F66: PTVU | G66: 2151 | H66: 2026-04-03 | I66: 1 | J66: EN3646A02461AN | K66: CONNECTEUR borne ne verrouille pas | L66: EN3646A02461AN | N66: F9251696400000 | O66: ELEC ASSY 272VU | P66: =IFERROR(IF(INDEX('Parts to price'!$M$2:$M$92,MATCH(J66,'Parts to price'!$A$2:$A$92,0))="","",INDEX('Parts to price'!$M$2:$M$92,MATCH(J66,'Parts to price'!$A$2:$A$92,0))),"") | Q66: =IF(P66="","",P66*I66) | R66: CONNECTEUR borne ne verrouille pas | NonConformity 0001 : Type of nonconformity : Electrical Assembly Installation * Sur la ligne A330 , 272VU MSN 2151 , nous constatons que la borne NN ne verrouille pas sur le connecteur EN3646A02461AN. * Nous demandons le remplacement du connecteur. Text Description : - TEL~ #TEL~ Task Completed : 0150 `` DO00 `` Task Description : nc traitée sous SO1 1028436454
A67: 216943435 | B67: REJ | C67: Rejection | D67: SERIE | E67: A330 | F67: PTVU | G67: 2151 | H67: 2026-04-07 | I67: 1 | J67: EN3646A02461AN | K67: CONNECTEUR borne ne verrouille pas | L67: EN3646A02461AN | N67: F9251696400000 | O67: ELEC ASSY 272VU | P67: =IFERROR(IF(INDEX('Parts to price'!$M$2:$M$92,MATCH(J67,'Parts to price'!$A$2:$A$92,0))="","",INDEX('Parts to price'!$M$2:$M$92,MATCH(J67,'Parts to price'!$A$2:$A$92,0))),"") | Q67: =IF(P67="","",P67*I67) | R67: CONNECTEUR borne ne verrouille pas | NonConformity 0001 : Type of nonconformity : Electrical Assembly Installation * Sur la ligne A330 , 272VU MSN 2151 , nous constatons que la borne NN ne se verrouille pas sur le connecteur EN3646A02461AN. * Nous demandons le remplacement du connecteur. Text Description : - TEL~ #TEL~ Task Completed : 0150 `` DO00 `` Task Description : NC traitée sur SO1 - Task Completed : 1000 `` ATQ0 `` Task Description : TRAVAIL FAIT
A68: 217584208 | B68: REJ | C68: Rejection | D68: SERIE | E68: A330 | F68: PTVU | G68: 2163 | H68: 2026-06-17 | I68: 1 | J68: EN3646A02461AN | K68: Plume cassé dans borne P | L68: EN3646A02461AN | N68: F9251693900000 | O68: ELEC ASSY 272VU | P68: =IFERROR(IF(INDEX('Parts to price'!$M$2:$M$92,MATCH(J68,'Parts to price'!$A$2:$A$92,0))="","",INDEX('Parts to price'!$M$2:$M$92,MATCH(J68,'Parts to price'!$A$2:$A$92,0))),"") | Q68: =IF(P68="","",P68*I68) | R68: Plume cassé dans borne P | NonConformity 0001 : Type of nonconformity : Electrical Assembly Installation * Sur la ligne A330 , nous constatons que la borne P est endommagée ( plume cassée à l'intérieur ) . Réf : EN3646A02461AN. Text Description : - Task Completed : 1000 `` ATQ0 `` Task Description : CHECK OK
A69: 218350053 | B69: REJ | C69: Rejection | D69: SERIE | E69: A330 | F69: PTVU | G69: 2170 | H69: 2026-09-22 | I69: 1 | J69: ERGOT DOUILLE D'AMPOULE HS | K69: Ergot douille d'ampoule HS | N69: F9251035100000 | O69: 452VU ELEC ASSY | P69: =IFERROR(IF(INDEX('Parts to price'!$M$2:$M$92,MATCH(J69,'Parts to price'!$A$2:$A$92,0))="","",INDEX('Parts to price'!$M$2:$M$92,MATCH(J69,'Parts to price'!$A$2:$A$92,0))),"") | Q69: =IF(P69="","",P69*I69) | R69: Ergot douille d'ampoule HS | NonConformity 0001 : Type of nonconformity : Electrical Assembly Installation * Lors de l'installation des douille d'ampoule sur le 452VB MSN 2170 , l'opérateur a endommagé l'ergot de positionnement. * Merci de recommander une nouvelle pièce. Text Description : - TEL~ #TEL~ Task Completed : 0200 `` DO00 `` Task Description : Pas d'action côté ST .
A70: 218145781 | B70: REJ | C70: Rejection | D70: SERIE | E70: A330 | F70: PTVU | G70: 2166 | H70: 2026-09-01 | I70: 1 | J70: ETEC 241VU NON CONFORME | K70: ETEC 241VU non conforme | N70: F9251671500000 | O70: ELEC ASSY 241VU | P70: =IFERROR(IF(INDEX('Parts to price'!$M$2:$M$92,MATCH(J70,'Parts to price'!$A$2:$A$92,0))="","",INDEX('Parts to price'!$M$2:$M$92,MATCH(J70,'Parts to price'!$A$2:$A$92,0))),"") | Q70: =IF(P70="","",P70*I70) | R70: ETEC 241VU non conforme | NonConformity 0001 : Type of nonconformity : Absence of Colour / Paint missing * Sur la ligne A330 petits VU , au contrôle final , il a été constaté que le nom du VU sur l'ETEC était partiellement effacé. * Nous demandons le réapprovisionnement d'un nouvel ETEC. * * Task Completed : 0100 `` DEC0 `` Decision Taken : REJECT Part Not Fitted Justification : Nous demandons le remplacement de l'ETEC ++++++++++++++++++++++++++++++++++++++++ Material characteristics * WBS : MSF-002166/FB148 Material : 000000006374856800 * MRP CONTROLER : SMITH Emmanuel STORAGE LOCATION : TS2
A71: 216207337 | B71: REJ_RW | C71: Rejection with a rework order | D71: SERIE | E71: A330 | F71: 740VU | G71: 2150 | H71: 2026-01-22 | I71: 1 | J71: ETIQUETTE FONCTION NON CONFORME | K71: ETIQUETTE FONCTION NON CONFORME | N71: F1131365000000 | O71: FUNCTIONAL LABEL | P71: =IFERROR(IF(INDEX('Parts to price'!$M$2:$M$92,MATCH(J71,'Parts to price'!$A$2:$A$92,0))="","",INDEX('Parts to price'!$M$2:$M$92,MATCH(J71,'Parts to price'!$A$2:$A$92,0))),"") | Q71: =IF(P71="","",P71*I71) | R71: ETIQUETTE FONCTION NON CONFORME | NonConformity 0001 : Type of nonconformity : Electrical Assembly Installation * Sur la ligne A330 , MSN 2150 , 740VU , nous constatons lors de l'inspection que l'étiquette de fonction ligne D est non conforme ( voir standard doc ) . Nous demandons le remplacement du lot d'étiquettes de fonction. Text Description : - TEL~ #TEL~ Task Completed : 0150 `` DO00 `` Task Description : > X TEL~ #TEL~ > X* so3 1028100658 * - TEL~ #TEL~ Task Completed : 0200 `` DO00 `` Task Description : NC prise en compte par OF 102810065. - TEL~ Task Completed : 0400 `` ATW0 `` Ta
A72: 217475055 | B72: REJ | C72: Rejection | D72: SERIE | E72: A330 | F72: 740VU | G72: 2163 | H72: 2026-06-05 | I72: 1 | J72: F1131202300000 | K72: LOT ETIQUETTE 740VU INCOMPLET | L72: F1131202300000 | N72: F92513993000S02 | O72: EQUIPEMENT 740VU | P72: =IFERROR(IF(INDEX('Parts to price'!$M$2:$M$92,MATCH(J72,'Parts to price'!$A$2:$A$92,0))="","",INDEX('Parts to price'!$M$2:$M$92,MATCH(J72,'Parts to price'!$A$2:$A$92,0))),"") | Q72: =IF(P72="","",P72*I72) | R72: LOT ETIQUETTE 740VU INCOMPLET | NonConformity 0001 : Type of nonconformity : Structural and Mechanical Assembly * Sur la ligne A330 , 740 VU , MSN 2163 , nous constatons que le lot d'étiquettes F1131202300000 est incomplet. * Nous demandons le remplacement du lot. Text Description : - Task Completed : 0150 `` DO00 `` Task Description : NC PRIS EN COMPTE PAR SO3 1029361481 - Task Completed : 1000 `` ATQ0 `` Task Description : CHECK OK
A73: 216350524 | B73: REJ | C73: Rejection | D73: SERIE | E73: A330 | F73: 740VU | G73: 2150 | H73: 2026-02-05 | I73: 1 | J73: F1131365000000 | K73: Lot etiquettes foctions non conforme | L73: F1131365000000 | P73: =IFERROR(IF(INDEX('Parts to price'!$M$2:$M$92,MATCH(J73,'Parts to price'!$A$2:$A$92,0))="","",INDEX('Parts to price'!$M$2:$M$92,MATCH(J73,'Parts to price'!$A$2:$A$92,0))),"") | Q73: =IF(P73="","",P73*I73) | R73: Lot etiquettes foctions non conforme | NonConformity 0001 : Type of nonconformity : Electrical Assembly Installation * Sur la ligne A330 , nous avons constaté que le LOTF1131365000000 ( Etiquettes de Fonctions ) est non conforme suite à une mise à jour non faite par le BE. Le plan a évolué à ce jour= > voir doc déclaratif. * Task Completed : 0100 `` DEC0 `` Decision Taken : REJECT Part Not Fitted Justification : lot etiquettes de fonctions non conforme * MRP CONTROLER : MATERIAL GROUP : ++++++++++++++++++++++++++++++++++++++++ * Text Description : - TEL~ #TEL~ Task Completed : 0200 `` DO00 `
A74: 218280141 | B74: REJ | C74: Rejection | D74: SERIE | E74: A330 | F74: PTVU | G74: 2169 | H74: 2026-09-15 | I74: 1 | J74: F9251017700000 | K74: STRUCTURE FACE AVANT RAYEE | L74: F9251017700000 | N74: F9251647400000 | O74: ELEC ASSY 314VU | P74: =IFERROR(IF(INDEX('Parts to price'!$M$2:$M$92,MATCH(J74,'Parts to price'!$A$2:$A$92,0))="","",INDEX('Parts to price'!$M$2:$M$92,MATCH(J74,'Parts to price'!$A$2:$A$92,0))),"") | Q74: =IF(P74="","",P74*I74) | R74: STRUCTURE FACE AVANT RAYEE | NonConformity 0001 : Type of nonconformity : Structural and Mechanical Assembly * Sur la ligne A330 , MSN 2169 , 314VU , nous constatons que la structure en face avant F9251017700000 est rayée. * Voir doc déclaratif. * Nous demandons le remplacement de la structure. * Task Completed : 0100 `` DEC0 `` Decision Taken : REJECT Part Not Fitted Justification : Structure rayée * MRP CONTROLER : STD #PRS~ #PRS~ #PRS~ #UID~ MATERIAL GROUP : ++++++++++++++++++++++++++++++++++++++++ * Text Description : - TEL~ #TEL~ Task Completed : 0200 `` DO00 `` Task Description : Pas d
A75: 218185629 | B75: REJ_RW | C75: Rejection with a rework order | D75: SERIE | E75: A330 | F75: PTVU | G75: 2166 | H75: 2026-09-04 | I75: 1 | J75: F9251031400000 | K75: DZUS SUR STRUCTURE 616VU ENDOMMAGE | L75: F9251031400000 | N75: F9251695100000 | O75: ELEC ASSY 616VU | P75: =IFERROR(IF(INDEX('Parts to price'!$M$2:$M$92,MATCH(J75,'Parts to price'!$A$2:$A$92,0))="","",INDEX('Parts to price'!$M$2:$M$92,MATCH(J75,'Parts to price'!$A$2:$A$92,0))),"") | Q75: =IF(P75="","",P75*I75) | R75: DZUS SUR STRUCTURE 616VU ENDOMMAGE | NonConformity 0001 : Type of nonconformity : Structural and Mechanical Assembly * Sur la ligne A330 , 616VU , MSN 2166 , nous constatons que le dzus côté droit en face avant est endommagé. * Nous demandons le remplacement de la structure F9251031400000. Text Description : - TEL~ #TEL~ Task Completed : 0200 `` DO00 `` Task Description : NC prise en compte par OF 1030897869. - Task Completed : 0400 `` ATW0 `` Task Description : travail effectué - Task Completed : 1000 `` ATQ0 `` Task Description : Vu remis en conformité
A76: 216156635 | B76: REJ_RW | C76: Rejection with a rework order | D76: SERIE | E76: A330 | F76: PTVU | G76: 2145 | H76: 2026-01-16 | I76: 1 | J76: F9251041800000 | K76: Rampe endommagée | L76: F9251041800000 | N76: F9251689600000 | O76: ELEC ASSY 215VU | P76: =IFERROR(IF(INDEX('Parts to price'!$M$2:$M$92,MATCH(J76,'Parts to price'!$A$2:$A$92,0))="","",INDEX('Parts to price'!$M$2:$M$92,MATCH(J76,'Parts to price'!$A$2:$A$92,0))),"") | Q76: =IF(P76="","",P76*I76) | R76: Rampe endommagée | NonConformity 0001 : Type of nonconformity : Electrical Assembly Installation * Sur la ligne A330 , MSN 2145 , 215 VU , nous constatons lors de l'installation que la rampe F9251041800000 est endommagée , la base de la rampe tourne dans le vide ce qui empêche l'installation de cette dernière. Nous demandons le remplacement de l'équipement. * Task Completed : 0100 `` DEC0 `` Decision Taken : REJECT Part Not Fitted Justification : Remplacement de l'équipement * MRP CONTROLER : MATERIAL GROUP : ++++++++++++++++++++++++++++++++++++++++ * Text Description : - TEL~ Task Completed
A77: 216163882 | B77: REJ_RW | C77: Rejection with a rework order | D77: SERIE | E77: A330 | F77: PTVU | G77: 2152 | H77: 2026-01-19 | I77: 1 | J77: F9251201000000 | K77: Filetage Rampe F9251201000000 endommagé | L77: F9251201000000 | N77: F9251501300000 | O77: 990VU ELEC ASSY | P77: =IFERROR(IF(INDEX('Parts to price'!$M$2:$M$92,MATCH(J77,'Parts to price'!$A$2:$A$92,0))="","",INDEX('Parts to price'!$M$2:$M$92,MATCH(J77,'Parts to price'!$A$2:$A$92,0))),"") | Q77: =IF(P77="","",P77*I77) | R77: Filetage Rampe F9251201000000 endommagé | NonConformity 0001 : Type of nonconformity : Structural and Mechanical Assembly * Sur la ligne A330 , MSN 2152 , 990VU , nous constatons lors de l'installation que le filetage de la rampe F9251201000000 est endommagé. Nous demandons le remplacement de la pièce. Text Description : - TEL~ #TEL~ Task Completed : 0150 `` DO00 `` Task Description : so3 1028050642 - TEL~ #TEL~ Task Completed : 0200 `` DO00 `` Task Description : NC prise en compte par OF 1028050642. - TEL~ Task Completed : 0400 `` ATW0 `` Task Description : Travail effectué
A78: 216198504 | B78: EXC | C78: Exchange | D78: SERIE | E78: A330 | F78: 743VU | G78: 2148 | H78: 2026-01-21 | I78: 1 | J78: F9251369800000 | K78: PLATINE EQUIPEE NON CONFORME | L78: F9251369800000 | N78: F92513839000S01 | O78: MECA PLATINE RELAIS 743VU | P78: =IFERROR(IF(INDEX('Parts to price'!$M$2:$M$92,MATCH(J78,'Parts to price'!$A$2:$A$92,0))="","",INDEX('Parts to price'!$M$2:$M$92,MATCH(J78,'Parts to price'!$A$2:$A$92,0))),"") | Q78: =IF(P78="","",P78*I78) | R78: PLATINE EQUIPEE NON CONFORME | NonConformity 0001 : Type of nonconformity : Electrical Assembly Installation * Sur la ligne A330 , nous constatons que la platine F9251369800000 est non conforme . Voir doc déclaratif Task Completed : 0100 `` DEC0 `` Request for Supplier Assessment Decision Taken : External Exchange Text Description : Task Completed : 0248 `` STE0 `` Request for Supplier Assessment Decision Taken : External Exchange Text Description : - Task Completed : 0348 `` STE0 `` Task Description : vu remis en conformité - Task Completed : 0650 `` ATQ0 `` Task Description : 743vu remis
A79: 216899465 | B79: EXC | C79: Exchange | D79: SERIE | E79: A330 | F79: 740VU | G79: 2155 | H79: 2026-04-01 | I79: 1 | J79: F9251527320000 | K79: TOLE DE FOND ENDOMMAGEE | L79: F9251527320000 | N79: FDOM0740VUINCOMING | O79: Gamme domestique 740VU INCOMING | P79: =IFERROR(IF(INDEX('Parts to price'!$M$2:$M$92,MATCH(J79,'Parts to price'!$A$2:$A$92,0))="","",INDEX('Parts to price'!$M$2:$M$92,MATCH(J79,'Parts to price'!$A$2:$A$92,0))),"") | Q79: =IF(P79="","",P79*I79) | R79: TOLE DE FOND ENDOMMAGEE | NonConformity 0001 : Type of nonconformity : Structural and Mechanical Assembly * Sur la ligne A330 , nous constatons que la tole de fond a été endommagée= > F9251527320000. Voir doc déclaratif. Nous demandons le replacement de cette piéce. * Task Completed : 0100 `` DEC0 `` Request for Supplier Assessment Decision Taken : External Exchange Text Description : Task Completed : 0001 `` ORI0 `` Task Description : Transfert de la NC 216653358 du MSN 2151 vers MSN 2155. Task Completed : 0100 `` DEC0 `` Request for Supplier Assessment Decision Taken : External Exchange T
A80: 216037622 | B80: EXC | C80: Exchange | D80: SERIE | E80: A330 | F80: 743VU | G80: 2152 | H80: 2026-01-05 | I80: 1 | J80: F9251529400000 | K80: FILETAGE ECROU SUPPORT PRISE H.S. | L80: F9251529400000 | N80: FDOM0743VUINCOMING | O80: Gamme domestique 743VU INCOMING | P80: =IFERROR(IF(INDEX('Parts to price'!$M$2:$M$92,MATCH(J80,'Parts to price'!$A$2:$A$92,0))="","",INDEX('Parts to price'!$M$2:$M$92,MATCH(J80,'Parts to price'!$A$2:$A$92,0))),"") | Q80: =IF(P80="","",P80*I80) | R80: FILETAGE ECROU SUPPORT PRISE H.S. | NonConformity 0001 : Type of nonconformity : Structural and Mechanical Assembly * Sur la ligne A330 , MSN 2152 , 743 VU , nous constatons lors de l'installation que le filetage écrou du support prise est endommagé. Réf : F9251529400000 Voir doc déclaratif. Task Completed : 0100 `` DEC0 `` Request for Supplier Assessment Decision Taken : External Exchange Text Description : ******************************************************************** Responsible of defect 1 updated by #UID~ Old value : Y4 147026 SOCIETE NOUVELLE CENTRAIR - SNCA New value : Y5 FTO2 EL
A81: 217162621 | B81: EXC | C81: Exchange | D81: SERIE | E81: A330 | F81: 743VU | G81: 2159 | H81: 2026-04-29 | I81: 1 | J81: F9251529400000 | K81: PAS DE VIS HS SUR SUPPORT PRISES | L81: F9251529400000 | N81: FDOM0743VUINCOMING | O81: Gamme domestique 743VU INCOMING | P81: =IFERROR(IF(INDEX('Parts to price'!$M$2:$M$92,MATCH(J81,'Parts to price'!$A$2:$A$92,0))="","",INDEX('Parts to price'!$M$2:$M$92,MATCH(J81,'Parts to price'!$A$2:$A$92,0))),"") | Q81: =IF(P81="","",P81*I81) | R81: PAS DE VIS HS SUR SUPPORT PRISES | NonConformity 0001 : Type of nonconformity : Structural and Mechanical Assembly * Sur la ligne A330 , nous constatons que le Pas de vis est endommagé sur le support prise F9251529400000. Voir doc déclaratif. * Task Completed : 0100 `` DEC0 `` Request for Supplier Assessment Decision Taken : External Exchange Text Description : - Task Completed : 0248 `` STE0 `` Task Description : Constaté monté sur le meuble. Mesures de métallisation ok .
A82: 217577268 | B82: EXC | C82: Exchange | D82: SERIE | E82: A330 | F82: 740VU | G82: 2165 | H82: 2026-06-16 | I82: 1 | J82: F9251533600000 | K82: Ecrou autofreine endommagé | L82: F9251533600000 MS21071-3 | N82: FDOM0740VUINCOMING | O82: Gamme domestique 740VU INCOMING | P82: =IFERROR(IF(INDEX('Parts to price'!$M$2:$M$92,MATCH(J82,'Parts to price'!$A$2:$A$92,0))="","",INDEX('Parts to price'!$M$2:$M$92,MATCH(J82,'Parts to price'!$A$2:$A$92,0))),"") | Q82: =IF(P82="","",P82*I82) | R82: Ecrou autofreine endommagé | NonConformity 0001 : Type of nonconformity : Structural and Mechanical Assembly * Sur la ligne A330 , nous constatons sur la porte 742VU F9251533600000 qu'un écrou autofreiné MS21071-3 a été endommagé. Nous demandons un parachévement pour la remise en conformité. Task Completed : 0100 `` DEC0 `` Request for Supplier Assessment Decision Taken : External Exchange Text Description :
A83: 217331925 | B83: REJ_RW | C83: Rejection with a rework order | D83: SERIE | E83: A330 | F83: PTVU | G83: 2140 | H83: 2026-05-20 | I83: 1 | J83: FIN 10DG2 | K83: Retouche Test 262VU MSN 02140 | M83: 10DG2 | N83: F9251693300000 | O83: ELEC ASSY 262VU | P83: =IFERROR(IF(INDEX('Parts to price'!$M$2:$M$92,MATCH(J83,'Parts to price'!$A$2:$A$92,0))="","",INDEX('Parts to price'!$M$2:$M$92,MATCH(J83,'Parts to price'!$A$2:$A$92,0))),"") | Q83: =IF(P83="","",P83*I83) | R83: Retouche Test 262VU MSN 02140 | NonConformity 0001 : Type of nonconformity : Connection * Def 1-Q11 : Suite à Inversion de branchement ( T04 ) et un mauvais sertissage ( Q07 ) sur un câble en 10DG2 , un contact est resté coincé dans le bouton poussoir. Merci remplacer ce bouton poussoir , refaire le contac , vérifier le sertissage de l'autre contact de l'équipement et remettre le VU en conformité. Text Description : - TEL~ #TEL~ Task Completed : 0200 `` DO00 `` Task Description : NC Prise en compte par OF 1029734923. - Task Completed : 0400 `` ATW0 `` Task Description : remis en conformité
A84: 216074010 | B84: REJ_RW | C84: Rejection with a rework order | D84: SERIE | E84: A330 | F84: PTVU | G84: 2148 | H84: 2026-01-08 | I84: 1 | J84: FIN 12CE1 | K84: Retouche Test 241VU MSN 02148 | M84: 12CE1 | N84: F9251671500000 | O84: ELEC ASSY 241VU | P84: =IFERROR(IF(INDEX('Parts to price'!$M$2:$M$92,MATCH(J84,'Parts to price'!$A$2:$A$92,0))="","",INDEX('Parts to price'!$M$2:$M$92,MATCH(J84,'Parts to price'!$A$2:$A$92,0))),"") | Q84: =IF(P84="","",P84*I84) | R84: Retouche Test 241VU MSN 02148 | NonConformity 0001 : Type of nonconformity : Electrical Assembly Installation * Def 1-Q11 : Colerette de de l'indicateur controle signal 12CE1 cassée. Merci de remplacer cet équipement. Text Description : - TEL~ #TEL~ Task Completed : 0150 `` DO00 `` Task Description : SO3 1028139503 - TEL~ #TEL~ Task Completed : 0200 `` DO00 `` Task Description : NC prise en compte par OF 1028139503. - Task Completed : 1000 `` ATQ0 `` Task Description : Contrôle ok
A85: 216052773 | B85: REJ_RW | C85: Rejection with a rework order | D85: SERIE | E85: A330 | F85: PTVU | G85: 2144 | H85: 2026-01-06 | I85: 1 | J85: FIN 14MQ | K85: Relais 14MQ endommagé | M85: 14MQ | N85: F9251623400000 | O85: ELEC ASSY 295VU | P85: =IFERROR(IF(INDEX('Parts to price'!$M$2:$M$92,MATCH(J85,'Parts to price'!$A$2:$A$92,0))="","",INDEX('Parts to price'!$M$2:$M$92,MATCH(J85,'Parts to price'!$A$2:$A$92,0))),"") | Q85: =IF(P85="","",P85*I85) | R85: Relais 14MQ endommagé | NonConformity 0001 : Type of nonconformity : Impact * Lors de l'inspection du 295VU , nous constons un impact sur le côté du relais 14MQ. * Code défaut : Q11-003 * Merci de remettre en état. NonConformity 0001 : Type of nonconformity : Impact * Lors de l'inspection du 295VU , nous constons un impact sur le côté du relais 14MQ. * Code défaut : Q11-003 * Merci de remettre en état. Task Completed : 0100 `` DEC0 `` Decision Taken : REJECT Part Fitted Justification : IMPACT SUR LE COTE * MRP CONTROLER : MATERIAL GROUP : ++++++++++++++++++++++++++++++++++++++++ * Text Descr
A86: 217600000 | B86: REJ | C86: Rejection | D86: SERIE | E86: A330 | F86: PTVU | G86: 2163 | H86: 2026-06-18 | I86: 1 | J86: FIN 153RH | K86: WARNING HORN DETROMPAGE HS | M86: 153RH | N86: F9251688700000 | O86: ELEC ASSY 265VU | P86: =IFERROR(IF(INDEX('Parts to price'!$M$2:$M$92,MATCH(J86,'Parts to price'!$A$2:$A$92,0))="","",INDEX('Parts to price'!$M$2:$M$92,MATCH(J86,'Parts to price'!$A$2:$A$92,0))),"") | Q86: =IF(P86="","",P86*I86) | R86: WARNING HORN DETROMPAGE HS | NonConformity 0001 : Type of nonconformity : Electrical Assembly Installation * Sur la ligne A330 , nous constatons que le détrompage du warning HORN FIN : 153RH est endommagé. * Task Completed : 0100 `` DEC0 `` Decision Taken : REJECT Part Not Fitted Justification : DETROMPAGE WARNING HORN ENDOMMAGE 153RH * MRP CONTROLER : IBEN HABEL Firas 33753595310 MATERIAL GROUP : ++++++++++++++++++++++++++++++++++++++++ * Text Description : - Task Completed : 1000 `` ATQ0 `` Task Description : CHECK OK
A87: 17232524 | B87: REJ | C87: Rejection | D87: SERIE | E87: A330 | F87: Other | G87: 2163 | H87: 2026-06-18 | I87: 1 | J87: FIN 153RH | K87: WARNING HORN DETROMPAGE HS | M87: 153RH | P87: =IFERROR(IF(INDEX('Parts to price'!$M$2:$M$92,MATCH(J87,'Parts to price'!$A$2:$A$92,0))="","",INDEX('Parts to price'!$M$2:$M$92,MATCH(J87,'Parts to price'!$A$2:$A$92,0))),"") | Q87: =IF(P87="","",P87*I87) | R87: WARNING HORN DETROMPAGE HS | NonConformity 0001 : Type of nonconformity : Electrical Assembly Installation * Sur la ligne A330 , nous constatons que le détrompage du warning HORN FIN : 153RH est endommagé. *
A88: 217037645 | B88: EXC | C88: Exchange | D88: SERIE | E88: A320 | F88: Other | G88: 13115 | H88: 2026-04-15 | I88: 1 | J88: FIN 15XE-A | K88: ESAO: GTI: 15XE-A INOP | M88: 15XE-A 15XE | P88: =IFERROR(IF(INDEX('Parts to price'!$M$2:$M$92,MATCH(J88,'Parts to price'!$A$2:$A$92,0))="","",INDEX('Parts to price'!$M$2:$M$92,MATCH(J88,'Parts to price'!$A$2:$A$92,0))),"") | Q88: =IF(P88="","",P88*I88) | R88: ESAO: GTI: 15XE-A INOP | NonConformity 0001 : Type of nonconformity : Broken component * While performing GTI : 8242612 we had a failure. * We troubleshot this failure to 15XE-A Contactor INOP. * Voltage and Ground are going to the connector but it is not closing the contacts between T1 , T2 , T3 and K1 , K2 , K3. * Please replace contactor 15XE-A. * Located in the Oxygen compartment. In the 106VU. - Task Completed : 0100 `` VAL0 `` Task Description : XP ME please order parts and raise W/O for rework to replace contactor 15XE-A , in 106VU. Task Completed : 0200 `` DEC0 `` Request for Supplie
A89: 217921767 | B89: REJ_RW | C89: Rejection with a rework order | D89: SERIE | E89: A330 | F89: 740VU | G89: 2165 | H89: 2026-07-22 | I89: 1 | J89: FIN 17CE | K89: Découpleur 17CE endommagé | M89: 17CE | N89: F92511185000S23 | O89: FINITION 740VU | P89: =IFERROR(IF(INDEX('Parts to price'!$M$2:$M$92,MATCH(J89,'Parts to price'!$A$2:$A$92,0))="","",INDEX('Parts to price'!$M$2:$M$92,MATCH(J89,'Parts to price'!$A$2:$A$92,0))),"") | Q89: =IF(P89="","",P89*I89) | R89: Découpleur 17CE endommagé | NonConformity 0001 : Type of nonconformity : Impact * Lors du PNE avant fermeture du meuble 740VU MSN 2165 , nous contatons que le découpleur 17CE est endommagé. * Voir standard doc. * Merci de changer le 17CE. Task Completed : 0100 `` DEC0 `` Decision Taken : REJECT Part Fitted Justification : Déformation sur le découpleur 17CE ++++++++++++++++++++++++++++++++++++++++ Material characteristics * WBS : MSF-002165/FB173 Material : 000000006325010000 SERIAL NUMBER FIN 68773 F 17CE * MRP CONTROLER : #PRS~ #PRS~ #PRS~ #UID~ STORAGE LOCATION : TS2F MATERIAL GROUP : BE1A
A90: 217504203 | B90: REJ_RW | C90: Rejection with a rework order | D90: SERIE | E90: A330 | F90: PTVU | G90: 2160 | H90: 2026-06-09 | I90: 1 | J90: FIN 180RH | K90: Retouches Test 211VU MSN 02160. | M90: 180RH | N90: F9251696100000 | O90: ELEC ASSY 211VU | P90: =IFERROR(IF(INDEX('Parts to price'!$M$2:$M$92,MATCH(J90,'Parts to price'!$A$2:$A$92,0))="","",INDEX('Parts to price'!$M$2:$M$92,MATCH(J90,'Parts to price'!$A$2:$A$92,0))),"") | Q90: =IF(P90="","",P90*I90) | R90: Retouches Test 211VU MSN 02160. | NonConformity 0001 : Type of nonconformity : Electrical Assembly Installation * Def 1-Q11 : Guard switch endommagé en 180RH. Merci de le remplacer. Text Description : - TEL~ #TEL~ Task Completed : 0200 `` DO00 `` Task Description : NC prise en compte par OF 1029940091. - TEL~ Task Completed : 0400 `` ATW0 `` Task Description : Travail effectué - Task Completed : 1000 `` ATQ0 `` Task Description : VU REMIS EN CONFORMITE
A91: 218098372 | B91: EXC | C91: Exchange | D91: SERIE | E91: A350 | F91: Other | G91: 868 | H91: 2026-08-26 | I91: 1 | J91: FIN 1WK11 | K91: Support Prisonnier détérioré | M91: 1WK11 | N91: V9281432500000 | O91: Montage clams et ramps planche de bord | P91: =IFERROR(IF(INDEX('Parts to price'!$M$2:$M$92,MATCH(J91,'Parts to price'!$A$2:$A$92,0))="","",INDEX('Parts to price'!$M$2:$M$92,MATCH(J91,'Parts to price'!$A$2:$A$92,0))),"") | Q91: =IF(P91="","",P91*I91) | R91: Support Prisonnier détérioré | TEL~ #TEL~ NonConformity 0001 : Type of nonconformity : Crack * Suite a l'utilisation d'une vis non conforme , le support prisonnier à l'arriere du pavé ARINC 1WK11 à été endommagé , veuillez s'il vous plait proceder a son remplacement. TEL~ #TEL~ Task Completed : 0100 `` DEC0 `` Request for Supplier Assessment Decision Taken : External Exchange Text Description :
A92: 217944847 | B92: REJ_RW | C92: Rejection with a rework order | D92: SERIE | E92: A330 | F92: PTVU | G92: 2165 | H92: 2026-07-24 | I92: 1 | J92: FIN 23FP | K92: RETOUCHE 23FP DEFECTUEUX | M92: 23FP | N92: F9251649300000 | O92: ELEC ASSY 221VU | P92: =IFERROR(IF(INDEX('Parts to price'!$M$2:$M$92,MATCH(J92,'Parts to price'!$A$2:$A$92,0))="","",INDEX('Parts to price'!$M$2:$M$92,MATCH(J92,'Parts to price'!$A$2:$A$92,0))),"") | Q92: =IF(P92="","",P92*I92) | R92: RETOUCHE 23FP DEFECTUEUX | NonConformity 0001 : Type of nonconformity : Insulation * DEF 1-Q11 : 23FP DEFAUT D'ISOLATION SUR LA BORNE 4. VEUILLEZ CHANGER L'EQUIPEMENT 23FP. Text Description : - TEL~ #TEL~ Task Completed : 0151 `` DO00 `` Task Description : NC prise en compte par OF 1030535457. - Task Completed : 0200 `` ATW0 `` Task Description : > X > X* > X > X* > X* remis en conformité > X* *
A93: 216341273 | B93: REJ_RW | C93: Rejection with a rework order | D93: REC | E93: A330 | F93: 245VU | G93: 2122 | H93: 2026-02-04 | I93: 1 | J93: FIN 245LF | K93: ETEC EQ 245LF à remplacer | M93: 245LF | P93: =IFERROR(IF(INDEX('Parts to price'!$M$2:$M$92,MATCH(J93,'Parts to price'!$A$2:$A$92,0))="","",INDEX('Parts to price'!$M$2:$M$92,MATCH(J93,'Parts to price'!$A$2:$A$92,0))),"") | Q93: =IF(P93="","",P93*I93) | R93: ETEC EQ 245LF à remplacer | NonConformity 0001 : Type of nonconformity : Incorrect connector * Suite à TLB ID194 veuillez remplacer l'etec du 245 VU Task Completed : 0100 `` DEC0 `` Decision Taken : REJECT Part Fitted Justification : Suite à TLB ID194 veuillez remplacer l'etec du 245 VU ++++++++++++++++++++++++++++++++++++++++ Material characteristics * WBS : MSF-002122/FB149 Material : 000000006374867600 * MRP CONTROLER : SMITH Emmanuel STORAGE LOCATION : TS2F MATERIAL GROUP : BLAF LIGHTED_PLATE ++++++++++++++++++++++++++++++++++++++++ * Text Description : - TEL~ #TEL~ Task Completed : 0200
A94: 217394034 | B94: REJ_RW | C94: Rejection with a rework order | D94: SERIE | E94: A330 | F94: 740VU | G94: 2159 | H94: 2026-05-28 | I94: 1 | J94: FIN 27XE | K94: Filetage endommagé sur relais 27XE | M94: 27XE | N94: F92511185000S23 | O94: FINITION 740VU | P94: =IFERROR(IF(INDEX('Parts to price'!$M$2:$M$92,MATCH(J94,'Parts to price'!$A$2:$A$92,0))="","",INDEX('Parts to price'!$M$2:$M$92,MATCH(J94,'Parts to price'!$A$2:$A$92,0))),"") | Q94: =IF(P94="","",P94*I94) | R94: Filetage endommagé sur relais 27XE | NonConformity 0001 : Type of nonconformity : Electrical Assembly Installation * Lors du changement de relais 27XE sur le 740VU MSN 2159 nous constatons que le même pas de vis que le précédent relais est endommagé lors du vissage. * Nous demandons le changement du relais 27XE ainsi que sa base relais 27XE A * Merci - Task Completed : 0001 `` ORI0 `` Task Description : Merci de changer le relais 27XE ainsi que sa base 27XE A Text Description : - Task Completed : 0150 `` DO00 `` Task Description : NC prise en comtpe par SO3 1029777599 * - TEL~ #TEL~ Task Co
A95: 216286560 | B95: REJ_RW | C95: Rejection with a rework order | D95: REC | E95: A330 | F95: 115VU | G95: 2122 | H95: 2026-01-29 | I95: 1 | J95: FIN 30CE | K95: TRIM POTENTIOMETER 30CE ON 115VU | M95: 30CE | P95: =IFERROR(IF(INDEX('Parts to price'!$M$2:$M$92,MATCH(J95,'Parts to price'!$A$2:$A$92,0))="","",INDEX('Parts to price'!$M$2:$M$92,MATCH(J95,'Parts to price'!$A$2:$A$92,0))),"") | Q95: =IF(P95="","",P95*I95) | R95: TRIM POTENTIOMETER 30CE ON 115VU | NonConformity 0001 : Type of nonconformity : Incorrect connector * Suite à TLB ID62 merci de remplacer le potentiometre 30CE sur le 115VU Task Completed : 0100 `` DEC0 `` Decision Taken : REJECT Part Fitted Justification : Suite à TLB ID62 merci de remplacer le potentiometre 30CE sur le 115VU * MRP CONTROLER : TESSIER Natacha +33785823004 MATERIAL GROUP : ++++++++++++++++++++++++++++++++++++++++ * Text Description : - Task Completed : 0200 `` DO00 `` Task Description : > X > X* S03 1028206999 * - Task Completed : 0700 `` ATW0 `` Task Description : travail
A96: 217394622 | B96: REJ_RW | C96: Rejection with a rework order | D96: REC | E96: A330 | F96: 311VU | G96: 2119 | H96: 2026-05-28 | I96: 1 | J96: FIN 311LF | K96: TLB ID435 | M96: 311LF | P96: =IFERROR(IF(INDEX('Parts to price'!$M$2:$M$92,MATCH(J96,'Parts to price'!$A$2:$A$92,0))="","",INDEX('Parts to price'!$M$2:$M$92,MATCH(J96,'Parts to price'!$A$2:$A$92,0))),"") | Q96: =IF(P96="","",P96*I96) | R96: TLB ID435 | NonConformity 0001 : Type of nonconformity : Electrical Assembly Installation * Suite au TLB ID435 , veuillez remplacer l'ETEC 311LF sur le 311VU. * Voir standard doc. * Text Description : - Task Completed : 0200 `` DO00 `` Task Description : S03 1029777637 cree - Task Completed : 0500 `` DO00 `` Task Description : Gamme + appro donnés en prod. - Task Completed : 0600 `` ATW0 `` Task Description : travail fait via WO 1029777637 - TEL~ #TEL~ Task Completed : 0700 `` DO00 `` Task Description : Travail contrôlé par ATIS ABZ - TEL~ #TEL~ Task Completed : 0800 `` DO00 `` Task Desc
A97: 218367147 | B97: REJ_RW | C97: Rejection with a rework order | D97: SERIE | E97: A330 | F97: PTVU | G97: 2172 | H97: 2026-09-23 | I97: 1 | J97: FIN 3DR1 | K97: Retouche Test 513VU MSN 02172 refus. | M97: 3DR1 | N97: F9251647500000 | O97: ELEC ASSY 513VU | P97: =IFERROR(IF(INDEX('Parts to price'!$M$2:$M$92,MATCH(J97,'Parts to price'!$A$2:$A$92,0))="","",INDEX('Parts to price'!$M$2:$M$92,MATCH(J97,'Parts to price'!$A$2:$A$92,0))),"") | Q97: =IF(P97="","",P97*I97) | R97: Retouche Test 513VU MSN 02172 refus. | NonConformity 0001 : Type of nonconformity : Electrical Assembly Installation * Def 1-Q11 : Switch overs subminiature 3DR1 endommagé bloqué. Merci de remplacer ce dernier. Text Description : - Task Completed : 0100 `` DEC0 `` Task Description : Passer avec #PRS~ - TEL~ #TEL~ Task Completed : 0150 `` DO00 `` Task Description : Merci de générer un SO3 de +1 - 1 afin qu'on puisse l'enrichir côté ST - TEL~ #TEL~ Task Completed : 0250 `` DO00 `` Task Description : NC traîté par le ST via OF 1031169913 - Task Completed : 0300 `` ATW0 `` Task Description :
A98: 217068263 | B98: REJ_RW | C98: Rejection with a rework order | D98: REC | E98: A330 | F98: 740VU | G98: 2149 | H98: 2026-04-20 | I98: 1 | J98: FIN 3XC | K98: Support 3XC cassé sur le 740 VU | M98: 3XC | P98: =IFERROR(IF(INDEX('Parts to price'!$M$2:$M$92,MATCH(J98,'Parts to price'!$A$2:$A$92,0))="","",INDEX('Parts to price'!$M$2:$M$92,MATCH(J98,'Parts to price'!$A$2:$A$92,0))),"") | Q98: =IF(P98="","",P98*I98) | R98: Support 3XC cassé sur le 740 VU | NonConformity 0001 : Type of nonconformity : Electrical Assembly Installation * Suite à la NC 217046251 merci de remplacer le support 3XC cassé sur le 740VU. * Voir standard doc * Text Description : Besoin généré sur S03 1029285423 - TEL~ #TEL~ Task Completed : 0400 `` DO00 `` Task Description : Voir OF 1029347652 , imprimé au C04. - TEL~ #TEL~ Task Completed : 0600 `` DO00 `` Task Description : nc ok - TEL~ #TEL~ Task Completed : 0800 `` DO00 `` Task Description : Travail contrôlé par #UID~ - TEL~ #TEL~ Task Completed : 0900 `` DO00 `` Task Description :
A99: 217944228 | B99: REJ_RW | C99: Rejection with a rework order | D99: SERIE | E99: A330 | F99: PTVU | G99: 2165 | H99: 2026-07-24 | I99: 1 | J99: FIN 48LE | K99: RETOUCHE 48LE HS | M99: 48LE | N99: F9251672100000 | O99: ELEC ASSY 275VU | P99: =IFERROR(IF(INDEX('Parts to price'!$M$2:$M$92,MATCH(J99,'Parts to price'!$A$2:$A$92,0))="","",INDEX('Parts to price'!$M$2:$M$92,MATCH(J99,'Parts to price'!$A$2:$A$92,0))),"") | Q99: =IF(P99="","",P99*I99) | R99: RETOUCHE 48LE HS | NonConformity 0001 : Type of nonconformity : Short-cut * DEF 1-Q11 : 48LE DEFAUT DE RESISTANCE. VEUILLEZ CHANGER L'EQUIPEMENT 48LE. Text Description : - TEL~ #TEL~ Task Completed : 0151 `` DO00 `` Task Description : NC prise en compte par OF 1030535434. - Task Completed : 0200 `` ATW0 `` Task Description : remis en conformité
A100: 216150332 | B100: REJ_RW | C100: Rejection with a rework order | D100: SERIE | E100: A330 | F100: PTVU | G100: 2145 | H100: 2026-01-16 | I100: 1 | J100: FIN 671HK | K100: Retouche Test 225VU MSN 02145. | M100: 671HK | N100: F9251649400000 | O100: ELEC ASSY 225VU | P100: =IFERROR(IF(INDEX('Parts to price'!$M$2:$M$92,MATCH(J100,'Parts to price'!$A$2:$A$92,0))="","",INDEX('Parts to price'!$M$2:$M$92,MATCH(J100,'Parts to price'!$A$2:$A$92,0))),"") | Q100: =IF(P100="","",P100*I100) | R100: Retouche Test 225VU MSN 02145. | NonConformity 0001 : Type of nonconformity : Electrical Assembly Installation * Def 1-Q11 : Temp Selector 671HK Hors Tolérance en butée droite , mesure mini demandée : 961 ohm mini , relevée : 1,08K ohm. merci de remplacer cet équipement. Text Description : TEL~ #TEL~ Pièce servi le 09.02 mise a dispo pr la prod - Task Completed : 0200 `` DO00 `` Task Description : NC traité par le ST via SO3 1028321886
...

Sheet Not charged to FTO2
A1: NC | B1: Decision | C1: Liability | D1: Phase | E1: Product | F1: Created | G1: Part reference / FIN / name | H1: Part (as named in the NC)
A2: 216366914 | B2: REJ_RW | C2: 0000314592 | D2: SERIE | E2: PTVU | F2: 2026-02-06 | G2: 314 VU STRUCTURE PEINTURE CADRE NC | H2: 314 VU STRUCTURE peinture cadre NC
A3: 216165997 | B3: REJ_RW | C3: FFF1 | D3: REC | E3: 125VU | F3: 2026-01-19 | G3: 6374845400 | H3: ETEC 125VU ENDOMMAGE
A4: 217128024 | B4: REJ_RW | C4: 249637 | D4: SERIE | E4: PTVU | F4: 2026-04-24 | G4: ABS0064-01 | H4: NC TEST DEFAUT CONTINUITE
A5: 216558859 | B5: EXC | C5: 148971 | D5: SERIE | E5: Other | F5: 2026-02-26 | G5: ABS0901R045 | H5: Collier de tuyauterie non serré
A6: 216969942 | B6: REJ | C6: 0000154965 | D6: SERIE | E6: PTVU | F6: 2026-04-09 | G6: ABS0951C3LM073 | H6: Indicateur HS
A7: 216062470 | B7: EXC | C7: SPAHUBC | D7: SERIE | E7: Other | F7: 2026-01-07 | G7: ABS2268C025A | H7: ATT*CKPT*C4/5*G*Manchon abîmé MIP*SD@*
A8: 216312177 | B8: EXC | C8: 147026 | D8: SERIE | E8: 743VU | F8: 2026-02-02 | G8: ASNA2551A01 | H8: MANQUE INSERT ASNA2551A01
A9: 216785207 | B9: EXC | C9: 147026 | D9: SERIE | E9: 743VU | F9: 2026-03-20 | G9: ASNA2551A01 | H9: INSERT ASNA2551A01 NON CONFORME
A10: 216194905 | B10: REJ | C10: 0000146662 | D10: SERIE | E10: MIP A350 | F10: 2026-01-21 | G10: BARRETTES TORDUES | H10: Barrettes tordues
A11: 217755445 | B11: EXC | C11: 180892 | D11: SERIE | E11: Other | F11: 2026-07-03 | G11: COCK*G/D*C06/09*L10*RIVETAGE OHP NC | H11: COCK*G/D*C06/09*L10*Rivetage OHP NC
A12: 217584160 | B12: EXC | C12: 150597 | D12: SERIE | E12: 300VU | F12: 2026-06-17 | G12: CÔTES MEUBLE 300VU HORS TOLÉRENCES | H12: Côtes Meuble 300VU hors tolérences
... A113: 216184552 | B113: EXC | C113: 150597 | D113: SERIE | E113: 300VU | F113: 2026-01-20 | G113: VISSERIE COURTES DANS INSERTS STRUCTURE | H113: Visserie courtes dans inserts structure
